Workbook

Sheet Lease Schedule blank
A2: 1 | B2: Lease Obligation Analysis: *Name here*
A4: 2 | B4: *Property name here* | E4: Current Remaining Obligations:
E5: Total Remaining Obligation: | F5: =IFERROR(_xlfn.XLOOKUP($C$13,$C$75:$C$198,$P$75:$P$198,"",0),INDEX($P$75:$P$198,MATCH($C$13,$C$75:$C$198,0))) -> 0
B6: Lease Drivers | E6: Remaining Base Rent: | F6: =IFERROR(_xlfn.XLOOKUP($C$13,$C$75:$C$198,$Q$75:$Q$198,"",0),INDEX($Q$75:$Q$198,MATCH($C$13,$C$75:$C$198,0))) -> 0
A7: 3 | B7: Rentable SF | E7: Remaining Nets: | F7: =IFERROR(_xlfn.XLOOKUP($C$13,$C$75:$C$198,$R$75:$R$198,"",0),INDEX($R$75:$R$198,MATCH($C$13,$C$75:$C$198,0))) -> 0
A8: 4 | B8: Lease Commencement Date | E8: Remaining Other Charges: | F8: =IFERROR(_xlfn.XLOOKUP($C$13,$C$75:$C$198,$S$75:$S$198,"",0),INDEX($S$75:$S$198,MATCH($C$13,$C$75:$C$198,0))) -> 0
A9: 5 | B9: Rent Commencement Date
A10: 6 | B10: Total Lease Term (Months): | C10: =DATEDIF(C8,C11,"M")+1 -> 1
A11: 7 | B11: Lease Expiration Date | E11: Exit & Renegotiation comparisons
A12: 8 | B12: Effective Date of Analysis: | E12: Discount Rate: | F12: 0.07
A13: 9 | B13: Effective Month #: | C13: =IFERROR(MATCH(C12,A75:A198,1),1) -> 1 | E13: SCENARIO COMPARISON - Renegotiation | F13: Effective Date of Analysis: | G13: =C12 -> 0
B14: Months Remaining: | C14: =MAX(0,C10-C13+1) -> 1 | F14: Base Case | G14: Modest | H14: Material | I14: Significant
B15: Month # of effective date: | C15: =C13 -> 1 | E15: % Discount | F15: 0 | G15: 0.1 | H15: 0.2 | I15: 0.3
B16: Months until next base rent escalation: | C16: =12-MOD(C13-1,12) -> 12 | E16: Monthly Base Rent | F16: =INDEX(E$75:E$198,MATCH($C$13,C$75:C$198,0)) -> 0 | G16: =$F$16*(1-G15) -> 0 | H16: =$F$16*(1-H15) -> 0 | I16: =$F$16*(1-I15) -> 0
E17: Base/$PSF | F17: =IF($C$7=0,0,F16/$C$7) -> 0 | G17: =IF($C$7=0,0,G16/$C$7) -> 0 | H17: =IF($C$7=0,0,H16/$C$7) -> 0 | I17: =IF($C$7=0,0,I16/$C$7) -> 0
B18: Monthly Rent Breakdown: | E18: Additional Rent (CAMs + Nets) | F18: =INDEX(M$75:M$198,MATCH($C$13,C$75:C$198,0)) -> 0 | G18: =F18 -> 0 | H18: =G18 -> 0 | I18: =H18 -> 0
B19: Date: | C19: =C12 -> 0 | E19: Total Occupancy Cost | F19: =F16+F18 -> 0 | G19: =G16+G18 -> 0 | H19: =H16+H18 -> 0 | I19: =I16+I18 -> 0
B20: Month: | C20: =TEXT(C12,"MMMM") -> January | E20: Effective $/PSF | F20: =IF($C$7=0,0,F19/$C$7) -> 0 | G20: =IF($C$7=0,0,G19/$C$7) -> 0 | H20: =IF($C$7=0,0,H19/$C$7) -> 0 | I20: =IF($C$7=0,0,I19/$C$7) -> 0
A21: 10 | B21: Scheduled Base Rent | E21: Lease Obligation (FV) | F21: {=SUMPRODUCT(($C$75:$C$198>=IF($C$13=0,1,$C$13))*N$75:N$198)} -> 0 | G21: {=SUMPRODUCT(($C$75:$C$198>=IF($C$13=0,1,$C$13))*T$75:T$198)} -> 0 | H21: {=SUMPRODUCT(($C$75:$C$198>=IF($C$13=0,1,$C$13))*U$75:U$198)} -> 0 | I21: {=SUMPRODUCT(($C$75:$C$198>=IF($C$13=0,1,$C$13))*V$75:V$198)} -> 0
A22: 11 | B22: Insurance Year 1 Monthly Rate ($) | E22: Gross Savings vs Base ($) | F22: =0 -> 0 | G22: =F21-G21 -> 0 | H22: =F21-H21 -> 0 | I22: =F21-I21 -> 0
A23: 12 | B23: Taxes Year 1 Monthly Rate ($) | E23: (+)Free Rent | G23: =G16*$F$23 -> 0 | H23: =H16*$F$23 -> 0 | I23: =I16*$F$23 -> 0
B24: CAMS Year 1 Monthly Rate ($) | E24: (+)TI | G24: =$F$24*$C$7 -> 0 | H24: =$F$24*$C$7 -> 0 | I24: =$F$24*$C$7 -> 0
B25: Security Year 1 Monthly Rate ($) | E25: Total Savings From Base | F25: - | G25: =SUM(G22:G24) -> 0 | H25: =SUM(H22:H24) -> 0 | I25: =SUM(I22:I24) -> 0
B26: Other Items Year 1 Monthly Rate ($) | E26: NPV | F26: {=SUMPRODUCT(($C$75:$C$198>=IF($C$13=0,1,$C$13))*N$75:N$198/(1+$F$12/12)^($C$75:$C$198-IF($C$13=0,0,$C$13)+1))} -> 0 | G26: {=SUMPRODUCT(($C$75:$C$198>=IF($C$13=0,1,$C$13))*T$75:T$198/(1+$F$12/12)^($C$75:$C$198-IF($C$13=0,0,$C$13)+1))} -> 0 | H26: {=SUMPRODUCT(($C$75:$C$198>=IF($C$13=0,1,$C$13))*U$75:U$198/(1+$F$12/12)^($C$75:$C$198-IF($C$13=0,0,$C$13)+1))} -> 0 | I26: {=SUMPRODUCT(($C$75:$C$198>=IF($C$13=0,1,$C$13))*V$75:V$198/(1+$F$12/12)^($C$75:$C$198-IF($C$13=0,0,$C$13)+1))} -> 0
E27: NPV Savings vs Base | F27: - | G27: =F26-G26 -> 0 | H27: =F26-H26 -> 0 | I27: =F26-I26 -> 0
B28: Escalations: | E28: % Savings vs Base | F28: - | G28: =IFERROR((F26-G26)/F26,0) -> 0 | H28: =IFERROR((F26-H26)/F26,0) -> 0 | I28: =IFERROR((F26-I26)/F26,0) -> 0
B29: Annual Base Rent Escalation Rate (%) | E29: Full-Lease FV (all months, no date filter) | F29: =SUM(N75:N198) -> 0 | G29: =SUM(T75:T198) -> 0 | H29: =SUM(U75:U198) -> 0 | I29: =SUM(V75:V198) -> 0
B30: CAMS Annual Escalation Rate (%) | E30: Cross-check: NNN after discount (orphan) | F30: =F18*(1-F15) -> 0 | G30: =F18*(1-G15) -> 0 | H30: =F18*(1-H15) -> 0 | I30: =F18*(1-I15) -> 0
B31: Insurance Annual Escalation Rate (%)
B32: Taxes Annual Escalation Rate (%) | E32: SCENARIO COMPARISON - exit | F32: Effective Date of Analysis: | G32: =C12 -> 0
B33: Security Annual Escalation Rate (%) | F33: Full Obligation | G33: Mild Discount | H33: Moderate Discount | I33: Material Discount | J33: Significant Discount
B34: Other Items Annual Escalation Rate (%) | E34: % Buyout | F34: 0 | G34: 0.2 | H34: 0.3 | I34: 0.4 | J34: 0.5
E35: Monthly Base Rent | F35: =F16 -> 0 | G35: =F35 -> 0 | H35: =F35 -> 0 | I35: =F35 -> 0 | J35: =F35 -> 0
B36: Abatement: | E36: Base/$PSF | F36: =IF($C$7=0,0,F35/$C$7) -> 0 | G36: =IF($C$7=0,0,G35/$C$7) -> 0 | H36: =IF($C$7=0,0,H35/$C$7) -> 0 | I36: =IF($C$7=0,0,I35/$C$7) -> 0 | J36: =IF($C$7=0,0,J35/$C$7) -> 0
B37: Abatement duration (months) | E37: Additional Rent (NNN) | F37: =F18 -> 0 | G37: =F37 -> 0 | H37: =F37 -> 0 | I37: =F37 -> 0
B38: Abatement start | E38: Total Occupancy Cost | F38: =F35+F37 -> 0 | G38: =G35+G37 -> 0 | H38: =H35+H37 -> 0 | I38: =I35+I37 -> 0
B39: Abatement end | E39: Effective $/PSF | F39: =IF($C$7=0,0,F38/$C$7) -> 0 | G39: =IF($C$7=0,0,G38/$C$7) -> 0 | H39: =IF($C$7=0,0,H38/$C$7) -> 0 | I39: =IF($C$7=0,0,I38/$C$7) -> 0
B40: Abatement % of full rent (dependent, don't change) | C40: =IF(C21=0,0,C41/C21) -> 0 | E40: Remaining Obligation (FV) | F40: =F21 -> 0 | G40: =F40*(1-G34) -> 0 | H40: =F40*(1-H34) -> 0 | I40: =F40*(1-I34) -> 0 | J40: =F40*(1-J34) -> 0
A41: 13 | B41: Abatement amt (dollars) | E41: Gross Savings vs Base ($) | F41: =0 -> 0 | G41: =F40-G40 -> 0 | H41: =F40-H40 -> 0 | I41: =F40-I40 -> 0 | J41: =F40-J40 -> 0
A42: 14 | B42: *Additional abatement later in lease? (If yes, view the lease schedule abatement column and hardcode your values) | C42: No | E42: (+)Free Rent | G42: =F35*$F$42 -> 0 | H42: =F35*$F$42 -> 0 | I42: =F35*$F$42 -> 0
E43: (+)TI | G43: =$F$24*$C$7 -> 0 | H43: =$F$24*$C$7 -> 0 | I43: =$F$24*$C$7 -> 0
A44: 15 | B44: Free Rent | E44: Total Savings From Base | F44: ="-" -> - | G44: =SUM(G41:G43) -> 0 | H44: =SUM(H41:H43) -> 0 | I44: =SUM(I41:I43) -> 0 | J44: =SUM(J41:J43) -> 0
B45: Free Rent duration (months) | E45: NPV | F45: =F26 -> 0 | G45: =F26*(1-G34) -> 0 | H45: =F26*(1-H34) -> 0 | I45: =F26*(1-I34) -> 0 | J45: =F26*(1-J34) -> 0
B46: Free Rent Start | E46: NPV Savings vs Base | F46: - | G46: =F45-G45 -> 0 | H46: =F45-H45 -> 0 | I46: =F45-I45 -> 0 | J46: =F45-J45 -> 0
B47: Free Rent End | E47: % Savings vs Base | F47: - | G47: =IFERROR((F45-G45)/F45,0) -> 0 | H47: =IFERROR((F45-H45)/F45,0) -> 0 | I47: =IFERROR((F45-I45)/F45,0) -> 0 | J47: =IFERROR((F45-J45)/F45,0) -> 0
B48: Free Rent assumption = 100%, if not.. Edit | E48: Full-Lease FV (all months, no date filter) | F48: =SUM(N75:N198) -> 0 | G48: =SUM(T75:T198) -> 0 | H48: =SUM(U75:U198) -> 0 | I48: =SUM(V75:V198) -> 0 | J48: =SUM(AA75:AA198) -> 0
B49: *Additional free rent later in lease? (If yes, view the lease schedule free rent column and harcode your values) | C49: No | E49: Simplified cross-check: Full FV × (1-buyout%) | F49: =F29*(1-F34) -> 0 | G49: =F29*(1-G34) -> 0 | H49: =F29*(1-H34) -> 0 | I49: =F29*(1-I34) -> 0 | J49: =F29*(1-J34) -> 0
A53: 16 | B53: Non Recurring Charges:
B54: One-Time Charge | C54: Amount (USD) | D54: Incurred / Due Date
B55: Security Deposit
B56: TIA — Initial Funding
B57: TIA — Final Funding
B58: Landlord Work Contribution
B59: Moving Allowance
B60: Base Rent Abatement (Months 1–4)
B61: Lease Commission — Tenant's Broker (JLL)
B62: Lease Commission — Landlord's Broker
B63: Parking Stall Deposit (20 stalls)
B64: HVAC Change-Order Charge
B65: After-Hours Access Control Install
B66: Roof Curb / Supplemental Mechanical Work
B67: Letter of Credit (in lieu of cash deposit)
B68: TOTAL | C68: =SUM(C55:C67) -> 0
B73: Existing Lease | T73: Renegotiation and exit
A74: Period Start | B74: Period End | C74: Month # | D74: Year # | E74: Scheduled Base Rent | F74: Base Rent Applied | G74: Abatement | H74: CAMS | I74: Insurance | J74: Taxes | K74: Security | L74: Other Items | M74: Total NNN ① | N74: Total Monthly Obligation ② | O74: Effective $/SF | P74: Obligation Remaining | Q74: Base Rent Remaining | R74: NNN Remaining | S74: OTC Remaining | T74: Renego: Modest (10%) | U74: Renego: Material (20%) | V74: Renego: Significant (30%) | W74: Exit: Full Obligation (0%) | X74: Exit: Mild Discount (20%) | Y74: Exit: Moderate Discount (30%) | Z74: Exit: Material Discount (40%) | AA74: Exit: Significant Discount (50%)
A75: =$C$8 -> 0 | B75: =EDATE($C$8,1)-1 -> 30 | C75: =ROW()-ROW($C$74) -> 1 | D75: =INT((C75-1)/12)+1 -> 1 | E75: =IF(C75>$C$10,0,$C$21*(1+$C$29)^(D75-1)) -> 0 | F75: =IF(C75>$C$10,0,IF(AND($C$38>0,A75>=$C$38,EOMONTH(A75,0)<=$C$39),E75*(1-$C$40),E75)) -> 0 | G75: =IF(C75>$C$10,0,IF(AND($C$38>0,A75>=$C$38,EOMONTH(A75,0)<=$C$39),-E75*$C$40,0)) -> 0 | H75: =IF(C75>$C$10,0,$C$24*(1+$C$30)^(D75-1)) -> 0 | I75: =IF(C75>$C$10,0,$C$22*(1+$C$31)^(D75-1)) -> 0 | J75: =IF(C75>$C$10,0,$C$23*(1+$C$32)^(D75-1)) -> 0 | K75: =IF(C75>$C$10,0,$C$25*(1+$C$33)^(D75-1)) -> 0 | L75: =IF(C75>$C$10,0,$C$26*(1+$C$34)^(D75-1)) -> 0 | M75: =H75+I75+J75+K75+L75 -> 0 | N75: =F75+M75 -> 0 | O75: =IF($C$7=0,0,N75/$C$7) -> 0 | P75: =MAX(SUM(N75:N198)+S75,0) -> 0 | Q75: =SUM(F75:F198) -> 0 | R75: =SUM(M75:M198) -> 0 | S75: =SUMPRODUCT(($C$55:$C$67)*($D$55:$D$67>=$A75)) -> 0 | T75: =IF(C75>$C$10,0,IF(AND($C$38>0,A75>=$C$38,EOMONTH(A75,0)<=$C$39),E75*(1-$C$40)*(1-G$15),E75*(1-G$15)))+M75 -> 0 | U75: =IF(C75>$C$10,0,IF(AND($C$38>0,A75>=$C$38,EOMONTH(A75,0)<=$C$39),E75*(1-$C$40)*(1-H$15),E75*(1-H$15)))+M75 -> 0 | V75: =IF(C75>$C$10,0,IF(AND($C$38>0,A75>=$C$38,EOMONTH(A75,0)<=$C$39),E75*(1-$C$40)*(1-I$15),E75*(1-I$15)))+M75 -> 0 | W75: =IF(C75>$C$10,0,IF(AND($C$38>0,A75>=$C$38,EOMONTH(A75,0)<=$C$39),E75*(1-$C$40)*(1-F$34),E75*(1-F$34)))+M75 -> 0 | X75: =IF(C75>$C$10,0,IF(AND($C$38>0,A75>=$C$38,EOMONTH(A75,0)<=$C$39),E75*(1-$C$40)*(1-G$34),E75*(1-G$34)))+M75 -> 0 | Y75: =IF(C75>$C$10,0,IF(AND($C$38>0,A75>=$C$38,EOMONTH(A75,0)<=$C$39),E75*(1-$C$40)*(1-H$34),E75*(1-H$34)))+M75 -> 0 | Z75: =IF(C75>$C$10,0,IF(AND($C$38>0,A75>=$C$38,EOMONTH(A75,0)<=$C$39),E75*(1-$C$40)*(1-I$34),E75*(1-I$34)))+M75 -> 0 | AA75: =IF(C75>$C$10,0,IF(AND($C$38>0,A75>=$C$38,EOMONTH(A75,0)<=$C$39),E75*(1-$C$40)*(1-J$34),E75*(1-J$34)))+M75 -> 0
A76: =EDATE($C$8,1) -> 31 | B76: =EDATE($C$8,2)-1 -> 59 | C76: =ROW()-ROW($C$74) -> 2 | D76: =INT((C76-1)/12)+1 -> 1 | E76: =IF(C76>$C$10,0,$C$21*(1+$C$29)^(D76-1)) -> 0 | F76: =IF(C76>$C$10,0,IF(AND($C$38>0,A76>=$C$38,EOMONTH(A76,0)<=$C$39),E76*(1-$C$40),E76)) -> 0 | G76: =IF(C76>$C$10,0,IF(AND($C$38>0,A76>=$C$38,EOMONTH(A76,0)<=$C$39),-E76*$C$40,0)) -> 0 | H76: =IF(C76>$C$10,0,$C$24*(1+$C$30)^(D76-1)) -> 0 | I76: =IF(C76>$C$10,0,$C$22*(1+$C$31)^(D76-1)) -> 0 | J76: =IF(C76>$C$10,0,$C$23*(1+$C$32)^(D76-1)) -> 0 | K76: =IF(C76>$C$10,0,$C$25*(1+$C$33)^(D76-1)) -> 0 | L76: =IF(C76>$C$10,0,$C$26*(1+$C$34)^(D76-1)) -> 0 | M76: =H76+I76+J76+K76+L76 -> 0 | N76: =F76+M76 -> 0 | O76: =IF($C$7=0,0,N76/$C$7) -> 0 | P76: =MAX(SUM(N76:N198)+S76,0) -> 0 | Q76: =SUM(F76:F198) -> 0 | R76: =SUM(M76:M198) -> 0 | S76: =SUMPRODUCT(($C$55:$C$67)*($D$55:$D$67>=$A76)) -> 0 | T76: =IF(C76>$C$10,0,IF(AND($C$38>0,A76>=$C$38,EOMONTH(A76,0)<=$C$39),E76*(1-$C$40)*(1-G$15),E76*(1-G$15)))+M76 -> 0 | U76: =IF(C76>$C$10,0,IF(AND($C$38>0,A76>=$C$38,EOMONTH(A76,0)<=$C$39),E76*(1-$C$40)*(1-H$15),E76*(1-H$15)))+M76 -> 0 | V76: =IF(C76>$C$10,0,IF(AND($C$38>0,A76>=$C$38,EOMONTH(A76,0)<=$C$39),E76*(1-$C$40)*(1-I$15),E76*(1-I$15)))+M76 -> 0 | W76: =IF(C76>$C$10,0,IF(AND($C$38>0,A76>=$C$38,EOMONTH(A76,0)<=$C$39),E76*(1-$C$40)*(1-F$34),E76*(1-F$34)))+M76 -> 0 | X76: =IF(C76>$C$10,0,IF(AND($C$38>0,A76>=$C$38,EOMONTH(A76,0)<=$C$39),E76*(1-$C$40)*(1-G$34),E76*(1-G$34)))+M76 -> 0 | Y76: =IF(C76>$C$10,0,IF(AND($C$38>0,A76>=$C$38,EOMONTH(A76,0)<=$C$39),E76*(1-$C$40)*(1-H$34),E76*(1-H$34)))+M76 -> 0 | Z76: =IF(C76>$C$10,0,IF(AND($C$38>0,A76>=$C$38,EOMONTH(A76,0)<=$C$39),E76*(1-$C$40)*(1-I$34),E76*(1-I$34)))+M76 -> 0 | AA76: =IF(C76>$C$10,0,IF(AND($C$38>0,A76>=$C$38,EOMONTH(A76,0)<=$C$39),E76*(1-$C$40)*(1-J$34),E76*(1-J$34)))+M76 -> 0
A77: =EDATE($C$8,2) -> 60 | B77: =EDATE($C$8,3)-1 -> 90 | C77: =ROW()-ROW($C$74) -> 3 | D77: =INT((C77-1)/12)+1 -> 1 | E77: =IF(C77>$C$10,0,$C$21*(1+$C$29)^(D77-1)) -> 0 | F77: =IF(C77>$C$10,0,IF(AND($C$38>0,A77>=$C$38,EOMONTH(A77,0)<=$C$39),E77*(1-$C$40),E77)) -> 0 | G77: =IF(C77>$C$10,0,IF(AND($C$38>0,A77>=$C$38,EOMONTH(A77,0)<=$C$39),-E77*$C$40,0)) -> 0 | H77: =IF(C77>$C$10,0,$C$24*(1+$C$30)^(D77-1)) -> 0 | I77: =IF(C77>$C$10,0,$C$22*(1+$C$31)^(D77-1)) -> 0 | J77: =IF(C77>$C$10,0,$C$23*(1+$C$32)^(D77-1)) -> 0 | K77: =IF(C77>$C$10,0,$C$25*(1+$C$33)^(D77-1)) -> 0 | L77: =IF(C77>$C$10,0,$C$26*(1+$C$34)^(D77-1)) -> 0 | M77: =H77+I77+J77+K77+L77 -> 0 | N77: =F77+M77 -> 0 | O77: =IF($C$7=0,0,N77/$C$7) -> 0 | P77: =MAX(SUM(N77:N198)+S77,0) -> 0 | Q77: =SUM(F77:F198) -> 0 | R77: =SUM(M77:M198) -> 0 | S77: =SUMPRODUCT(($C$55:$C$67)*($D$55:$D$67>=$A77)) -> 0 | T77: =IF(C77>$C$10,0,IF(AND($C$38>0,A77>=$C$38,EOMONTH(A77,0)<=$C$39),E77*(1-$C$40)*(1-G$15),E77*(1-G$15)))+M77 -> 0 | U77: =IF(C77>$C$10,0,IF(AND($C$38>0,A77>=$C$38,EOMONTH(A77,0)<=$C$39),E77*(1-$C$40)*(1-H$15),E77*(1-H$15)))+M77 -> 0 | V77: =IF(C77>$C$10,0,IF(AND($C$38>0,A77>=$C$38,EOMONTH(A77,0)<=$C$39),E77*(1-$C$40)*(1-I$15),E77*(1-I$15)))+M77 -> 0 | W77: =IF(C77>$C$10,0,IF(AND($C$38>0,A77>=$C$38,EOMONTH(A77,0)<=$C$39),E77*(1-$C$40)*(1-F$34),E77*(1-F$34)))+M77 -> 0 | X77: =IF(C77>$C$10,0,IF(AND($C$38>0,A77>=$C$38,EOMONTH(A77,0)<=$C$39),E77*(1-$C$40)*(1-G$34),E77*(1-G$34)))+M77 -> 0 | Y77: =IF(C77>$C$10,0,IF(AND($C$38>0,A77>=$C$38,EOMONTH(A77,0)<=$C$39),E77*(1-$C$40)*(1-H$34),E77*(1-H$34)))+M77 -> 0 | Z77: =IF(C77>$C$10,0,IF(AND($C$38>0,A77>=$C$38,EOMONTH(A77,0)<=$C$39),E77*(1-$C$40)*(1-I$34),E77*(1-I$34)))+M77 -> 0 | AA77: =IF(C77>$C$10,0,IF(AND($C$38>0,A77>=$C$38,EOMONTH(A77,0)<=$C$39),E77*(1-$C$40)*(1-J$34),E77*(1-J$34)))+M77 -> 0
A78: =EDATE($C$8,3) -> 91 | B78: =EDATE($C$8,4)-1 -> 120 | C78: =ROW()-ROW($C$74) -> 4 | D78: =INT((C78-1)/12)+1 -> 1 | E78: =IF(C78>$C$10,0,$C$21*(1+$C$29)^(D78-1)) -> 0 | F78: =IF(C78>$C$10,0,IF(AND($C$38>0,A78>=$C$38,EOMONTH(A78,0)<=$C$39),E78*(1-$C$40),E78)) -> 0 | G78: =IF(C78>$C$10,0,IF(AND($C$38>0,A78>=$C$38,EOMONTH(A78,0)<=$C$39),-E78*$C$40,0)) -> 0 | H78: =IF(C78>$C$10,0,$C$24*(1+$C$30)^(D78-1)) -> 0 | I78: =IF(C78>$C$10,0,$C$22*(1+$C$31)^(D78-1)) -> 0 | J78: =IF(C78>$C$10,0,$C$23*(1+$C$32)^(D78-1)) -> 0 | K78: =IF(C78>$C$10,0,$C$25*(1+$C$33)^(D78-1)) -> 0 | L78: =IF(C78>$C$10,0,$C$26*(1+$C$34)^(D78-1)) -> 0 | M78: =H78+I78+J78+K78+L78 -> 0 | N78: =F78+M78 -> 0 | O78: =IF($C$7=0,0,N78/$C$7) -> 0 | P78: =MAX(SUM(N78:N198)+S78,0) -> 0 | Q78: =SUM(F78:F198) -> 0 | R78: =SUM(M78:M198) -> 0 | S78: =SUMPRODUCT(($C$55:$C$67)*($D$55:$D$67>=$A78)) -> 0 | T78: =IF(C78>$C$10,0,IF(AND($C$38>0,A78>=$C$38,EOMONTH(A78,0)<=$C$39),E78*(1-$C$40)*(1-G$15),E78*(1-G$15)))+M78 -> 0 | U78: =IF(C78>$C$10,0,IF(AND($C$38>0,A78>=$C$38,EOMONTH(A78,0)<=$C$39),E78*(1-$C$40)*(1-H$15),E78*(1-H$15)))+M78 -> 0 | V78: =IF(C78>$C$10,0,IF(AND($C$38>0,A78>=$C$38,EOMONTH(A78,0)<=$C$39),E78*(1-$C$40)*(1-I$15),E78*(1-I$15)))+M78 -> 0 | W78: =IF(C78>$C$10,0,IF(AND($C$38>0,A78>=$C$38,EOMONTH(A78,0)<=$C$39),E78*(1-$C$40)*(1-F$34),E78*(1-F$34)))+M78 -> 0 | X78: =IF(C78>$C$10,0,IF(AND($C$38>0,A78>=$C$38,EOMONTH(A78,0)<=$C$39),E78*(1-$C$40)*(1-G$34),E78*(1-G$34)))+M78 -> 0 | Y78: =IF(C78>$C$10,0,IF(AND($C$38>0,A78>=$C$38,EOMONTH(A78,0)<=$C$39),E78*(1-$C$40)*(1-H$34),E78*(1-H$34)))+M78 -> 0 | Z78: =IF(C78>$C$10,0,IF(AND($C$38>0,A78>=$C$38,EOMONTH(A78,0)<=$C$39),E78*(1-$C$40)*(1-I$34),E78*(1-I$34)))+M78 -> 0 | AA78: =IF(C78>$C$10,0,IF(AND($C$38>0,A78>=$C$38,EOMONTH(A78,0)<=$C$39),E78*(1-$C$40)*(1-J$34),E78*(1-J$34)))+M78 -> 0
A79: =EDATE($C$8,4) -> 121 | B79: =EDATE($C$8,5)-1 -> 151 | C79: =ROW()-ROW($C$74) -> 5 | D79: =INT((C79-1)/12)+1 -> 1 | E79: =IF(C79>$C$10,0,$C$21*(1+$C$29)^(D79-1)) -> 0 | F79: =IF(C79>$C$10,0,IF(AND($C$38>0,A79>=$C$38,EOMONTH(A79,0)<=$C$39),E79*(1-$C$40),E79)) -> 0 | G79: =IF(C79>$C$10,0,IF(AND($C$38>0,A79>=$C$38,EOMONTH(A79,0)<=$C$39),-E79*$C$40,0)) -> 0 | H79: =IF(C79>$C$10,0,$C$24*(1+$C$30)^(D79-1)) -> 0 | I79: =IF(C79>$C$10,0,$C$22*(1+$C$31)^(D79-1)) -> 0 | J79: =IF(C79>$C$10,0,$C$23*(1+$C$32)^(D79-1)) -> 0 | K79: =IF(C79>$C$10,0,$C$25*(1+$C$33)^(D79-1)) -> 0 | L79: =IF(C79>$C$10,0,$C$26*(1+$C$34)^(D79-1)) -> 0 | M79: =H79+I79+J79+K79+L79 -> 0 | N79: =F79+M79 -> 0 | O79: =IF($C$7=0,0,N79/$C$7) -> 0 | P79: =MAX(SUM(N79:N198)+S79,0) -> 0 | Q79: =SUM(F79:F198) -> 0 | R79: =SUM(M79:M198) -> 0 | S79: =SUMPRODUCT(($C$55:$C$67)*($D$55:$D$67>=$A79)) -> 0 | T79: =IF(C79>$C$10,0,IF(AND($C$38>0,A79>=$C$38,EOMONTH(A79,0)<=$C$39),E79*(1-$C$40)*(1-G$15),E79*(1-G$15)))+M79 -> 0 | U79: =IF(C79>$C$10,0,IF(AND($C$38>0,A79>=$C$38,EOMONTH(A79,0)<=$C$39),E79*(1-$C$40)*(1-H$15),E79*(1-H$15)))+M79 -> 0 | V79: =IF(C79>$C$10,0,IF(AND($C$38>0,A79>=$C$38,EOMONTH(A79,0)<=$C$39),E79*(1-$C$40)*(1-I$15),E79*(1-I$15)))+M79 -> 0 | W79: =IF(C79>$C$10,0,IF(AND($C$38>0,A79>=$C$38,EOMONTH(A79,0)<=$C$39),E79*(1-$C$40)*(1-F$34),E79*(1-F$34)))+M79 -> 0 | X79: =IF(C79>$C$10,0,IF(AND($C$38>0,A79>=$C$38,EOMONTH(A79,0)<=$C$39),E79*(1-$C$40)*(1-G$34),E79*(1-G$34)))+M79 -> 0 | Y79: =IF(C79>$C$10,0,IF(AND($C$38>0,A79>=$C$38,EOMONTH(A79,0)<=$C$39),E79*(1-$C$40)*(1-H$34),E79*(1-H$34)))+M79 -> 0 | Z79: =IF(C79>$C$10,0,IF(AND($C$38>0,A79>=$C$38,EOMONTH(A79,0)<=$C$39),E79*(1-$C$40)*(1-I$34),E79*(1-I$34)))+M79 -> 0 | AA79: =IF(C79>$C$10,0,IF(AND($C$38>0,A79>=$C$38,EOMONTH(A79,0)<=$C$39),E79*(1-$C$40)*(1-J$34),E79*(1-J$34)))+M79 -> 0
A80: =EDATE($C$8,5) -> 152 | B80: =EDATE($C$8,6)-1 -> 181 | C80: =ROW()-ROW($C$74) -> 6 | D80: =INT((C80-1)/12)+1 -> 1 | E80: =IF(C80>$C$10,0,$C$21*(1+$C$29)^(D80-1)) -> 0 | F80: =IF(C80>$C$10,0,IF(AND($C$38>0,A80>=$C$38,EOMONTH(A80,0)<=$C$39),E80*(1-$C$40),E80)) -> 0 | G80: =IF(C80>$C$10,0,IF(AND($C$38>0,A80>=$C$38,EOMONTH(A80,0)<=$C$39),-E80*$C$40,0)) -> 0 | H80: =IF(C80>$C$10,0,$C$24*(1+$C$30)^(D80-1)) -> 0 | I80: =IF(C80>$C$10,0,$C$22*(1+$C$31)^(D80-1)) -> 0 | J80: =IF(C80>$C$10,0,$C$23*(1+$C$32)^(D80-1)) -> 0 | K80: =IF(C80>$C$10,0,$C$25*(1+$C$33)^(D80-1)) -> 0 | L80: =IF(C80>$C$10,0,$C$26*(1+$C$34)^(D80-1)) -> 0 | M80: =H80+I80+J80+K80+L80 -> 0 | N80: =F80+M80 -> 0 | O80: =IF($C$7=0,0,N80/$C$7) -> 0 | P80: =MAX(SUM(N80:N198)+S80,0) -> 0 | Q80: =SUM(F80:F198) -> 0 | R80: =SUM(M80:M198) -> 0 | S80: =SUMPRODUCT(($C$55:$C$67)*($D$55:$D$67>=$A80)) -> 0 | T80: =IF(C80>$C$10,0,IF(AND($C$38>0,A80>=$C$38,EOMONTH(A80,0)<=$C$39),E80*(1-$C$40)*(1-G$15),E80*(1-G$15)))+M80 -> 0 | U80: =IF(C80>$C$10,0,IF(AND($C$38>0,A80>=$C$38,EOMONTH(A80,0)<=$C$39),E80*(1-$C$40)*(1-H$15),E80*(1-H$15)))+M80 -> 0 | V80: =IF(C80>$C$10,0,IF(AND($C$38>0,A80>=$C$38,EOMONTH(A80,0)<=$C$39),E80*(1-$C$40)*(1-I$15),E80*(1-I$15)))+M80 -> 0 | W80: =IF(C80>$C$10,0,IF(AND($C$38>0,A80>=$C$38,EOMONTH(A80,0)<=$C$39),E80*(1-$C$40)*(1-F$34),E80*(1-F$34)))+M80 -> 0 | X80: =IF(C80>$C$10,0,IF(AND($C$38>0,A80>=$C$38,EOMONTH(A80,0)<=$C$39),E80*(1-$C$40)*(1-G$34),E80*(1-G$34)))+M80 -> 0 | Y80: =IF(C80>$C$10,0,IF(AND($C$38>0,A80>=$C$38,EOMONTH(A80,0)<=$C$39),E80*(1-$C$40)*(1-H$34),E80*(1-H$34)))+M80 -> 0 | Z80: =IF(C80>$C$10,0,IF(AND($C$38>0,A80>=$C$38,EOMONTH(A80,0)<=$C$39),E80*(1-$C$40)*(1-I$34),E80*(1-I$34)))+M80 -> 0 | AA80: =IF(C80>$C$10,0,IF(AND($C$38>0,A80>=$C$38,EOMONTH(A80,0)<=$C$39),E80*(1-$C$40)*(1-J$34),E80*(1-J$34)))+M80 -> 0
A81: =EDATE($C$8,6) -> 182 | B81: =EDATE($C$8,7)-1 -> 212 | C81: =ROW()-ROW($C$74) -> 7 | D81: =INT((C81-1)/12)+1 -> 1 | E81: =IF(C81>$C$10,0,$C$21*(1+$C$29)^(D81-1)) -> 0 | F81: =IF(C81>$C$10,0,IF(AND($C$38>0,A81>=$C$38,EOMONTH(A81,0)<=$C$39),E81*(1-$C$40),E81)) -> 0 | G81: =IF(C81>$C$10,0,IF(AND($C$38>0,A81>=$C$38,EOMONTH(A81,0)<=$C$39),-E81*$C$40,0)) -> 0 | H81: =IF(C81>$C$10,0,$C$24*(1+$C$30)^(D81-1)) -> 0 | I81: =IF(C81>$C$10,0,$C$22*(1+$C$31)^(D81-1)) -> 0 | J81: =IF(C81>$C$10,0,$C$23*(1+$C$32)^(D81-1)) -> 0 | K81: =IF(C81>$C$10,0,$C$25*(1+$C$33)^(D81-1)) -> 0 | L81: =IF(C81>$C$10,0,$C$26*(1+$C$34)^(D81-1)) -> 0 | M81: =H81+I81+J81+K81+L81 -> 0 | N81: =F81+M81 -> 0 | O81: =IF($C$7=0,0,N81/$C$7) -> 0 | P81: =MAX(SUM(N81:N198)+S81,0) -> 0 | Q81: =SUM(F81:F198) -> 0 | R81: =SUM(M81:M198) -> 0 | S81: =SUMPRODUCT(($C$55:$C$67)*($D$55:$D$67>=$A81)) -> 0 | T81: =IF(C81>$C$10,0,IF(AND($C$38>0,A81>=$C$38,EOMONTH(A81,0)<=$C$39),E81*(1-$C$40)*(1-G$15),E81*(1-G$15)))+M81 -> 0 | U81: =IF(C81>$C$10,0,IF(AND($C$38>0,A81>=$C$38,EOMONTH(A81,0)<=$C$39),E81*(1-$C$40)*(1-H$15),E81*(1-H$15)))+M81 -> 0 | V81: =IF(C81>$C$10,0,IF(AND($C$38>0,A81>=$C$38,EOMONTH(A81,0)<=$C$39),E81*(1-$C$40)*(1-I$15),E81*(1-I$15)))+M81 -> 0 | W81: =IF(C81>$C$10,0,IF(AND($C$38>0,A81>=$C$38,EOMONTH(A81,0)<=$C$39),E81*(1-$C$40)*(1-F$34),E81*(1-F$34)))+M81 -> 0 | X81: =IF(C81>$C$10,0,IF(AND($C$38>0,A81>=$C$38,EOMONTH(A81,0)<=$C$39),E81*(1-$C$40)*(1-G$34),E81*(1-G$34)))+M81 -> 0 | Y81: =IF(C81>$C$10,0,IF(AND($C$38>0,A81>=$C$38,EOMONTH(A81,0)<=$C$39),E81*(1-$C$40)*(1-H$34),E81*(1-H$34)))+M81 -> 0 | Z81: =IF(C81>$C$10,0,IF(AND($C$38>0,A81>=$C$38,EOMONTH(A81,0)<=$C$39),E81*(1-$C$40)*(1-I$34),E81*(1-I$34)))+M81 -> 0 | AA81: =IF(C81>$C$10,0,IF(AND($C$38>0,A81>=$C$38,EOMONTH(A81,0)<=$C$39),E81*(1-$C$40)*(1-J$34),E81*(1-J$34)))+M81 -> 0
A82: =EDATE($C$8,7) -> 213 | B82: =EDATE($C$8,8)-1 -> 243 | C82: =ROW()-ROW($C$74) -> 8 | D82: =INT((C82-1)/12)+1 -> 1 | E82: =IF(C82>$C$10,0,$C$21*(1+$C$29)^(D82-1)) -> 0 | F82: =IF(C82>$C$10,0,IF(AND($C$38>0,A82>=$C$38,EOMONTH(A82,0)<=$C$39),E82*(1-$C$40),E82)) -> 0 | G82: =IF(C82>$C$10,0,IF(AND($C$38>0,A82>=$C$38,EOMONTH(A82,0)<=$C$39),-E82*$C$40,0)) -> 0 | H82: =IF(C82>$C$10,0,$C$24*(1+$C$30)^(D82-1)) -> 0 | I82: =IF(C82>$C$10,0,$C$22*(1+$C$31)^(D82-1)) -> 0 | J82: =IF(C82>$C$10,0,$C$23*(1+$C$32)^(D82-1)) -> 0 | K82: =IF(C82>$C$10,0,$C$25*(1+$C$33)^(D82-1)) -> 0 | L82: =IF(C82>$C$10,0,$C$26*(1+$C$34)^(D82-1)) -> 0 | M82: =H82+I82+J82+K82+L82 -> 0 | N82: =F82+M82 -> 0 | O82: =IF($C$7=0,0,N82/$C$7) -> 0 | P82: =MAX(SUM(N82:N198)+S82,0) -> 0 | Q82: =SUM(F82:F198) -> 0 | R82: =SUM(M82:M198) -> 0 | S82: =SUMPRODUCT(($C$55:$C$67)*($D$55:$D$67>=$A82)) -> 0 | T82: =IF(C82>$C$10,0,IF(AND($C$38>0,A82>=$C$38,EOMONTH(A82,0)<=$C$39),E82*(1-$C$40)*(1-G$15),E82*(1-G$15)))+M82 -> 0 | U82: =IF(C82>$C$10,0,IF(AND($C$38>0,A82>=$C$38,EOMONTH(A82,0)<=$C$39),E82*(1-$C$40)*(1-H$15),E82*(1-H$15)))+M82 -> 0 | V82: =IF(C82>$C$10,0,IF(AND($C$38>0,A82>=$C$38,EOMONTH(A82,0)<=$C$39),E82*(1-$C$40)*(1-I$15),E82*(1-I$15)))+M82 -> 0 | W82: =IF(C82>$C$10,0,IF(AND($C$38>0,A82>=$C$38,EOMONTH(A82,0)<=$C$39),E82*(1-$C$40)*(1-F$34),E82*(1-F$34)))+M82 -> 0 | X82: =IF(C82>$C$10,0,IF(AND($C$38>0,A82>=$C$38,EOMONTH(A82,0)<=$C$39),E82*(1-$C$40)*(1-G$34),E82*(1-G$34)))+M82 -> 0 | Y82: =IF(C82>$C$10,0,IF(AND($C$38>0,A82>=$C$38,EOMONTH(A82,0)<=$C$39),E82*(1-$C$40)*(1-H$34),E82*(1-H$34)))+M82 -> 0 | Z82: =IF(C82>$C$10,0,IF(AND($C$38>0,A82>=$C$38,EOMONTH(A82,0)<=$C$39),E82*(1-$C$40)*(1-I$34),E82*(1-I$34)))+M82 -> 0 | AA82: =IF(C82>$C$10,0,IF(AND($C$38>0,A82>=$C$38,EOMONTH(A82,0)<=$C$39),E82*(1-$C$40)*(1-J$34),E82*(1-J$34)))+M82 -> 0
A83: =EDATE($C$8,8) -> 244 | B83: =EDATE($C$8,9)-1 -> 273 | C83: =ROW()-ROW($C$74) -> 9 | D83: =INT((C83-1)/12)+1 -> 1 | E83: =IF(C83>$C$10,0,$C$21*(1+$C$29)^(D83-1)) -> 0 | F83: =IF(C83>$C$10,0,IF(AND($C$38>0,A83>=$C$38,EOMONTH(A83,0)<=$C$39),E83*(1-$C$40),E83)) -> 0 | G83: =IF(C83>$C$10,0,IF(AND($C$38>0,A83>=$C$38,EOMONTH(A83,0)<=$C$39),-E83*$C$40,0)) -> 0 | H83: =IF(C83>$C$10,0,$C$24*(1+$C$30)^(D83-1)) -> 0 | I83: =IF(C83>$C$10,0,$C$22*(1+$C$31)^(D83-1)) -> 0 | J83: =IF(C83>$C$10,0,$C$23*(1+$C$32)^(D83-1)) -> 0 | K83: =IF(C83>$C$10,0,$C$25*(1+$C$33)^(D83-1)) -> 0 | L83: =IF(C83>$C$10,0,$C$26*(1+$C$34)^(D83-1)) -> 0 | M83: =H83+I83+J83+K83+L83 -> 0 | N83: =F83+M83 -> 0 | O83: =IF($C$7=0,0,N83/$C$7) -> 0 | P83: =MAX(SUM(N83:N198)+S83,0) -> 0 | Q83: =SUM(F83:F198) -> 0 | R83: =SUM(M83:M198) -> 0 | S83: =SUMPRODUCT(($C$55:$C$67)*($D$55:$D$67>=$A83)) -> 0 | T83: =IF(C83>$C$10,0,IF(AND($C$38>0,A83>=$C$38,EOMONTH(A83,0)<=$C$39),E83*(1-$C$40)*(1-G$15),E83*(1-G$15)))+M83 -> 0 | U83: =IF(C83>$C$10,0,IF(AND($C$38>0,A83>=$C$38,EOMONTH(A83,0)<=$C$39),E83*(1-$C$40)*(1-H$15),E83*(1-H$15)))+M83 -> 0 | V83: =IF(C83>$C$10,0,IF(AND($C$38>0,A83>=$C$38,EOMONTH(A83,0)<=$C$39),E83*(1-$C$40)*(1-I$15),E83*(1-I$15)))+M83 -> 0 | W83: =IF(C83>$C$10,0,IF(AND($C$38>0,A83>=$C$38,EOMONTH(A83,0)<=$C$39),E83*(1-$C$40)*(1-F$34),E83*(1-F$34)))+M83 -> 0 | X83: =IF(C83>$C$10,0,IF(AND($C$38>0,A83>=$C$38,EOMONTH(A83,0)<=$C$39),E83*(1-$C$40)*(1-G$34),E83*(1-G$34)))+M83 -> 0 | Y83: =IF(C83>$C$10,0,IF(AND($C$38>0,A83>=$C$38,EOMONTH(A83,0)<=$C$39),E83*(1-$C$40)*(1-H$34),E83*(1-H$34)))+M83 -> 0 | Z83: =IF(C83>$C$10,0,IF(AND($C$38>0,A83>=$C$38,EOMONTH(A83,0)<=$C$39),E83*(1-$C$40)*(1-I$34),E83*(1-I$34)))+M83 -> 0 | AA83: =IF(C83>$C$10,0,IF(AND($C$38>0,A83>=$C$38,EOMONTH(A83,0)<=$C$39),E83*(1-$C$40)*(1-J$34),E83*(1-J$34)))+M83 -> 0
A84: =EDATE($C$8,9) -> 274 | B84: =EDATE($C$8,10)-1 -> 304 | C84: =ROW()-ROW($C$74) -> 10 | D84: =INT((C84-1)/12)+1 -> 1 | E84: =IF(C84>$C$10,0,$C$21*(1+$C$29)^(D84-1)) -> 0 | F84: =IF(C84>$C$10,0,IF(AND($C$38>0,A84>=$C$38,EOMONTH(A84,0)<=$C$39),E84*(1-$C$40),E84)) -> 0 | G84: =IF(C84>$C$10,0,IF(AND($C$38>0,A84>=$C$38,EOMONTH(A84,0)<=$C$39),-E84*$C$40,0)) -> 0 | H84: =IF(C84>$C$10,0,$C$24*(1+$C$30)^(D84-1)) -> 0 | I84: =IF(C84>$C$10,0,$C$22*(1+$C$31)^(D84-1)) -> 0 | J84: =IF(C84>$C$10,0,$C$23*(1+$C$32)^(D84-1)) -> 0 | K84: =IF(C84>$C$10,0,$C$25*(1+$C$33)^(D84-1)) -> 0 | L84: =IF(C84>$C$10,0,$C$26*(1+$C$34)^(D84-1)) -> 0 | M84: =H84+I84+J84+K84+L84 -> 0 | N84: =F84+M84 -> 0 | O84: =IF($C$7=0,0,N84/$C$7) -> 0 | P84: =MAX(SUM(N84:N198)+S84,0) -> 0 | Q84: =SUM(F84:F198) -> 0 | R84: =SUM(M84:M198) -> 0 | S84: =SUMPRODUCT(($C$55:$C$67)*($D$55:$D$67>=$A84)) -> 0 | T84: =IF(C84>$C$10,0,IF(AND($C$38>0,A84>=$C$38,EOMONTH(A84,0)<=$C$39),E84*(1-$C$40)*(1-G$15),E84*(1-G$15)))+M84 -> 0 | U84: =IF(C84>$C$10,0,IF(AND($C$38>0,A84>=$C$38,EOMONTH(A84,0)<=$C$39),E84*(1-$C$40)*(1-H$15),E84*(1-H$15)))+M84 -> 0 | V84: =IF(C84>$C$10,0,IF(AND($C$38>0,A84>=$C$38,EOMONTH(A84,0)<=$C$39),E84*(1-$C$40)*(1-I$15),E84*(1-I$15)))+M84 -> 0 | W84: =IF(C84>$C$10,0,IF(AND($C$38>0,A84>=$C$38,EOMONTH(A84,0)<=$C$39),E84*(1-$C$40)*(1-F$34),E84*(1-F$34)))+M84 -> 0 | X84: =IF(C84>$C$10,0,IF(AND($C$38>0,A84>=$C$38,EOMONTH(A84,0)<=$C$39),E84*(1-$C$40)*(1-G$34),E84*(1-G$34)))+M84 -> 0 | Y84: =IF(C84>$C$10,0,IF(AND($C$38>0,A84>=$C$38,EOMONTH(A84,0)<=$C$39),E84*(1-$C$40)*(1-H$34),E84*(1-H$34)))+M84 -> 0 | Z84: =IF(C84>$C$10,0,IF(AND($C$38>0,A84>=$C$38,EOMONTH(A84,0)<=$C$39),E84*(1-$C$40)*(1-I$34),E84*(1-I$34)))+M84 -> 0 | AA84: =IF(C84>$C$10,0,IF(AND($C$38>0,A84>=$C$38,EOMONTH(A84,0)<=$C$39),E84*(1-$C$40)*(1-J$34),E84*(1-J$34)))+M84 -> 0
A85: =EDATE($C$8,10) -> 305 | B85: =EDATE($C$8,11)-1 -> 334 | C85: =ROW()-ROW($C$74) -> 11 | D85: =INT((C85-1)/12)+1 -> 1 | E85: =IF(C85>$C$10,0,$C$21*(1+$C$29)^(D85-1)) -> 0 | F85: =IF(C85>$C$10,0,IF(AND($C$38>0,A85>=$C$38,EOMONTH(A85,0)<=$C$39),E85*(1-$C$40),E85)) -> 0 | G85: =IF(C85>$C$10,0,IF(AND($C$38>0,A85>=$C$38,EOMONTH(A85,0)<=$C$39),-E85*$C$40,0)) -> 0 | H85: =IF(C85>$C$10,0,$C$24*(1+$C$30)^(D85-1)) -> 0 | I85: =IF(C85>$C$10,0,$C$22*(1+$C$31)^(D85-1)) -> 0 | J85: =IF(C85>$C$10,0,$C$23*(1+$C$32)^(D85-1)) -> 0 | K85: =IF(C85>$C$10,0,$C$25*(1+$C$33)^(D85-1)) -> 0 | L85: =IF(C85>$C$10,0,$C$26*(1+$C$34)^(D85-1)) -> 0 | M85: =H85+I85+J85+K85+L85 -> 0 | N85: =F85+M85 -> 0 | O85: =IF($C$7=0,0,N85/$C$7) -> 0 | P85: =MAX(SUM(N85:N198)+S85,0) -> 0 | Q85: =SUM(F85:F198) -> 0 | R85: =SUM(M85:M198) -> 0 | S85: =SUMPRODUCT(($C$55:$C$67)*($D$55:$D$67>=$A85)) -> 0 | T85: =IF(C85>$C$10,0,IF(AND($C$38>0,A85>=$C$38,EOMONTH(A85,0)<=$C$39),E85*(1-$C$40)*(1-G$15),E85*(1-G$15)))+M85 -> 0 | U85: =IF(C85>$C$10,0,IF(AND($C$38>0,A85>=$C$38,EOMONTH(A85,0)<=$C$39),E85*(1-$C$40)*(1-H$15),E85*(1-H$15)))+M85 -> 0 | V85: =IF(C85>$C$10,0,IF(AND($C$38>0,A85>=$C$38,EOMONTH(A85,0)<=$C$39),E85*(1-$C$40)*(1-I$15),E85*(1-I$15)))+M85 -> 0 | W85: =IF(C85>$C$10,0,IF(AND($C$38>0,A85>=$C$38,EOMONTH(A85,0)<=$C$39),E85*(1-$C$40)*(1-F$34),E85*(1-F$34)))+M85 -> 0 | X85: =IF(C85>$C$10,0,IF(AND($C$38>0,A85>=$C$38,EOMONTH(A85,0)<=$C$39),E85*(1-$C$40)*(1-G$34),E85*(1-G$34)))+M85 -> 0 | Y85: =IF(C85>$C$10,0,IF(AND($C$38>0,A85>=$C$38,EOMONTH(A85,0)<=$C$39),E85*(1-$C$40)*(1-H$34),E85*(1-H$34)))+M85 -> 0 | Z85: =IF(C85>$C$10,0,IF(AND($C$38>0,A85>=$C$38,EOMONTH(A85,0)<=$C$39),E85*(1-$C$40)*(1-I$34),E85*(1-I$34)))+M85 -> 0 | AA85: =IF(C85>$C$10,0,IF(AND($C$38>0,A85>=$C$38,EOMONTH(A85,0)<=$C$39),E85*(1-$C$40)*(1-J$34),E85*(1-J$34)))+M85 -> 0
A86: =EDATE($C$8,11) -> 335 | B86: =EDATE($C$8,12)-1 -> 365 | C86: =ROW()-ROW($C$74) -> 12 | D86: =INT((C86-1)/12)+1 -> 1 | E86: =IF(C86>$C$10,0,$C$21*(1+$C$29)^(D86-1)) -> 0 | F86: =IF(C86>$C$10,0,IF(AND($C$38>0,A86>=$C$38,EOMONTH(A86,0)<=$C$39),E86*(1-$C$40),E86)) -> 0 | G86: =IF(C86>$C$10,0,IF(AND($C$38>0,A86>=$C$38,EOMONTH(A86,0)<=$C$39),-E86*$C$40,0)) -> 0 | H86: =IF(C86>$C$10,0,$C$24*(1+$C$30)^(D86-1)) -> 0 | I86: =IF(C86>$C$10,0,$C$22*(1+$C$31)^(D86-1)) -> 0 | J86: =IF(C86>$C$10,0,$C$23*(1+$C$32)^(D86-1)) -> 0 | K86: =IF(C86>$C$10,0,$C$25*(1+$C$33)^(D86-1)) -> 0 | L86: =IF(C86>$C$10,0,$C$26*(1+$C$34)^(D86-1)) -> 0 | M86: =H86+I86+J86+K86+L86 -> 0 | N86: =F86+M86 -> 0 | O86: =IF($C$7=0,0,N86/$C$7) -> 0 | P86: =MAX(SUM(N86:N198)+S86,0) -> 0 | Q86: =SUM(F86:F198) -> 0 | R86: =SUM(M86:M198) -> 0 | S86: =SUMPRODUCT(($C$55:$C$67)*($D$55:$D$67>=$A86)) -> 0 | T86: =IF(C86>$C$10,0,IF(AND($C$38>0,A86>=$C$38,EOMONTH(A86,0)<=$C$39),E86*(1-$C$40)*(1-G$15),E86*(1-G$15)))+M86 -> 0 | U86: =IF(C86>$C$10,0,IF(AND($C$38>0,A86>=$C$38,EOMONTH(A86,0)<=$C$39),E86*(1-$C$40)*(1-H$15),E86*(1-H$15)))+M86 -> 0 | V86: =IF(C86>$C$10,0,IF(AND($C$38>0,A86>=$C$38,EOMONTH(A86,0)<=$C$39),E86*(1-$C$40)*(1-I$15),E86*(1-I$15)))+M86 -> 0 | W86: =IF(C86>$C$10,0,IF(AND($C$38>0,A86>=$C$38,EOMONTH(A86,0)<=$C$39),E86*(1-$C$40)*(1-F$34),E86*(1-F$34)))+M86 -> 0 | X86: =IF(C86>$C$10,0,IF(AND($C$38>0,A86>=$C$38,EOMONTH(A86,0)<=$C$39),E86*(1-$C$40)*(1-G$34),E86*(1-G$34)))+M86 -> 0 | Y86: =IF(C86>$C$10,0,IF(AND($C$38>0,A86>=$C$38,EOMONTH(A86,0)<=$C$39),E86*(1-$C$40)*(1-H$34),E86*(1-H$34)))+M86 -> 0 | Z86: =IF(C86>$C$10,0,IF(AND($C$38>0,A86>=$C$38,EOMONTH(A86,0)<=$C$39),E86*(1-$C$40)*(1-I$34),E86*(1-I$34)))+M86 -> 0 | AA86: =IF(C86>$C$10,0,IF(AND($C$38>0,A86>=$C$38,EOMONTH(A86,0)<=$C$39),E86*(1-$C$40)*(1-J$34),E86*(1-J$34)))+M86 -> 0
A87: =EDATE($C$8,12) -> 366 | B87: =EDATE($C$8,13)-1 -> 396 | C87: =ROW()-ROW($C$74) -> 13 | D87: =INT((C87-1)/12)+1 -> 2 | E87: =IF(C87>$C$10,0,$C$21*(1+$C$29)^(D87-1)) -> 0 | F87: =IF(C87>$C$10,0,IF(AND($C$38>0,A87>=$C$38,EOMONTH(A87,0)<=$C$39),E87*(1-$C$40),E87)) -> 0 | G87: =IF(C87>$C$10,0,IF(AND($C$38>0,A87>=$C$38,EOMONTH(A87,0)<=$C$39),-E87*$C$40,0)) -> 0 | H87: =IF(C87>$C$10,0,$C$24*(1+$C$30)^(D87-1)) -> 0 | I87: =IF(C87>$C$10,0,$C$22*(1+$C$31)^(D87-1)) -> 0 | J87: =IF(C87>$C$10,0,$C$23*(1+$C$32)^(D87-1)) -> 0 | K87: =IF(C87>$C$10,0,$C$25*(1+$C$33)^(D87-1)) -> 0 | L87: =IF(C87>$C$10,0,$C$26*(1+$C$34)^(D87-1)) -> 0 | M87: =H87+I87+J87+K87+L87 -> 0 | N87: =F87+M87 -> 0 | O87: =IF($C$7=0,0,N87/$C$7) -> 0 | P87: =MAX(SUM(N87:N198)+S87,0) -> 0 | Q87: =SUM(F87:F198) -> 0 | R87: =SUM(M87:M198) -> 0 | S87: =SUMPRODUCT(($C$55:$C$67)*($D$55:$D$67>=$A87)) -> 0 | T87: =IF(C87>$C$10,0,IF(AND($C$38>0,A87>=$C$38,EOMONTH(A87,0)<=$C$39),E87*(1-$C$40)*(1-G$15),E87*(1-G$15)))+M87 -> 0 | U87: =IF(C87>$C$10,0,IF(AND($C$38>0,A87>=$C$38,EOMONTH(A87,0)<=$C$39),E87*(1-$C$40)*(1-H$15),E87*(1-H$15)))+M87 -> 0 | V87: =IF(C87>$C$10,0,IF(AND($C$38>0,A87>=$C$38,EOMONTH(A87,0)<=$C$39),E87*(1-$C$40)*(1-I$15),E87*(1-I$15)))+M87 -> 0 | W87: =IF(C87>$C$10,0,IF(AND($C$38>0,A87>=$C$38,EOMONTH(A87,0)<=$C$39),E87*(1-$C$40)*(1-F$34),E87*(1-F$34)))+M87 -> 0 | X87: =IF(C87>$C$10,0,IF(AND($C$38>0,A87>=$C$38,EOMONTH(A87,0)<=$C$39),E87*(1-$C$40)*(1-G$34),E87*(1-G$34)))+M87 -> 0 | Y87: =IF(C87>$C$10,0,IF(AND($C$38>0,A87>=$C$38,EOMONTH(A87,0)<=$C$39),E87*(1-$C$40)*(1-H$34),E87*(1-H$34)))+M87 -> 0 | Z87: =IF(C87>$C$10,0,IF(AND($C$38>0,A87>=$C$38,EOMONTH(A87,0)<=$C$39),E87*(1-$C$40)*(1-I$34),E87*(1-I$34)))+M87 -> 0 | AA87: =IF(C87>$C$10,0,IF(AND($C$38>0,A87>=$C$38,EOMONTH(A87,0)<=$C$39),E87*(1-$C$40)*(1-J$34),E87*(1-J$34)))+M87 -> 0
A88: =EDATE($C$8,13) -> 397 | B88: =EDATE($C$8,14)-1 -> 424 | C88: =ROW()-ROW($C$74) -> 14 | D88: =INT((C88-1)/12)+1 -> 2 | E88: =IF(C88>$C$10,0,$C$21*(1+$C$29)^(D88-1)) -> 0 | F88: =IF(C88>$C$10,0,IF(AND($C$38>0,A88>=$C$38,EOMONTH(A88,0)<=$C$39),E88*(1-$C$40),E88)) -> 0 | G88: =IF(C88>$C$10,0,IF(AND($C$38>0,A88>=$C$38,EOMONTH(A88,0)<=$C$39),-E88*$C$40,0)) -> 0 | H88: =IF(C88>$C$10,0,$C$24*(1+$C$30)^(D88-1)) -> 0 | I88: =IF(C88>$C$10,0,$C$22*(1+$C$31)^(D88-1)) -> 0 | J88: =IF(C88>$C$10,0,$C$23*(1+$C$32)^(D88-1)) -> 0 | K88: =IF(C88>$C$10,0,$C$25*(1+$C$33)^(D88-1)) -> 0 | L88: =IF(C88>$C$10,0,$C$26*(1+$C$34)^(D88-1)) -> 0 | M88: =H88+I88+J88+K88+L88 -> 0 | N88: =F88+M88 -> 0 | O88: =IF($C$7=0,0,N88/$C$7) -> 0 | P88: =MAX(SUM(N88:N198)+S88,0) -> 0 | Q88: =SUM(F88:F198) -> 0 | R88: =SUM(M88:M198) -> 0 | S88: =SUMPRODUCT(($C$55:$C$67)*($D$55:$D$67>=$A88)) -> 0 | T88: =IF(C88>$C$10,0,IF(AND($C$38>0,A88>=$C$38,EOMONTH(A88,0)<=$C$39),E88*(1-$C$40)*(1-G$15),E88*(1-G$15)))+M88 -> 0 | U88: =IF(C88>$C$10,0,IF(AND($C$38>0,A88>=$C$38,EOMONTH(A88,0)<=$C$39),E88*(1-$C$40)*(1-H$15),E88*(1-H$15)))+M88 -> 0 | V88: =IF(C88>$C$10,0,IF(AND($C$38>0,A88>=$C$38,EOMONTH(A88,0)<=$C$39),E88*(1-$C$40)*(1-I$15),E88*(1-I$15)))+M88 -> 0 | W88: =IF(C88>$C$10,0,IF(AND($C$38>0,A88>=$C$38,EOMONTH(A88,0)<=$C$39),E88*(1-$C$40)*(1-F$34),E88*(1-F$34)))+M88 -> 0 | X88: =IF(C88>$C$10,0,IF(AND($C$38>0,A88>=$C$38,EOMONTH(A88,0)<=$C$39),E88*(1-$C$40)*(1-G$34),E88*(1-G$34)))+M88 -> 0 | Y88: =IF(C88>$C$10,0,IF(AND($C$38>0,A88>=$C$38,EOMONTH(A88,0)<=$C$39),E88*(1-$C$40)*(1-H$34),E88*(1-H$34)))+M88 -> 0 | Z88: =IF(C88>$C$10,0,IF(AND($C$38>0,A88>=$C$38,EOMONTH(A88,0)<=$C$39),E88*(1-$C$40)*(1-I$34),E88*(1-I$34)))+M88 -> 0 | AA88: =IF(C88>$C$10,0,IF(AND($C$38>0,A88>=$C$38,EOMONTH(A88,0)<=$C$39),E88*(1-$C$40)*(1-J$34),E88*(1-J$34)))+M88 -> 0
A89: =EDATE($C$8,14) -> 425 | B89: =EDATE($C$8,15)-1 -> 455 | C89: =ROW()-ROW($C$74) -> 15 | D89: =INT((C89-1)/12)+1 -> 2 | E89: =IF(C89>$C$10,0,$C$21*(1+$C$29)^(D89-1)) -> 0 | F89: =IF(C89>$C$10,0,IF(AND($C$38>0,A89>=$C$38,EOMONTH(A89,0)<=$C$39),E89*(1-$C$40),E89)) -> 0 | G89: =IF(C89>$C$10,0,IF(AND($C$38>0,A89>=$C$38,EOMONTH(A89,0)<=$C$39),-E89*$C$40,0)) -> 0 | H89: =IF(C89>$C$10,0,$C$24*(1+$C$30)^(D89-1)) -> 0 | I89: =IF(C89>$C$10,0,$C$22*(1+$C$31)^(D89-1)) -> 0 | J89: =IF(C89>$C$10,0,$C$23*(1+$C$32)^(D89-1)) -> 0 | K89: =IF(C89>$C$10,0,$C$25*(1+$C$33)^(D89-1)) -> 0 | L89: =IF(C89>$C$10,0,$C$26*(1+$C$34)^(D89-1)) -> 0 | M89: =H89+I89+J89+K89+L89 -> 0 | N89: =F89+M89 -> 0 | O89: =IF($C$7=0,0,N89/$C$7) -> 0 | P89: =MAX(SUM(N89:N198)+S89,0) -> 0 | Q89: =SUM(F89:F198) -> 0 | R89: =SUM(M89:M198) -> 0 | S89: =SUMPRODUCT(($C$55:$C$67)*($D$55:$D$67>=$A89)) -> 0 | T89: =IF(C89>$C$10,0,IF(AND($C$38>0,A89>=$C$38,EOMONTH(A89,0)<=$C$39),E89*(1-$C$40)*(1-G$15),E89*(1-G$15)))+M89 -> 0 | U89: =IF(C89>$C$10,0,IF(AND($C$38>0,A89>=$C$38,EOMONTH(A89,0)<=$C$39),E89*(1-$C$40)*(1-H$15),E89*(1-H$15)))+M89 -> 0 | V89: =IF(C89>$C$10,0,IF(AND($C$38>0,A89>=$C$38,EOMONTH(A89,0)<=$C$39),E89*(1-$C$40)*(1-I$15),E89*(1-I$15)))+M89 -> 0 | W89: =IF(C89>$C$10,0,IF(AND($C$38>0,A89>=$C$38,EOMONTH(A89,0)<=$C$39),E89*(1-$C$40)*(1-F$34),E89*(1-F$34)))+M89 -> 0 | X89: =IF(C89>$C$10,0,IF(AND($C$38>0,A89>=$C$38,EOMONTH(A89,0)<=$C$39),E89*(1-$C$40)*(1-G$34),E89*(1-G$34)))+M89 -> 0 | Y89: =IF(C89>$C$10,0,IF(AND($C$38>0,A89>=$C$38,EOMONTH(A89,0)<=$C$39),E89*(1-$C$40)*(1-H$34),E89*(1-H$34)))+M89 -> 0 | Z89: =IF(C89>$C$10,0,IF(AND($C$38>0,A89>=$C$38,EOMONTH(A89,0)<=$C$39),E89*(1-$C$40)*(1-I$34),E89*(1-I$34)))+M89 -> 0 | AA89: =IF(C89>$C$10,0,IF(AND($C$38>0,A89>=$C$38,EOMONTH(A89,0)<=$C$39),E89*(1-$C$40)*(1-J$34),E89*(1-J$34)))+M89 -> 0
A90: =EDATE($C$8,15) -> 456 | B90: =EDATE($C$8,16)-1 -> 485 | C90: =ROW()-ROW($C$74) -> 16 | D90: =INT((C90-1)/12)+1 -> 2 | E90: =IF(C90>$C$10,0,$C$21*(1+$C$29)^(D90-1)) -> 0 | F90: =IF(C90>$C$10,0,IF(AND($C$38>0,A90>=$C$38,EOMONTH(A90,0)<=$C$39),E90*(1-$C$40),E90)) -> 0 | G90: =IF(C90>$C$10,0,IF(AND($C$38>0,A90>=$C$38,EOMONTH(A90,0)<=$C$39),-E90*$C$40,0)) -> 0 | H90: =IF(C90>$C$10,0,$C$24*(1+$C$30)^(D90-1)) -> 0 | I90: =IF(C90>$C$10,0,$C$22*(1+$C$31)^(D90-1)) -> 0 | J90: =IF(C90>$C$10,0,$C$23*(1+$C$32)^(D90-1)) -> 0 | K90: =IF(C90>$C$10,0,$C$25*(1+$C$33)^(D90-1)) -> 0 | L90: =IF(C90>$C$10,0,$C$26*(1+$C$34)^(D90-1)) -> 0 | M90: =H90+I90+J90+K90+L90 -> 0 | N90: =F90+M90 -> 0 | O90: =IF($C$7=0,0,N90/$C$7) -> 0 | P90: =MAX(SUM(N90:N198)+S90,0) -> 0 | Q90: =SUM(F90:F198) -> 0 | R90: =SUM(M90:M198) -> 0 | S90: =SUMPRODUCT(($C$55:$C$67)*($D$55:$D$67>=$A90)) -> 0 | T90: =IF(C90>$C$10,0,IF(AND($C$38>0,A90>=$C$38,EOMONTH(A90,0)<=$C$39),E90*(1-$C$40)*(1-G$15),E90*(1-G$15)))+M90 -> 0 | U90: =IF(C90>$C$10,0,IF(AND($C$38>0,A90>=$C$38,EOMONTH(A90,0)<=$C$39),E90*(1-$C$40)*(1-H$15),E90*(1-H$15)))+M90 -> 0 | V90: =IF(C90>$C$10,0,IF(AND($C$38>0,A90>=$C$38,EOMONTH(A90,0)<=$C$39),E90*(1-$C$40)*(1-I$15),E90*(1-I$15)))+M90 -> 0 | W90: =IF(C90>$C$10,0,IF(AND($C$38>0,A90>=$C$38,EOMONTH(A90,0)<=$C$39),E90*(1-$C$40)*(1-F$34),E90*(1-F$34)))+M90 -> 0 | X90: =IF(C90>$C$10,0,IF(AND($C$38>0,A90>=$C$38,EOMONTH(A90,0)<=$C$39),E90*(1-$C$40)*(1-G$34),E90*(1-G$34)))+M90 -> 0 | Y90: =IF(C90>$C$10,0,IF(AND($C$38>0,A90>=$C$38,EOMONTH(A90,0)<=$C$39),E90*(1-$C$40)*(1-H$34),E90*(1-H$34)))+M90 -> 0 | Z90: =IF(C90>$C$10,0,IF(AND($C$38>0,A90>=$C$38,EOMONTH(A90,0)<=$C$39),E90*(1-$C$40)*(1-I$34),E90*(1-I$34)))+M90 -> 0 | AA90: =IF(C90>$C$10,0,IF(AND($C$38>0,A90>=$C$38,EOMONTH(A90,0)<=$C$39),E90*(1-$C$40)*(1-J$34),E90*(1-J$34)))+M90 -> 0
A91: =EDATE($C$8,16) -> 486 | B91: =EDATE($C$8,17)-1 -> 516 | C91: =ROW()-ROW($C$74) -> 17 | D91: =INT((C91-1)/12)+1 -> 2 | E91: =IF(C91>$C$10,0,$C$21*(1+$C$29)^(D91-1)) -> 0 | F91: =IF(C91>$C$10,0,IF(AND($C$38>0,A91>=$C$38,EOMONTH(A91,0)<=$C$39),E91*(1-$C$40),E91)) -> 0 | G91: =IF(C91>$C$10,0,IF(AND($C$38>0,A91>=$C$38,EOMONTH(A91,0)<=$C$39),-E91*$C$40,0)) -> 0 | H91: =IF(C91>$C$10,0,$C$24*(1+$C$30)^(D91-1)) -> 0 | I91: =IF(C91>$C$10,0,$C$22*(1+$C$31)^(D91-1)) -> 0 | J91: =IF(C91>$C$10,0,$C$23*(1+$C$32)^(D91-1)) -> 0 | K91: =IF(C91>$C$10,0,$C$25*(1+$C$33)^(D91-1)) -> 0 | L91: =IF(C91>$C$10,0,$C$26*(1+$C$34)^(D91-1)) -> 0 | M91: =H91+I91+J91+K91+L91 -> 0 | N91: =F91+M91 -> 0 | O91: =IF($C$7=0,0,N91/$C$7) -> 0 | P91: =MAX(SUM(N91:N198)+S91,0) -> 0 | Q91: =SUM(F91:F198) -> 0 | R91: =SUM(M91:M198) -> 0 | S91: =SUMPRODUCT(($C$55:$C$67)*($D$55:$D$67>=$A91)) -> 0 | T91: =IF(C91>$C$10,0,IF(AND($C$38>0,A91>=$C$38,EOMONTH(A91,0)<=$C$39),E91*(1-$C$40)*(1-G$15),E91*(1-G$15)))+M91 -> 0 | U91: =IF(C91>$C$10,0,IF(AND($C$38>0,A91>=$C$38,EOMONTH(A91,0)<=$C$39),E91*(1-$C$40)*(1-H$15),E91*(1-H$15)))+M91 -> 0 | V91: =IF(C91>$C$10,0,IF(AND($C$38>0,A91>=$C$38,EOMONTH(A91,0)<=$C$39),E91*(1-$C$40)*(1-I$15),E91*(1-I$15)))+M91 -> 0 | W91: =IF(C91>$C$10,0,IF(AND($C$38>0,A91>=$C$38,EOMONTH(A91,0)<=$C$39),E91*(1-$C$40)*(1-F$34),E91*(1-F$34)))+M91 -> 0 | X91: =IF(C91>$C$10,0,IF(AND($C$38>0,A91>=$C$38,EOMONTH(A91,0)<=$C$39),E91*(1-$C$40)*(1-G$34),E91*(1-G$34)))+M91 -> 0 | Y91: =IF(C91>$C$10,0,IF(AND($C$38>0,A91>=$C$38,EOMONTH(A91,0)<=$C$39),E91*(1-$C$40)*(1-H$34),E91*(1-H$34)))+M91 -> 0 | Z91: =IF(C91>$C$10,0,IF(AND($C$38>0,A91>=$C$38,EOMONTH(A91,0)<=$C$39),E91*(1-$C$40)*(1-I$34),E91*(1-I$34)))+M91 -> 0 | AA91: =IF(C91>$C$10,0,IF(AND($C$38>0,A91>=$C$38,EOMONTH(A91,0)<=$C$39),E91*(1-$C$40)*(1-J$34),E91*(1-J$34)))+M91 -> 0
A92: =EDATE($C$8,17) -> 517 | B92: =EDATE($C$8,18)-1 -> 546 | C92: =ROW()-ROW($C$74) -> 18 | D92: =INT((C92-1)/12)+1 -> 2 | E92: =IF(C92>$C$10,0,$C$21*(1+$C$29)^(D92-1)) -> 0 | F92: =IF(C92>$C$10,0,IF(AND($C$38>0,A92>=$C$38,EOMONTH(A92,0)<=$C$39),E92*(1-$C$40),E92)) -> 0 | G92: =IF(C92>$C$10,0,IF(AND($C$38>0,A92>=$C$38,EOMONTH(A92,0)<=$C$39),-E92*$C$40,0)) -> 0 | H92: =IF(C92>$C$10,0,$C$24*(1+$C$30)^(D92-1)) -> 0 | I92: =IF(C92>$C$10,0,$C$22*(1+$C$31)^(D92-1)) -> 0 | J92: =IF(C92>$C$10,0,$C$23*(1+$C$32)^(D92-1)) -> 0 | K92: =IF(C92>$C$10,0,$C$25*(1+$C$33)^(D92-1)) -> 0 | L92: =IF(C92>$C$10,0,$C$26*(1+$C$34)^(D92-1)) -> 0 | M92: =H92+I92+J92+K92+L92 -> 0 | N92: =F92+M92 -> 0 | O92: =IF($C$7=0,0,N92/$C$7) -> 0 | P92: =MAX(SUM(N92:N198)+S92,0) -> 0 | Q92: =SUM(F92:F198) -> 0 | R92: =SUM(M92:M198) -> 0 | S92: =SUMPRODUCT(($C$55:$C$67)*($D$55:$D$67>=$A92)) -> 0 | T92: =IF(C92>$C$10,0,IF(AND($C$38>0,A92>=$C$38,EOMONTH(A92,0)<=$C$39),E92*(1-$C$40)*(1-G$15),E92*(1-G$15)))+M92 -> 0 | U92: =IF(C92>$C$10,0,IF(AND($C$38>0,A92>=$C$38,EOMONTH(A92,0)<=$C$39),E92*(1-$C$40)*(1-H$15),E92*(1-H$15)))+M92 -> 0 | V92: =IF(C92>$C$10,0,IF(AND($C$38>0,A92>=$C$38,EOMONTH(A92,0)<=$C$39),E92*(1-$C$40)*(1-I$15),E92*(1-I$15)))+M92 -> 0 | W92: =IF(C92>$C$10,0,IF(AND($C$38>0,A92>=$C$38,EOMONTH(A92,0)<=$C$39),E92*(1-$C$40)*(1-F$34),E92*(1-F$34)))+M92 -> 0 | X92: =IF(C92>$C$10,0,IF(AND($C$38>0,A92>=$C$38,EOMONTH(A92,0)<=$C$39),E92*(1-$C$40)*(1-G$34),E92*(1-G$34)))+M92 -> 0 | Y92: =IF(C92>$C$10,0,IF(AND($C$38>0,A92>=$C$38,EOMONTH(A92,0)<=$C$39),E92*(1-$C$40)*(1-H$34),E92*(1-H$34)))+M92 -> 0 | Z92: =IF(C92>$C$10,0,IF(AND($C$38>0,A92>=$C$38,EOMONTH(A92,0)<=$C$39),E92*(1-$C$40)*(1-I$34),E92*(1-I$34)))+M92 -> 0 | AA92: =IF(C92>$C$10,0,IF(AND($C$38>0,A92>=$C$38,EOMONTH(A92,0)<=$C$39),E92*(1-$C$40)*(1-J$34),E92*(1-J$34)))+M92 -> 0
A93: =EDATE($C$8,18) -> 547 | B93: =EDATE($C$8,19)-1 -> 577 | C93: =ROW()-ROW($C$74) -> 19 | D93: =INT((C93-1)/12)+1 -> 2 | E93: =IF(C93>$C$10,0,$C$21*(1+$C$29)^(D93-1)) -> 0 | F93: =IF(C93>$C$10,0,IF(AND($C$38>0,A93>=$C$38,EOMONTH(A93,0)<=$C$39),E93*(1-$C$40),E93)) -> 0 | G93: =IF(C93>$C$10,0,IF(AND($C$38>0,A93>=$C$38,EOMONTH(A93,0)<=$C$39),-E93*$C$40,0)) -> 0 | H93: =IF(C93>$C$10,0,$C$24*(1+$C$30)^(D93-1)) -> 0 | I93: =IF(C93>$C$10,0,$C$22*(1+$C$31)^(D93-1)) -> 0 | J93: =IF(C93>$C$10,0,$C$23*(1+$C$32)^(D93-1)) -> 0 | K93: =IF(C93>$C$10,0,$C$25*(1+$C$33)^(D93-1)) -> 0 | L93: =IF(C93>$C$10,0,$C$26*(1+$C$34)^(D93-1)) -> 0 | M93: =H93+I93+J93+K93+L93 -> 0 | N93: =F93+M93 -> 0 | O93: =IF($C$7=0,0,N93/$C$7) -> 0 | P93: =MAX(SUM(N93:N198)+S93,0) -> 0 | Q93: =SUM(F93:F198) -> 0 | R93: =SUM(M93:M198) -> 0 | S93: =SUMPRODUCT(($C$55:$C$67)*($D$55:$D$67>=$A93)) -> 0 | T93: =IF(C93>$C$10,0,IF(AND($C$38>0,A93>=$C$38,EOMONTH(A93,0)<=$C$39),E93*(1-$C$40)*(1-G$15),E93*(1-G$15)))+M93 -> 0 | U93: =IF(C93>$C$10,0,IF(AND($C$38>0,A93>=$C$38,EOMONTH(A93,0)<=$C$39),E93*(1-$C$40)*(1-H$15),E93*(1-H$15)))+M93 -> 0 | V93: =IF(C93>$C$10,0,IF(AND($C$38>0,A93>=$C$38,EOMONTH(A93,0)<=$C$39),E93*(1-$C$40)*(1-I$15),E93*(1-I$15)))+M93 -> 0 | W93: =IF(C93>$C$10,0,IF(AND($C$38>0,A93>=$C$38,EOMONTH(A93,0)<=$C$39),E93*(1-$C$40)*(1-F$34),E93*(1-F$34)))+M93 -> 0 | X93: =IF(C93>$C$10,0,IF(AND($C$38>0,A93>=$C$38,EOMONTH(A93,0)<=$C$39),E93*(1-$C$40)*(1-G$34),E93*(1-G$34)))+M93 -> 0 | Y93: =IF(C93>$C$10,0,IF(AND($C$38>0,A93>=$C$38,EOMONTH(A93,0)<=$C$39),E93*(1-$C$40)*(1-H$34),E93*(1-H$34)))+M93 -> 0 | Z93: =IF(C93>$C$10,0,IF(AND($C$38>0,A93>=$C$38,EOMONTH(A93,0)<=$C$39),E93*(1-$C$40)*(1-I$34),E93*(1-I$34)))+M93 -> 0 | AA93: =IF(C93>$C$10,0,IF(AND($C$38>0,A93>=$C$38,EOMONTH(A93,0)<=$C$39),E93*(1-$C$40)*(1-J$34),E93*(1-J$34)))+M93 -> 0
A94: =EDATE($C$8,19) -> 578 | B94: =EDATE($C$8,20)-1 -> 608 | C94: =ROW()-ROW($C$74) -> 20 | D94: =INT((C94-1)/12)+1 -> 2 | E94: =IF(C94>$C$10,0,$C$21*(1+$C$29)^(D94-1)) -> 0 | F94: =IF(C94>$C$10,0,IF(AND($C$38>0,A94>=$C$38,EOMONTH(A94,0)<=$C$39),E94*(1-$C$40),E94)) -> 0 | G94: =IF(C94>$C$10,0,IF(AND($C$38>0,A94>=$C$38,EOMONTH(A94,0)<=$C$39),-E94*$C$40,0)) -> 0 | H94: =IF(C94>$C$10,0,$C$24*(1+$C$30)^(D94-1)) -> 0 | I94: =IF(C94>$C$10,0,$C$22*(1+$C$31)^(D94-1)) -> 0 | J94: =IF(C94>$C$10,0,$C$23*(1+$C$32)^(D94-1)) -> 0 | K94: =IF(C94>$C$10,0,$C$25*(1+$C$33)^(D94-1)) -> 0 | L94: =IF(C94>$C$10,0,$C$26*(1+$C$34)^(D94-1)) -> 0 | M94: =H94+I94+J94+K94+L94 -> 0 | N94: =F94+M94 -> 0 | O94: =IF($C$7=0,0,N94/$C$7) -> 0 | P94: =MAX(SUM(N94:N198)+S94,0) -> 0 | Q94: =SUM(F94:F198) -> 0 | R94: =SUM(M94:M198) -> 0 | S94: =SUMPRODUCT(($C$55:$C$67)*($D$55:$D$67>=$A94)) -> 0 | T94: =IF(C94>$C$10,0,IF(AND($C$38>0,A94>=$C$38,EOMONTH(A94,0)<=$C$39),E94*(1-$C$40)*(1-G$15),E94*(1-G$15)))+M94 -> 0 | U94: =IF(C94>$C$10,0,IF(AND($C$38>0,A94>=$C$38,EOMONTH(A94,0)<=$C$39),E94*(1-$C$40)*(1-H$15),E94*(1-H$15)))+M94 -> 0 | V94: =IF(C94>$C$10,0,IF(AND($C$38>0,A94>=$C$38,EOMONTH(A94,0)<=$C$39),E94*(1-$C$40)*(1-I$15),E94*(1-I$15)))+M94 -> 0 | W94: =IF(C94>$C$10,0,IF(AND($C$38>0,A94>=$C$38,EOMONTH(A94,0)<=$C$39),E94*(1-$C$40)*(1-F$34),E94*(1-F$34)))+M94 -> 0 | X94: =IF(C94>$C$10,0,IF(AND($C$38>0,A94>=$C$38,EOMONTH(A94,0)<=$C$39),E94*(1-$C$40)*(1-G$34),E94*(1-G$34)))+M94 -> 0 | Y94: =IF(C94>$C$10,0,IF(AND($C$38>0,A94>=$C$38,EOMONTH(A94,0)<=$C$39),E94*(1-$C$40)*(1-H$34),E94*(1-H$34)))+M94 -> 0 | Z94: =IF(C94>$C$10,0,IF(AND($C$38>0,A94>=$C$38,EOMONTH(A94,0)<=$C$39),E94*(1-$C$40)*(1-I$34),E94*(1-I$34)))+M94 -> 0 | AA94: =IF(C94>$C$10,0,IF(AND($C$38>0,A94>=$C$38,EOMONTH(A94,0)<=$C$39),E94*(1-$C$40)*(1-J$34),E94*(1-J$34)))+M94 -> 0
A95: =EDATE($C$8,20) -> 609 | B95: =EDATE($C$8,21)-1 -> 638 | C95: =ROW()-ROW($C$74) -> 21 | D95: =INT((C95-1)/12)+1 -> 2 | E95: =IF(C95>$C$10,0,$C$21*(1+$C$29)^(D95-1)) -> 0 | F95: =IF(C95>$C$10,0,IF(AND($C$38>0,A95>=$C$38,EOMONTH(A95,0)<=$C$39),E95*(1-$C$40),E95)) -> 0 | G95: =IF(C95>$C$10,0,IF(AND($C$38>0,A95>=$C$38,EOMONTH(A95,0)<=$C$39),-E95*$C$40,0)) -> 0 | H95: =IF(C95>$C$10,0,$C$24*(1+$C$30)^(D95-1)) -> 0 | I95: =IF(C95>$C$10,0,$C$22*(1+$C$31)^(D95-1)) -> 0 | J95: =IF(C95>$C$10,0,$C$23*(1+$C$32)^(D95-1)) -> 0 | K95: =IF(C95>$C$10,0,$C$25*(1+$C$33)^(D95-1)) -> 0 | L95: =IF(C95>$C$10,0,$C$26*(1+$C$34)^(D95-1)) -> 0 | M95: =H95+I95+J95+K95+L95 -> 0 | N95: =F95+M95 -> 0 | O95: =IF($C$7=0,0,N95/$C$7) -> 0 | P95: =MAX(SUM(N95:N198)+S95,0) -> 0 | Q95: =SUM(F95:F198) -> 0 | R95: =SUM(M95:M198) -> 0 | S95: =SUMPRODUCT(($C$55:$C$67)*($D$55:$D$67>=$A95)) -> 0 | T95: =IF(C95>$C$10,0,IF(AND($C$38>0,A95>=$C$38,EOMONTH(A95,0)<=$C$39),E95*(1-$C$40)*(1-G$15),E95*(1-G$15)))+M95 -> 0 | U95: =IF(C95>$C$10,0,IF(AND($C$38>0,A95>=$C$38,EOMONTH(A95,0)<=$C$39),E95*(1-$C$40)*(1-H$15),E95*(1-H$15)))+M95 -> 0 | V95: =IF(C95>$C$10,0,IF(AND($C$38>0,A95>=$C$38,EOMONTH(A95,0)<=$C$39),E95*(1-$C$40)*(1-I$15),E95*(1-I$15)))+M95 -> 0 | W95: =IF(C95>$C$10,0,IF(AND($C$38>0,A95>=$C$38,EOMONTH(A95,0)<=$C$39),E95*(1-$C$40)*(1-F$34),E95*(1-F$34)))+M95 -> 0 | X95: =IF(C95>$C$10,0,IF(AND($C$38>0,A95>=$C$38,EOMONTH(A95,0)<=$C$39),E95*(1-$C$40)*(1-G$34),E95*(1-G$34)))+M95 -> 0 | Y95: =IF(C95>$C$10,0,IF(AND($C$38>0,A95>=$C$38,EOMONTH(A95,0)<=$C$39),E95*(1-$C$40)*(1-H$34),E95*(1-H$34)))+M95 -> 0 | Z95: =IF(C95>$C$10,0,IF(AND($C$38>0,A95>=$C$38,EOMONTH(A95,0)<=$C$39),E95*(1-$C$40)*(1-I$34),E95*(1-I$34)))+M95 -> 0 | AA95: =IF(C95>$C$10,0,IF(AND($C$38>0,A95>=$C$38,EOMONTH(A95,0)<=$C$39),E95*(1-$C$40)*(1-J$34),E95*(1-J$34)))+M95 -> 0
A96: =EDATE($C$8,21) -> 639 | B96: =EDATE($C$8,22)-1 -> 669 | C96: =ROW()-ROW($C$74) -> 22 | D96: =INT((C96-1)/12)+1 -> 2 | E96: =IF(C96>$C$10,0,$C$21*(1+$C$29)^(D96-1)) -> 0 | F96: =IF(C96>$C$10,0,IF(AND($C$38>0,A96>=$C$38,EOMONTH(A96,0)<=$C$39),E96*(1-$C$40),E96)) -> 0 | G96: =IF(C96>$C$10,0,IF(AND($C$38>0,A96>=$C$38,EOMONTH(A96,0)<=$C$39),-E96*$C$40,0)) -> 0 | H96: =IF(C96>$C$10,0,$C$24*(1+$C$30)^(D96-1)) -> 0 | I96: =IF(C96>$C$10,0,$C$22*(1+$C$31)^(D96-1)) -> 0 | J96: =IF(C96>$C$10,0,$C$23*(1+$C$32)^(D96-1)) -> 0 | K96: =IF(C96>$C$10,0,$C$25*(1+$C$33)^(D96-1)) -> 0 | L96: =IF(C96>$C$10,0,$C$26*(1+$C$34)^(D96-1)) -> 0 | M96: =H96+I96+J96+K96+L96 -> 0 | N96: =F96+M96 -> 0 | O96: =IF($C$7=0,0,N96/$C$7) -> 0 | P96: =MAX(SUM(N96:N198)+S96,0) -> 0 | Q96: =SUM(F96:F198) -> 0 | R96: =SUM(M96:M198) -> 0 | S96: =SUMPRODUCT(($C$55:$C$67)*($D$55:$D$67>=$A96)) -> 0 | T96: =IF(C96>$C$10,0,IF(AND($C$38>0,A96>=$C$38,EOMONTH(A96,0)<=$C$39),E96*(1-$C$40)*(1-G$15),E96*(1-G$15)))+M96 -> 0 | U96: =IF(C96>$C$10,0,IF(AND($C$38>0,A96>=$C$38,EOMONTH(A96,0)<=$C$39),E96*(1-$C$40)*(1-H$15),E96*(1-H$15)))+M96 -> 0 | V96: =IF(C96>$C$10,0,IF(AND($C$38>0,A96>=$C$38,EOMONTH(A96,0)<=$C$39),E96*(1-$C$40)*(1-I$15),E96*(1-I$15)))+M96 -> 0 | W96: =IF(C96>$C$10,0,IF(AND($C$38>0,A96>=$C$38,EOMONTH(A96,0)<=$C$39),E96*(1-$C$40)*(1-F$34),E96*(1-F$34)))+M96 -> 0 | X96: =IF(C96>$C$10,0,IF(AND($C$38>0,A96>=$C$38,EOMONTH(A96,0)<=$C$39),E96*(1-$C$40)*(1-G$34),E96*(1-G$34)))+M96 -> 0 | Y96: =IF(C96>$C$10,0,IF(AND($C$38>0,A96>=$C$38,EOMONTH(A96,0)<=$C$39),E96*(1-$C$40)*(1-H$34),E96*(1-H$34)))+M96 -> 0 | Z96: =IF(C96>$C$10,0,IF(AND($C$38>0,A96>=$C$38,EOMONTH(A96,0)<=$C$39),E96*(1-$C$40)*(1-I$34),E96*(1-I$34)))+M96 -> 0 | AA96: =IF(C96>$C$10,0,IF(AND($C$38>0,A96>=$C$38,EOMONTH(A96,0)<=$C$39),E96*(1-$C$40)*(1-J$34),E96*(1-J$34)))+M96 -> 0
A97: =EDATE($C$8,22) -> 670 | B97: =EDATE($C$8,23)-1 -> 699 | C97: =ROW()-ROW($C$74) -> 23 | D97: =INT((C97-1)/12)+1 -> 2 | E97: =IF(C97>$C$10,0,$C$21*(1+$C$29)^(D97-1)) -> 0 | F97: =IF(C97>$C$10,0,IF(AND($C$38>0,A97>=$C$38,EOMONTH(A97,0)<=$C$39),E97*(1-$C$40),E97)) -> 0 | G97: =IF(C97>$C$10,0,IF(AND($C$38>0,A97>=$C$38,EOMONTH(A97,0)<=$C$39),-E97*$C$40,0)) -> 0 | H97: =IF(C97>$C$10,0,$C$24*(1+$C$30)^(D97-1)) -> 0 | I97: =IF(C97>$C$10,0,$C$22*(1+$C$31)^(D97-1)) -> 0 | J97: =IF(C97>$C$10,0,$C$23*(1+$C$32)^(D97-1)) -> 0 | K97: =IF(C97>$C$10,0,$C$25*(1+$C$33)^(D97-1)) -> 0 | L97: =IF(C97>$C$10,0,$C$26*(1+$C$34)^(D97-1)) -> 0 | M97: =H97+I97+J97+K97+L97 -> 0 | N97: =F97+M97 -> 0 | O97: =IF($C$7=0,0,N97/$C$7) -> 0 | P97: =MAX(SUM(N97:N198)+S97,0) -> 0 | Q97: =SUM(F97:F198) -> 0 | R97: =SUM(M97:M198) -> 0 | S97: =SUMPRODUCT(($C$55:$C$67)*($D$55:$D$67>=$A97)) -> 0 | T97: =IF(C97>$C$10,0,IF(AND($C$38>0,A97>=$C$38,EOMONTH(A97,0)<=$C$39),E97*(1-$C$40)*(1-G$15),E97*(1-G$15)))+M97 -> 0 | U97: =IF(C97>$C$10,0,IF(AND($C$38>0,A97>=$C$38,EOMONTH(A97,0)<=$C$39),E97*(1-$C$40)*(1-H$15),E97*(1-H$15)))+M97 -> 0 | V97: =IF(C97>$C$10,0,IF(AND($C$38>0,A97>=$C$38,EOMONTH(A97,0)<=$C$39),E97*(1-$C$40)*(1-I$15),E97*(1-I$15)))+M97 -> 0 | W97: =IF(C97>$C$10,0,IF(AND($C$38>0,A97>=$C$38,EOMONTH(A97,0)<=$C$39),E97*(1-$C$40)*(1-F$34),E97*(1-F$34)))+M97 -> 0 | X97: =IF(C97>$C$10,0,IF(AND($C$38>0,A97>=$C$38,EOMONTH(A97,0)<=$C$39),E97*(1-$C$40)*(1-G$34),E97*(1-G$34)))+M97 -> 0 | Y97: =IF(C97>$C$10,0,IF(AND($C$38>0,A97>=$C$38,EOMONTH(A97,0)<=$C$39),E97*(1-$C$40)*(1-H$34),E97*(1-H$34)))+M97 -> 0 | Z97: =IF(C97>$C$10,0,IF(AND($C$38>0,A97>=$C$38,EOMONTH(A97,0)<=$C$39),E97*(1-$C$40)*(1-I$34),E97*(1-I$34)))+M97 -> 0 | AA97: =IF(C97>$C$10,0,IF(AND($C$38>0,A97>=$C$38,EOMONTH(A97,0)<=$C$39),E97*(1-$C$40)*(1-J$34),E97*(1-J$34)))+M97 -> 0
A98: =EDATE($C$8,23) -> 700 | B98: =EDATE($C$8,24)-1 -> 730 | C98: =ROW()-ROW($C$74) -> 24 | D98: =INT((C98-1)/12)+1 -> 2 | E98: =IF(C98>$C$10,0,$C$21*(1+$C$29)^(D98-1)) -> 0 | F98: =IF(C98>$C$10,0,IF(AND($C$38>0,A98>=$C$38,EOMONTH(A98,0)<=$C$39),E98*(1-$C$40),E98)) -> 0 | G98: =IF(C98>$C$10,0,IF(AND($C$38>0,A98>=$C$38,EOMONTH(A98,0)<=$C$39),-E98*$C$40,0)) -> 0 | H98: =IF(C98>$C$10,0,$C$24*(1+$C$30)^(D98-1)) -> 0 | I98: =IF(C98>$C$10,0,$C$22*(1+$C$31)^(D98-1)) -> 0 | J98: =IF(C98>$C$10,0,$C$23*(1+$C$32)^(D98-1)) -> 0 | K98: =IF(C98>$C$10,0,$C$25*(1+$C$33)^(D98-1)) -> 0 | L98: =IF(C98>$C$10,0,$C$26*(1+$C$34)^(D98-1)) -> 0 | M98: =H98+I98+J98+K98+L98 -> 0 | N98: =F98+M98 -> 0 | O98: =IF($C$7=0,0,N98/$C$7) -> 0 | P98: =MAX(SUM(N98:N198)+S98,0) -> 0 | Q98: =SUM(F98:F198) -> 0 | R98: =SUM(M98:M198) -> 0 | S98: =SUMPRODUCT(($C$55:$C$67)*($D$55:$D$67>=$A98)) -> 0 | T98: =IF(C98>$C$10,0,IF(AND($C$38>0,A98>=$C$38,EOMONTH(A98,0)<=$C$39),E98*(1-$C$40)*(1-G$15),E98*(1-G$15)))+M98 -> 0 | U98: =IF(C98>$C$10,0,IF(AND($C$38>0,A98>=$C$38,EOMONTH(A98,0)<=$C$39),E98*(1-$C$40)*(1-H$15),E98*(1-H$15)))+M98 -> 0 | V98: =IF(C98>$C$10,0,IF(AND($C$38>0,A98>=$C$38,EOMONTH(A98,0)<=$C$39),E98*(1-$C$40)*(1-I$15),E98*(1-I$15)))+M98 -> 0 | W98: =IF(C98>$C$10,0,IF(AND($C$38>0,A98>=$C$38,EOMONTH(A98,0)<=$C$39),E98*(1-$C$40)*(1-F$34),E98*(1-F$34)))+M98 -> 0 | X98: =IF(C98>$C$10,0,IF(AND($C$38>0,A98>=$C$38,EOMONTH(A98,0)<=$C$39),E98*(1-$C$40)*(1-G$34),E98*(1-G$34)))+M98 -> 0 | Y98: =IF(C98>$C$10,0,IF(AND($C$38>0,A98>=$C$38,EOMONTH(A98,0)<=$C$39),E98*(1-$C$40)*(1-H$34),E98*(1-H$34)))+M98 -> 0 | Z98: =IF(C98>$C$10,0,IF(AND($C$38>0,A98>=$C$38,EOMONTH(A98,0)<=$C$39),E98*(1-$C$40)*(1-I$34),E98*(1-I$34)))+M98 -> 0 | AA98: =IF(C98>$C$10,0,IF(AND($C$38>0,A98>=$C$38,EOMONTH(A98,0)<=$C$39),E98*(1-$C$40)*(1-J$34),E98*(1-J$34)))+M98 -> 0
A99: =EDATE($C$8,24) -> 731 | B99: =EDATE($C$8,25)-1 -> 761 | C99: =ROW()-ROW($C$74) -> 25 | D99: =INT((C99-1)/12)+1 -> 3 | E99: =IF(C99>$C$10,0,$C$21*(1+$C$29)^(D99-1)) -> 0 | F99: =IF(C99>$C$10,0,IF(AND($C$38>0,A99>=$C$38,EOMONTH(A99,0)<=$C$39),E99*(1-$C$40),E99)) -> 0 | G99: =IF(C99>$C$10,0,IF(AND($C$38>0,A99>=$C$38,EOMONTH(A99,0)<=$C$39),-E99*$C$40,0)) -> 0 | H99: =IF(C99>$C$10,0,$C$24*(1+$C$30)^(D99-1)) -> 0 | I99: =IF(C99>$C$10,0,$C$22*(1+$C$31)^(D99-1)) -> 0 | J99: =IF(C99>$C$10,0,$C$23*(1+$C$32)^(D99-1)) -> 0 | K99: =IF(C99>$C$10,0,$C$25*(1+$C$33)^(D99-1)) -> 0 | L99: =IF(C99>$C$10,0,$C$26*(1+$C$34)^(D99-1)) -> 0 | M99: =H99+I99+J99+K99+L99 -> 0 | N99: =F99+M99 -> 0 | O99: =IF($C$7=0,0,N99/$C$7) -> 0 | P99: =MAX(SUM(N99:N198)+S99,0) -> 0 | Q99: =SUM(F99:F198) -> 0 | R99: =SUM(M99:M198) -> 0 | S99: =SUMPRODUCT(($C$55:$C$67)*($D$55:$D$67>=$A99)) -> 0 | T99: =IF(C99>$C$10,0,IF(AND($C$38>0,A99>=$C$38,EOMONTH(A99,0)<=$C$39),E99*(1-$C$40)*(1-G$15),E99*(1-G$15)))+M99 -> 0 | U99: =IF(C99>$C$10,0,IF(AND($C$38>0,A99>=$C$38,EOMONTH(A99,0)<=$C$39),E99*(1-$C$40)*(1-H$15),E99*(1-H$15)))+M99 -> 0 | V99: =IF(C99>$C$10,0,IF(AND($C$38>0,A99>=$C$38,EOMONTH(A99,0)<=$C$39),E99*(1-$C$40)*(1-I$15),E99*(1-I$15)))+M99 -> 0 | W99: =IF(C99>$C$10,0,IF(AND($C$38>0,A99>=$C$38,EOMONTH(A99,0)<=$C$39),E99*(1-$C$40)*(1-F$34),E99*(1-F$34)))+M99 -> 0 | X99: =IF(C99>$C$10,0,IF(AND($C$38>0,A99>=$C$38,EOMONTH(A99,0)<=$C$39),E99*(1-$C$40)*(1-G$34),E99*(1-G$34)))+M99 -> 0 | Y99: =IF(C99>$C$10,0,IF(AND($C$38>0,A99>=$C$38,EOMONTH(A99,0)<=$C$39),E99*(1-$C$40)*(1-H$34),E99*(1-H$34)))+M99 -> 0 | Z99: =IF(C99>$C$10,0,IF(AND($C$38>0,A99>=$C$38,EOMONTH(A99,0)<=$C$39),E99*(1-$C$40)*(1-I$34),E99*(1-I$34)))+M99 -> 0 | AA99: =IF(C99>$C$10,0,IF(AND($C$38>0,A99>=$C$38,EOMONTH(A99,0)<=$C$39),E99*(1-$C$40)*(1-J$34),E99*(1-J$34)))+M99 -> 0
A100: =EDATE($C$8,25) -> 762 | B100: =EDATE($C$8,26)-1 -> 789 | C100: =ROW()-ROW($C$74) -> 26 | D100: =INT((C100-1)/12)+1 -> 3 | E100: =IF(C100>$C$10,0,$C$21*(1+$C$29)^(D100-1)) -> 0 | F100: =IF(C100>$C$10,0,IF(AND($C$38>0,A100>=$C$38,EOMONTH(A100,0)<=$C$39),E100*(1-$C$40),E100)) -> 0 | G100: =IF(C100>$C$10,0,IF(AND($C$38>0,A100>=$C$38,EOMONTH(A100,0)<=$C$39),-E100*$C$40,0)) -> 0 | H100: =IF(C100>$C$10,0,$C$24*(1+$C$30)^(D100-1)) -> 0 | I100: =IF(C100>$C$10,0,$C$22*(1+$C$31)^(D100-1)) -> 0 | J100: =IF(C100>$C$10,0,$C$23*(1+$C$32)^(D100-1)) -> 0 | K100: =IF(C100>$C$10,0,$C$25*(1+$C$33)^(D100-1)) -> 0 | L100: =IF(C100>$C$10,0,$C$26*(1+$C$34)^(D100-1)) -> 0 | M100: =H100+I100+J100+K100+L100 -> 0 | N100: =F100+M100 -> 0 | O100: =IF($C$7=0,0,N100/$C$7) -> 0 | P100: =MAX(SUM(N100:N198)+S100,0) -> 0 | Q100: =SUM(F100:F198) -> 0 | R100: =SUM(M100:M198) -> 0 | S100: =SUMPRODUCT(($C$55:$C$67)*($D$55:$D$67>=$A100)) -> 0 | T100: =IF(C100>$C$10,0,IF(AND($C$38>0,A100>=$C$38,EOMONTH(A100,0)<=$C$39),E100*(1-$C$40)*(1-G$15),E100*(1-G$15)))+M100 -> 0 | U100: =IF(C100>$C$10,0,IF(AND($C$38>0,A100>=$C$38,EOMONTH(A100,0)<=$C$39),E100*(1-$C$40)*(1-H$15),E100*(1-H$15)))+M100 -> 0 | V100: =IF(C100>$C$10,0,IF(AND($C$38>0,A100>=$C$38,EOMONTH(A100,0)<=$C$39),E100*(1-$C$40)*(1-I$15),E100*(1-I$15)))+M100 -> 0 | W100: =IF(C100>$C$10,0,IF(AND($C$38>0,A100>=$C$38,EOMONTH(A100,0)<=$C$39),E100*(1-$C$40)*(1-F$34),E100*(1-F$34)))+M100 -> 0 | X100: =IF(C100>$C$10,0,IF(AND($C$38>0,A100>=$C$38,EOMONTH(A100,0)<=$C$39),E100*(1-$C$40)*(1-G$34),E100*(1-G$34)))+M100 -> 0 | Y100: =IF(C100>$C$10,0,IF(AND($C$38>0,A100>=$C$38,EOMONTH(A100,0)<=$C$39),E100*(1-$C$40)*(1-H$34),E100*(1-H$34)))+M100 -> 0 | Z100: =IF(C100>$C$10,0,IF(AND($C$38>0,A100>=$C$38,EOMONTH(A100,0)<=$C$39),E100*(1-$C$40)*(1-I$34),E100*(1-I$34)))+M100 -> 0 | AA100: =IF(C100>$C$10,0,IF(AND($C$38>0,A100>=$C$38,EOMONTH(A100,0)<=$C$39),E100*(1-$C$40)*(1-J$34),E100*(1-J$34)))+M100 -> 0
A101: =EDATE($C$8,26) -> 790 | B101: =EDATE($C$8,27)-1 -> 820 | C101: =ROW()-ROW($C$74) -> 27 | D101: =INT((C101-1)/12)+1 -> 3 | E101: =IF(C101>$C$10,0,$C$21*(1+$C$29)^(D101-1)) -> 0 | F101: =IF(C101>$C$10,0,IF(AND($C$38>0,A101>=$C$38,EOMONTH(A101,0)<=$C$39),E101*(1-$C$40),E101)) -> 0 | G101: =IF(C101>$C$10,0,IF(AND($C$38>0,A101>=$C$38,EOMONTH(A101,0)<=$C$39),-E101*$C$40,0)) -> 0 | H101: =IF(C101>$C$10,0,$C$24*(1+$C$30)^(D101-1)) -> 0 | I101: =IF(C101>$C$10,0,$C$22*(1+$C$31)^(D101-1)) -> 0 | J101: =IF(C101>$C$10,0,$C$23*(1+$C$32)^(D101-1)) -> 0 | K101: =IF(C101>$C$10,0,$C$25*(1+$C$33)^(D101-1)) -> 0 | L101: =IF(C101>$C$10,0,$C$26*(1+$C$34)^(D101-1)) -> 0 | M101: =H101+I101+J101+K101+L101 -> 0 | N101: =F101+M101 -> 0 | O101: =IF($C$7=0,0,N101/$C$7) -> 0 | P101: =MAX(SUM(N101:N198)+S101,0) -> 0 | Q101: =SUM(F101:F198) -> 0 | R101: =SUM(M101:M198) -> 0 | S101: =SUMPRODUCT(($C$55:$C$67)*($D$55:$D$67>=$A101)) -> 0 | T101: =IF(C101>$C$10,0,IF(AND($C$38>0,A101>=$C$38,EOMONTH(A101,0)<=$C$39),E101*(1-$C$40)*(1-G$15),E101*(1-G$15)))+M101 -> 0 | U101: =IF(C101>$C$10,0,IF(AND($C$38>0,A101>=$C$38,EOMONTH(A101,0)<=$C$39),E101*(1-$C$40)*(1-H$15),E101*(1-H$15)))+M101 -> 0 | V101: =IF(C101>$C$10,0,IF(AND($C$38>0,A101>=$C$38,EOMONTH(A101,0)<=$C$39),E101*(1-$C$40)*(1-I$15),E101*(1-I$15)))+M101 -> 0 | W101: =IF(C101>$C$10,0,IF(AND($C$38>0,A101>=$C$38,EOMONTH(A101,0)<=$C$39),E101*(1-$C$40)*(1-F$34),E101*(1-F$34)))+M101 -> 0 | X101: =IF(C101>$C$10,0,IF(AND($C$38>0,A101>=$C$38,EOMONTH(A101,0)<=$C$39),E101*(1-$C$40)*(1-G$34),E101*(1-G$34)))+M101 -> 0 | Y101: =IF(C101>$C$10,0,IF(AND($C$38>0,A101>=$C$38,EOMONTH(A101,0)<=$C$39),E101*(1-$C$40)*(1-H$34),E101*(1-H$34)))+M101 -> 0 | Z101: =IF(C101>$C$10,0,IF(AND($C$38>0,A101>=$C$38,EOMONTH(A101,0)<=$C$39),E101*(1-$C$40)*(1-I$34),E101*(1-I$34)))+M101 -> 0 | AA101: =IF(C101>$C$10,0,IF(AND($C$38>0,A101>=$C$38,EOMONTH(A101,0)<=$C$39),E101*(1-$C$40)*(1-J$34),E101*(1-J$34)))+M101 -> 0
A102: =EDATE($C$8,27) -> 821 | B102: =EDATE($C$8,28)-1 -> 850 | C102: =ROW()-ROW($C$74) -> 28 | D102: =INT((C102-1)/12)+1 -> 3 | E102: =IF(C102>$C$10,0,$C$21*(1+$C$29)^(D102-1)) -> 0 | F102: =IF(C102>$C$10,0,IF(AND($C$38>0,A102>=$C$38,EOMONTH(A102,0)<=$C$39),E102*(1-$C$40),E102)) -> 0 | G102: =IF(C102>$C$10,0,IF(AND($C$38>0,A102>=$C$38,EOMONTH(A102,0)<=$C$39),-E102*$C$40,0)) -> 0 | H102: =IF(C102>$C$10,0,$C$24*(1+$C$30)^(D102-1)) -> 0 | I102: =IF(C102>$C$10,0,$C$22*(1+$C$31)^(D102-1)) -> 0 | J102: =IF(C102>$C$10,0,$C$23*(1+$C$32)^(D102-1)) -> 0 | K102: =IF(C102>$C$10,0,$C$25*(1+$C$33)^(D102-1)) -> 0 | L102: =IF(C102>$C$10,0,$C$26*(1+$C$34)^(D102-1)) -> 0 | M102: =H102+I102+J102+K102+L102 -> 0 | N102: =F102+M102 -> 0 | O102: =IF($C$7=0,0,N102/$C$7) -> 0 | P102: =MAX(SUM(N102:N198)+S102,0) -> 0 | Q102: =SUM(F102:F198) -> 0 | R102: =SUM(M102:M198) -> 0 | S102: =SUMPRODUCT(($C$55:$C$67)*($D$55:$D$67>=$A102)) -> 0 | T102: =IF(C102>$C$10,0,IF(AND($C$38>0,A102>=$C$38,EOMONTH(A102,0)<=$C$39),E102*(1-$C$40)*(1-G$15),E102*(1-G$15)))+M102 -> 0 | U102: =IF(C102>$C$10,0,IF(AND($C$38>0,A102>=$C$38,EOMONTH(A102,0)<=$C$39),E102*(1-$C$40)*(1-H$15),E102*(1-H$15)))+M102 -> 0 | V102: =IF(C102>$C$10,0,IF(AND($C$38>0,A102>=$C$38,EOMONTH(A102,0)<=$C$39),E102*(1-$C$40)*(1-I$15),E102*(1-I$15)))+M102 -> 0 | W102: =IF(C102>$C$10,0,IF(AND($C$38>0,A102>=$C$38,EOMONTH(A102,0)<=$C$39),E102*(1-$C$40)*(1-F$34),E102*(1-F$34)))+M102 -> 0 | X102: =IF(C102>$C$10,0,IF(AND($C$38>0,A102>=$C$38,EOMONTH(A102,0)<=$C$39),E102*(1-$C$40)*(1-G$34),E102*(1-G$34)))+M102 -> 0 | Y102: =IF(C102>$C$10,0,IF(AND($C$38>0,A102>=$C$38,EOMONTH(A102,0)<=$C$39),E102*(1-$C$40)*(1-H$34),E102*(1-H$34)))+M102 -> 0 | Z102: =IF(C102>$C$10,0,IF(AND($C$38>0,A102>=$C$38,EOMONTH(A102,0)<=$C$39),E102*(1-$C$40)*(1-I$34),E102*(1-I$34)))+M102 -> 0 | AA102: =IF(C102>$C$10,0,IF(AND($C$38>0,A102>=$C$38,EOMONTH(A102,0)<=$C$39),E102*(1-$C$40)*(1-J$34),E102*(1-J$34)))+M102 -> 0
A103: =EDATE($C$8,28) -> 851 | B103: =EDATE($C$8,29)-1 -> 881 | C103: =ROW()-ROW($C$74) -> 29 | D103: =INT((C103-1)/12)+1 -> 3 | E103: =IF(C103>$C$10,0,$C$21*(1+$C$29)^(D103-1)) -> 0 | F103: =IF(C103>$C$10,0,IF(AND($C$38>0,A103>=$C$38,EOMONTH(A103,0)<=$C$39),E103*(1-$C$40),E103)) -> 0 | G103: =IF(C103>$C$10,0,IF(AND($C$38>0,A103>=$C$38,EOMONTH(A103,0)<=$C$39),-E103*$C$40,0)) -> 0 | H103: =IF(C103>$C$10,0,$C$24*(1+$C$30)^(D103-1)) -> 0 | I103: =IF(C103>$C$10,0,$C$22*(1+$C$31)^(D103-1)) -> 0 | J103: =IF(C103>$C$10,0,$C$23*(1+$C$32)^(D103-1)) -> 0 | K103: =IF(C103>$C$10,0,$C$25*(1+$C$33)^(D103-1)) -> 0 | L103: =IF(C103>$C$10,0,$C$26*(1+$C$34)^(D103-1)) -> 0 | M103: =H103+I103+J103+K103+L103 -> 0 | N103: =F103+M103 -> 0 | O103: =IF($C$7=0,0,N103/$C$7) -> 0 | P103: =MAX(SUM(N103:N198)+S103,0) -> 0 | Q103: =SUM(F103:F198) -> 0 | R103: =SUM(M103:M198) -> 0 | S103: =SUMPRODUCT(($C$55:$C$67)*($D$55:$D$67>=$A103)) -> 0 | T103: =IF(C103>$C$10,0,IF(AND($C$38>0,A103>=$C$38,EOMONTH(A103,0)<=$C$39),E103*(1-$C$40)*(1-G$15),E103*(1-G$15)))+M103 -> 0 | U103: =IF(C103>$C$10,0,IF(AND($C$38>0,A103>=$C$38,EOMONTH(A103,0)<=$C$39),E103*(1-$C$40)*(1-H$15),E103*(1-H$15)))+M103 -> 0 | V103: =IF(C103>$C$10,0,IF(AND($C$38>0,A103>=$C$38,EOMONTH(A103,0)<=$C$39),E103*(1-$C$40)*(1-I$15),E103*(1-I$15)))+M103 -> 0 | W103: =IF(C103>$C$10,0,IF(AND($C$38>0,A103>=$C$38,EOMONTH(A103,0)<=$C$39),E103*(1-$C$40)*(1-F$34),E103*(1-F$34)))+M103 -> 0 | X103: =IF(C103>$C$10,0,IF(AND($C$38>0,A103>=$C$38,EOMONTH(A103,0)<=$C$39),E103*(1-$C$40)*(1-G$34),E103*(1-G$34)))+M103 -> 0 | Y103: =IF(C103>$C$10,0,IF(AND($C$38>0,A103>=$C$38,EOMONTH(A103,0)<=$C$39),E103*(1-$C$40)*(1-H$34),E103*(1-H$34)))+M103 -> 0 | Z103: =IF(C103>$C$10,0,IF(AND($C$38>0,A103>=$C$38,EOMONTH(A103,0)<=$C$39),E103*(1-$C$40)*(1-I$34),E103*(1-I$34)))+M103 -> 0 | AA103: =IF(C103>$C$10,0,IF(AND($C$38>0,A103>=$C$38,EOMONTH(A103,0)<=$C$39),E103*(1-$C$40)*(1-J$34),E103*(1-J$34)))+M103 -> 0
A104: =EDATE($C$8,29) -> 882 | B104: =EDATE($C$8,30)-1 -> 911 | C104: =ROW()-ROW($C$74) -> 30 | D104: =INT((C104-1)/12)+1 -> 3 | E104: =IF(C104>$C$10,0,$C$21*(1+$C$29)^(D104-1)) -> 0 | F104: =IF(C104>$C$10,0,IF(AND($C$38>0,A104>=$C$38,EOMONTH(A104,0)<=$C$39),E104*(1-$C$40),E104)) -> 0 | G104: =IF(C104>$C$10,0,IF(AND($C$38>0,A104>=$C$38,EOMONTH(A104,0)<=$C$39),-E104*$C$40,0)) -> 0 | H104: =IF(C104>$C$10,0,$C$24*(1+$C$30)^(D104-1)) -> 0 | I104: =IF(C104>$C$10,0,$C$22*(1+$C$31)^(D104-1)) -> 0 | J104: =IF(C104>$C$10,0,$C$23*(1+$C$32)^(D104-1)) -> 0 | K104: =IF(C104>$C$10,0,$C$25*(1+$C$33)^(D104-1)) -> 0 | L104: =IF(C104>$C$10,0,$C$26*(1+$C$34)^(D104-1)) -> 0 | M104: =H104+I104+J104+K104+L104 -> 0 | N104: =F104+M104 -> 0 | O104: =IF($C$7=0,0,N104/$C$7) -> 0 | P104: =MAX(SUM(N104:N198)+S104,0) -> 0 | Q104: =SUM(F104:F198) -> 0 | R104: =SUM(M104:M198) -> 0 | S104: =SUMPRODUCT(($C$55:$C$67)*($D$55:$D$67>=$A104)) -> 0 | T104: =IF(C104>$C$10,0,IF(AND($C$38>0,A104>=$C$38,EOMONTH(A104,0)<=$C$39),E104*(1-$C$40)*(1-G$15),E104*(1-G$15)))+M104 -> 0 | U104: =IF(C104>$C$10,0,IF(AND($C$38>0,A104>=$C$38,EOMONTH(A104,0)<=$C$39),E104*(1-$C$40)*(1-H$15),E104*(1-H$15)))+M104 -> 0 | V104: =IF(C104>$C$10,0,IF(AND($C$38>0,A104>=$C$38,EOMONTH(A104,0)<=$C$39),E104*(1-$C$40)*(1-I$15),E104*(1-I$15)))+M104 -> 0 | W104: =IF(C104>$C$10,0,IF(AND($C$38>0,A104>=$C$38,EOMONTH(A104,0)<=$C$39),E104*(1-$C$40)*(1-F$34),E104*(1-F$34)))+M104 -> 0 | X104: =IF(C104>$C$10,0,IF(AND($C$38>0,A104>=$C$38,EOMONTH(A104,0)<=$C$39),E104*(1-$C$40)*(1-G$34),E104*(1-G$34)))+M104 -> 0 | Y104: =IF(C104>$C$10,0,IF(AND($C$38>0,A104>=$C$38,EOMONTH(A104,0)<=$C$39),E104*(1-$C$40)*(1-H$34),E104*(1-H$34)))+M104 -> 0 | Z104: =IF(C104>$C$10,0,IF(AND($C$38>0,A104>=$C$38,EOMONTH(A104,0)<=$C$39),E104*(1-$C$40)*(1-I$34),E104*(1-I$34)))+M104 -> 0 | AA104: =IF(C104>$C$10,0,IF(AND($C$38>0,A104>=$C$38,EOMONTH(A104,0)<=$C$39),E104*(1-$C$40)*(1-J$34),E104*(1-J$34)))+M104 -> 0
A105: =EDATE($C$8,30) -> 912 | B105: =EDATE($C$8,31)-1 -> 942 | C105: =ROW()-ROW($C$74) -> 31 | D105: =INT((C105-1)/12)+1 -> 3 | E105: =IF(C105>$C$10,0,$C$21*(1+$C$29)^(D105-1)) -> 0 | F105: =IF(C105>$C$10,0,IF(AND($C$38>0,A105>=$C$38,EOMONTH(A105,0)<=$C$39),E105*(1-$C$40),E105)) -> 0 | G105: =IF(C105>$C$10,0,IF(AND($C$38>0,A105>=$C$38,EOMONTH(A105,0)<=$C$39),-E105*$C$40,0)) -> 0 | H105: =IF(C105>$C$10,0,$C$24*(1+$C$30)^(D105-1)) -> 0 | I105: =IF(C105>$C$10,0,$C$22*(1+$C$31)^(D105-1)) -> 0 | J105: =IF(C105>$C$10,0,$C$23*(1+$C$32)^(D105-1)) -> 0 | K105: =IF(C105>$C$10,0,$C$25*(1+$C$33)^(D105-1)) -> 0 | L105: =IF(C105>$C$10,0,$C$26*(1+$C$34)^(D105-1)) -> 0 | M105: =H105+I105+J105+K105+L105 -> 0 | N105: =F105+M105 -> 0 | O105: =IF($C$7=0,0,N105/$C$7) -> 0 | P105: =MAX(SUM(N105:N198)+S105,0) -> 0 | Q105: =SUM(F105:F198) -> 0 | R105: =SUM(M105:M198) -> 0 | S105: =SUMPRODUCT(($C$55:$C$67)*($D$55:$D$67>=$A105)) -> 0 | T105: =IF(C105>$C$10,0,IF(AND($C$38>0,A105>=$C$38,EOMONTH(A105,0)<=$C$39),E105*(1-$C$40)*(1-G$15),E105*(1-G$15)))+M105 -> 0 | U105: =IF(C105>$C$10,0,IF(AND($C$38>0,A105>=$C$38,EOMONTH(A105,0)<=$C$39),E105*(1-$C$40)*(1-H$15),E105*(1-H$15)))+M105 -> 0 | V105: =IF(C105>$C$10,0,IF(AND($C$38>0,A105>=$C$38,EOMONTH(A105,0)<=$C$39),E105*(1-$C$40)*(1-I$15),E105*(1-I$15)))+M105 -> 0 | W105: =IF(C105>$C$10,0,IF(AND($C$38>0,A105>=$C$38,EOMONTH(A105,0)<=$C$39),E105*(1-$C$40)*(1-F$34),E105*(1-F$34)))+M105 -> 0 | X105: =IF(C105>$C$10,0,IF(AND($C$38>0,A105>=$C$38,EOMONTH(A105,0)<=$C$39),E105*(1-$C$40)*(1-G$34),E105*(1-G$34)))+M105 -> 0 | Y105: =IF(C105>$C$10,0,IF(AND($C$38>0,A105>=$C$38,EOMONTH(A105,0)<=$C$39),E105*(1-$C$40)*(1-H$34),E105*(1-H$34)))+M105 -> 0 | Z105: =IF(C105>$C$10,0,IF(AND($C$38>0,A105>=$C$38,EOMONTH(A105,0)<=$C$39),E105*(1-$C$40)*(1-I$34),E105*(1-I$34)))+M105 -> 0 | AA105: =IF(C105>$C$10,0,IF(AND($C$38>0,A105>=$C$38,EOMONTH(A105,0)<=$C$39),E105*(1-$C$40)*(1-J$34),E105*(1-J$34)))+M105 -> 0
A106: =EDATE($C$8,31) -> 943 | B106: =EDATE($C$8,32)-1 -> 973 | C106: =ROW()-ROW($C$74) -> 32 | D106: =INT((C106-1)/12)+1 -> 3 | E106: =IF(C106>$C$10,0,$C$21*(1+$C$29)^(D106-1)) -> 0 | F106: =IF(C106>$C$10,0,IF(AND($C$38>0,A106>=$C$38,EOMONTH(A106,0)<=$C$39),E106*(1-$C$40),E106)) -> 0 | G106: =IF(C106>$C$10,0,IF(AND($C$38>0,A106>=$C$38,EOMONTH(A106,0)<=$C$39),-E106*$C$40,0)) -> 0 | H106: =IF(C106>$C$10,0,$C$24*(1+$C$30)^(D106-1)) -> 0 | I106: =IF(C106>$C$10,0,$C$22*(1+$C$31)^(D106-1)) -> 0 | J106: =IF(C106>$C$10,0,$C$23*(1+$C$32)^(D106-1)) -> 0 | K106: =IF(C106>$C$10,0,$C$25*(1+$C$33)^(D106-1)) -> 0 | L106: =IF(C106>$C$10,0,$C$26*(1+$C$34)^(D106-1)) -> 0 | M106: =H106+I106+J106+K106+L106 -> 0 | N106: =F106+M106 -> 0 | O106: =IF($C$7=0,0,N106/$C$7) -> 0 | P106: =MAX(SUM(N106:N198)+S106,0) -> 0 | Q106: =SUM(F106:F198) -> 0 | R106: =SUM(M106:M198) -> 0 | S106: =SUMPRODUCT(($C$55:$C$67)*($D$55:$D$67>=$A106)) -> 0 | T106: =IF(C106>$C$10,0,IF(AND($C$38>0,A106>=$C$38,EOMONTH(A106,0)<=$C$39),E106*(1-$C$40)*(1-G$15),E106*(1-G$15)))+M106 -> 0 | U106: =IF(C106>$C$10,0,IF(AND($C$38>0,A106>=$C$38,EOMONTH(A106,0)<=$C$39),E106*(1-$C$40)*(1-H$15),E106*(1-H$15)))+M106 -> 0 | V106: =IF(C106>$C$10,0,IF(AND($C$38>0,A106>=$C$38,EOMONTH(A106,0)<=$C$39),E106*(1-$C$40)*(1-I$15),E106*(1-I$15)))+M106 -> 0 | W106: =IF(C106>$C$10,0,IF(AND($C$38>0,A106>=$C$38,EOMONTH(A106,0)<=$C$39),E106*(1-$C$40)*(1-F$34),E106*(1-F$34)))+M106 -> 0 | X106: =IF(C106>$C$10,0,IF(AND($C$38>0,A106>=$C$38,EOMONTH(A106,0)<=$C$39),E106*(1-$C$40)*(1-G$34),E106*(1-G$34)))+M106 -> 0 | Y106: =IF(C106>$C$10,0,IF(AND($C$38>0,A106>=$C$38,EOMONTH(A106,0)<=$C$39),E106*(1-$C$40)*(1-H$34),E106*(1-H$34)))+M106 -> 0 | Z106: =IF(C106>$C$10,0,IF(AND($C$38>0,A106>=$C$38,EOMONTH(A106,0)<=$C$39),E106*(1-$C$40)*(1-I$34),E106*(1-I$34)))+M106 -> 0 | AA106: =IF(C106>$C$10,0,IF(AND($C$38>0,A106>=$C$38,EOMONTH(A106,0)<=$C$39),E106*(1-$C$40)*(1-J$34),E106*(1-J$34)))+M106 -> 0
A107: =EDATE($C$8,32) -> 974 | B107: =EDATE($C$8,33)-1 -> 1003 | C107: =ROW()-ROW($C$74) -> 33 | D107: =INT((C107-1)/12)+1 -> 3 | E107: =IF(C107>$C$10,0,$C$21*(1+$C$29)^(D107-1)) -> 0 | F107: =IF(C107>$C$10,0,IF(AND($C$38>0,A107>=$C$38,EOMONTH(A107,0)<=$C$39),E107*(1-$C$40),E107)) -> 0 | G107: =IF(C107>$C$10,0,IF(AND($C$38>0,A107>=$C$38,EOMONTH(A107,0)<=$C$39),-E107*$C$40,0)) -> 0 | H107: =IF(C107>$C$10,0,$C$24*(1+$C$30)^(D107-1)) -> 0 | I107: =IF(C107>$C$10,0,$C$22*(1+$C$31)^(D107-1)) -> 0 | J107: =IF(C107>$C$10,0,$C$23*(1+$C$32)^(D107-1)) -> 0 | K107: =IF(C107>$C$10,0,$C$25*(1+$C$33)^(D107-1)) -> 0 | L107: =IF(C107>$C$10,0,$C$26*(1+$C$34)^(D107-1)) -> 0 | M107: =H107+I107+J107+K107+L107 -> 0 | N107: =F107+M107 -> 0 | O107: =IF($C$7=0,0,N107/$C$7) -> 0 | P107: =MAX(SUM(N107:N198)+S107,0) -> 0 | Q107: =SUM(F107:F198) -> 0 | R107: =SUM(M107:M198) -> 0 | S107: =SUMPRODUCT(($C$55:$C$67)*($D$55:$D$67>=$A107)) -> 0 | T107: =IF(C107>$C$10,0,IF(AND($C$38>0,A107>=$C$38,EOMONTH(A107,0)<=$C$39),E107*(1-$C$40)*(1-G$15),E107*(1-G$15)))+M107 -> 0 | U107: =IF(C107>$C$10,0,IF(AND($C$38>0,A107>=$C$38,EOMONTH(A107,0)<=$C$39),E107*(1-$C$40)*(1-H$15),E107*(1-H$15)))+M107 -> 0 | V107: =IF(C107>$C$10,0,IF(AND($C$38>0,A107>=$C$38,EOMONTH(A107,0)<=$C$39),E107*(1-$C$40)*(1-I$15),E107*(1-I$15)))+M107 -> 0 | W107: =IF(C107>$C$10,0,IF(AND($C$38>0,A107>=$C$38,EOMONTH(A107,0)<=$C$39),E107*(1-$C$40)*(1-F$34),E107*(1-F$34)))+M107 -> 0 | X107: =IF(C107>$C$10,0,IF(AND($C$38>0,A107>=$C$38,EOMONTH(A107,0)<=$C$39),E107*(1-$C$40)*(1-G$34),E107*(1-G$34)))+M107 -> 0 | Y107: =IF(C107>$C$10,0,IF(AND($C$38>0,A107>=$C$38,EOMONTH(A107,0)<=$C$39),E107*(1-$C$40)*(1-H$34),E107*(1-H$34)))+M107 -> 0 | Z107: =IF(C107>$C$10,0,IF(AND($C$38>0,A107>=$C$38,EOMONTH(A107,0)<=$C$39),E107*(1-$C$40)*(1-I$34),E107*(1-I$34)))+M107 -> 0 | AA107: =IF(C107>$C$10,0,IF(AND($C$38>0,A107>=$C$38,EOMONTH(A107,0)<=$C$39),E107*(1-$C$40)*(1-J$34),E107*(1-J$34)))+M107 -> 0
A108: =EDATE($C$8,33) -> 1004 | B108: =EDATE($C$8,34)-1 -> 1034 | C108: =ROW()-ROW($C$74) -> 34 | D108: =INT((C108-1)/12)+1 -> 3 | E108: =IF(C108>$C$10,0,$C$21*(1+$C$29)^(D108-1)) -> 0 | F108: =IF(C108>$C$10,0,IF(AND($C$38>0,A108>=$C$38,EOMONTH(A108,0)<=$C$39),E108*(1-$C$40),E108)) -> 0 | G108: =IF(C108>$C$10,0,IF(AND($C$38>0,A108>=$C$38,EOMONTH(A108,0)<=$C$39),-E108*$C$40,0)) -> 0 | H108: =IF(C108>$C$10,0,$C$24*(1+$C$30)^(D108-1)) -> 0 | I108: =IF(C108>$C$10,0,$C$22*(1+$C$31)^(D108-1)) -> 0 | J108: =IF(C108>$C$10,0,$C$23*(1+$C$32)^(D108-1)) -> 0 | K108: =IF(C108>$C$10,0,$C$25*(1+$C$33)^(D108-1)) -> 0 | L108: =IF(C108>$C$10,0,$C$26*(1+$C$34)^(D108-1)) -> 0 | M108: =H108+I108+J108+K108+L108 -> 0 | N108: =F108+M108 -> 0 | O108: =IF($C$7=0,0,N108/$C$7) -> 0 | P108: =MAX(SUM(N108:N198)+S108,0) -> 0 | Q108: =SUM(F108:F198) -> 0 | R108: =SUM(M108:M198) -> 0 | S108: =SUMPRODUCT(($C$55:$C$67)*($D$55:$D$67>=$A108)) -> 0 | T108: =IF(C108>$C$10,0,IF(AND($C$38>0,A108>=$C$38,EOMONTH(A108,0)<=$C$39),E108*(1-$C$40)*(1-G$15),E108*(1-G$15)))+M108 -> 0 | U108: =IF(C108>$C$10,0,IF(AND($C$38>0,A108>=$C$38,EOMONTH(A108,0)<=$C$39),E108*(1-$C$40)*(1-H$15),E108*(1-H$15)))+M108 -> 0 | V108: =IF(C108>$C$10,0,IF(AND($C$38>0,A108>=$C$38,EOMONTH(A108,0)<=$C$39),E108*(1-$C$40)*(1-I$15),E108*(1-I$15)))+M108 -> 0 | W108: =IF(C108>$C$10,0,IF(AND($C$38>0,A108>=$C$38,EOMONTH(A108,0)<=$C$39),E108*(1-$C$40)*(1-F$34),E108*(1-F$34)))+M108 -> 0 | X108: =IF(C108>$C$10,0,IF(AND($C$38>0,A108>=$C$38,EOMONTH(A108,0)<=$C$39),E108*(1-$C$40)*(1-G$34),E108*(1-G$34)))+M108 -> 0 | Y108: =IF(C108>$C$10,0,IF(AND($C$38>0,A108>=$C$38,EOMONTH(A108,0)<=$C$39),E108*(1-$C$40)*(1-H$34),E108*(1-H$34)))+M108 -> 0 | Z108: =IF(C108>$C$10,0,IF(AND($C$38>0,A108>=$C$38,EOMONTH(A108,0)<=$C$39),E108*(1-$C$40)*(1-I$34),E108*(1-I$34)))+M108 -> 0 | AA108: =IF(C108>$C$10,0,IF(AND($C$38>0,A108>=$C$38,EOMONTH(A108,0)<=$C$39),E108*(1-$C$40)*(1-J$34),E108*(1-J$34)))+M108 -> 0
A109: =EDATE($C$8,34) -> 1035 | B109: =EDATE($C$8,35)-1 -> 1064 | C109: =ROW()-ROW($C$74) -> 35 | D109: =INT((C109-1)/12)+1 -> 3 | E109: =IF(C109>$C$10,0,$C$21*(1+$C$29)^(D109-1)) -> 0 | F109: =IF(C109>$C$10,0,IF(AND($C$38>0,A109>=$C$38,EOMONTH(A109,0)<=$C$39),E109*(1-$C$40),E109)) -> 0 | G109: =IF(C109>$C$10,0,IF(AND($C$38>0,A109>=$C$38,EOMONTH(A109,0)<=$C$39),-E109*$C$40,0)) -> 0 | H109: =IF(C109>$C$10,0,$C$24*(1+$C$30)^(D109-1)) -> 0 | I109: =IF(C109>$C$10,0,$C$22*(1+$C$31)^(D109-1)) -> 0 | J109: =IF(C109>$C$10,0,$C$23*(1+$C$32)^(D109-1)) -> 0 | K109: =IF(C109>$C$10,0,$C$25*(1+$C$33)^(D109-1)) -> 0 | L109: =IF(C109>$C$10,0,$C$26*(1+$C$34)^(D109-1)) -> 0 | M109: =H109+I109+J109+K109+L109 -> 0 | N109: =F109+M109 -> 0 | O109: =IF($C$7=0,0,N109/$C$7) -> 0 | P109: =MAX(SUM(N109:N198)+S109,0) -> 0 | Q109: =SUM(F109:F198) -> 0 | R109: =SUM(M109:M198) -> 0 | S109: =SUMPRODUCT(($C$55:$C$67)*($D$55:$D$67>=$A109)) -> 0 | T109: =IF(C109>$C$10,0,IF(AND($C$38>0,A109>=$C$38,EOMONTH(A109,0)<=$C$39),E109*(1-$C$40)*(1-G$15),E109*(1-G$15)))+M109 -> 0 | U109: =IF(C109>$C$10,0,IF(AND($C$38>0,A109>=$C$38,EOMONTH(A109,0)<=$C$39),E109*(1-$C$40)*(1-H$15),E109*(1-H$15)))+M109 -> 0 | V109: =IF(C109>$C$10,0,IF(AND($C$38>0,A109>=$C$38,EOMONTH(A109,0)<=$C$39),E109*(1-$C$40)*(1-I$15),E109*(1-I$15)))+M109 -> 0 | W109: =IF(C109>$C$10,0,IF(AND($C$38>0,A109>=$C$38,EOMONTH(A109,0)<=$C$39),E109*(1-$C$40)*(1-F$34),E109*(1-F$34)))+M109 -> 0 | X109: =IF(C109>$C$10,0,IF(AND($C$38>0,A109>=$C$38,EOMONTH(A109,0)<=$C$39),E109*(1-$C$40)*(1-G$34),E109*(1-G$34)))+M109 -> 0 | Y109: =IF(C109>$C$10,0,IF(AND($C$38>0,A109>=$C$38,EOMONTH(A109,0)<=$C$39),E109*(1-$C$40)*(1-H$34),E109*(1-H$34)))+M109 -> 0 | Z109: =IF(C109>$C$10,0,IF(AND($C$38>0,A109>=$C$38,EOMONTH(A109,0)<=$C$39),E109*(1-$C$40)*(1-I$34),E109*(1-I$34)))+M109 -> 0 | AA109: =IF(C109>$C$10,0,IF(AND($C$38>0,A109>=$C$38,EOMONTH(A109,0)<=$C$39),E109*(1-$C$40)*(1-J$34),E109*(1-J$34)))+M109 -> 0
...

Sheet Lease Schedule (populated)
A2: 1 | B2: Lease Obligation Analysis: *Name here*
A4: 2 | B4: *Property name here* | E4: Current Remaining Obligations:
E5: Total Remaining Obligation: | F5: =IFERROR(_xlfn.XLOOKUP($C$13,$C$75:$C$198,$P$75:$P$198,"",0),INDEX($P$75:$P$198,MATCH($C$13,$C$75:$C$198,0))) -> 2153223.6
B6: Lease Drivers | E6: Remaining Base Rent: | F6: =IFERROR(_xlfn.XLOOKUP($C$13,$C$75:$C$198,$Q$75:$Q$198,"",0),INDEX($Q$75:$Q$198,MATCH($C$13,$C$75:$C$198,0))) -> 1090337.9
A7: 3 | B7: Rentable SF | C7: 15000 | E7: Remaining Nets: | F7: =IFERROR(_xlfn.XLOOKUP($C$13,$C$75:$C$198,$R$75:$R$198,"",0),INDEX($R$75:$R$198,MATCH($C$13,$C$75:$C$198,0))) -> 1062885.8
A8: 4 | B8: Lease Commencement Date | C8: 43352 | E8: Remaining Other Charges: | F8: =IFERROR(_xlfn.XLOOKUP($C$13,$C$75:$C$198,$S$75:$S$198,"",0),INDEX($S$75:$S$198,MATCH($C$13,$C$75:$C$198,0))) -> 0
A9: 5 | B9: Rent Commencement Date | C9: 43352
A10: 6 | B10: Total Lease Term (Months): | C10: =DATEDIF(C8,C11,"M")+1 -> 121
A11: 7 | B11: Lease Expiration Date | C11: 47005 | E11: Exit & Renegotiation comparisons
A12: 8 | B12: Effective Date of Analysis: | C12: 44205 | E12: Discount Rate: | F12: 0.07
A13: 9 | B13: Effective Month #: | C13: =IFERROR(MATCH(C12,A75:A198,1),1) -> 29 | E13: SCENARIO COMPARISON - Renegotiation | F13: Effective Date of Analysis: | G13: =C12 -> 44205
B14: Months Remaining: | C14: =MAX(0,C10-C13+1) -> 93 | F14: Base Case | G14: Modest | H14: Material | I14: Significant
B15: Month # of effective date: | C15: =C13 -> 29 | E15: % Discount | F15: 0 | G15: 0.1 | H15: 0.2 | I15: 0.3
B16: Months until next base rent escalation: | C16: =12-MOD(C13-1,12) -> 8 | E16: Monthly Base Rent | F16: =INDEX(E$75:E$198,MATCH($C$13,C$75:C$198,0)) -> 10609 | G16: =$F$16*(1-G15) -> 9548.1 | H16: =$F$16*(1-H15) -> 8487.2 | I16: =$F$16*(1-I15) -> 7426.3
E17: Base/$PSF | F17: =IF($C$7=0,0,F16/$C$7) -> 0.70726667 | G17: =IF($C$7=0,0,G16/$C$7) -> 0.63654 | H17: =IF($C$7=0,0,H16/$C$7) -> 0.56581333 | I17: =IF($C$7=0,0,I16/$C$7) -> 0.49508667
B18: Monthly Rent Breakdown: | E18: Additional Rent (CAMs + Nets) | F18: =INDEX(M$75:M$198,MATCH($C$13,C$75:C$198,0)) -> 10258.25 | G18: =F18 -> 10258.25 | H18: =G18 -> 10258.25 | I18: =H18 -> 10258.25
B19: Date: | C19: =C12 -> 44205 | E19: Total Occupancy Cost | F19: =F16+F18 -> 20867.25 | G19: =G16+G18 -> 19806.35 | H19: =H16+H18 -> 18745.45 | I19: =I16+I18 -> 17684.55
B20: Month: | C20: =TEXT(C12,"MMMM") -> January | E20: Effective $/PSF | F20: =IF($C$7=0,0,F19/$C$7) -> 1.39115 | G20: =IF($C$7=0,0,G19/$C$7) -> 1.3204233 | H20: =IF($C$7=0,0,H19/$C$7) -> 1.2496967 | I20: =IF($C$7=0,0,I19/$C$7) -> 1.17897
A21: 10 | B21: Scheduled Base Rent | C21: 10000 | E21: Lease Obligation (FV) | F21: {=SUMPRODUCT(($C$75:$C$198>=IF($C$13=0,1,$C$13))*N$75:N$198)} -> 2153223.6 | G21: {=SUMPRODUCT(($C$75:$C$198>=IF($C$13=0,1,$C$13))*T$75:T$198)} -> 2044189.9 | H21: {=SUMPRODUCT(($C$75:$C$198>=IF($C$13=0,1,$C$13))*U$75:U$198)} -> 1935156.1 | I21: {=SUMPRODUCT(($C$75:$C$198>=IF($C$13=0,1,$C$13))*V$75:V$198)} -> 1826122.3
A22: 11 | B22: Insurance Year 1 Monthly Rate ($) | C22: 1875 | E22: Gross Savings vs Base ($) | F22: =0 -> 0 | G22: =F21-G21 -> 109033.79 | H22: =F21-H21 -> 218067.58 | I22: =F21-I21 -> 327101.36
A23: 12 | B23: Taxes Year 1 Monthly Rate ($) | C23: 3125 | E23: (+)Free Rent | G23: =G16*$F$23 -> 0 | H23: =H16*$F$23 -> 0 | I23: =I16*$F$23 -> 0
B24: CAMS Year 1 Monthly Rate ($) | C24: 3750 | E24: (+)TI | G24: =$F$24*$C$7 -> 0 | H24: =$F$24*$C$7 -> 0 | I24: =$F$24*$C$7 -> 0
B25: Security Year 1 Monthly Rate ($) | C25: 625 | E25: Total Savings From Base | F25: - | G25: =SUM(G22:G24) -> 109033.79 | H25: =SUM(H22:H24) -> 218067.58 | I25: =SUM(I22:I24) -> 327101.36
B26: Other Items Year 1 Monthly Rate ($) | C26: 312.5 | E26: NPV | F26: {=SUMPRODUCT(($C$75:$C$198>=IF($C$13=0,1,$C$13))*N$75:N$198/(1+$F$12/12)^($C$75:$C$198-IF($C$13=0,0,$C$13)+1))} -> 1638686.8 | G26: {=SUMPRODUCT(($C$75:$C$198>=IF($C$13=0,1,$C$13))*T$75:T$198/(1+$F$12/12)^($C$75:$C$198-IF($C$13=0,0,$C$13)+1))} -> 1555861 | H26: {=SUMPRODUCT(($C$75:$C$198>=IF($C$13=0,1,$C$13))*U$75:U$198/(1+$F$12/12)^($C$75:$C$198-IF($C$13=0,0,$C$13)+1))} -> 1473035.3 | I26: {=SUMPRODUCT(($C$75:$C$198>=IF($C$13=0,1,$C$13))*V$75:V$198/(1+$F$12/12)^($C$75:$C$198-IF($C$13=0,0,$C$13)+1))} -> 1390209.5
E27: NPV Savings vs Base | F27: - | G27: =F26-G26 -> 82825.762 | H27: =F26-H26 -> 165651.52 | I27: =F26-I26 -> 248477.29
B28: Escalations: | E28: % Savings vs Base | F28: - | G28: =IFERROR((F26-G26)/F26,0) -> 0.050543986 | H28: =IFERROR((F26-H26)/F26,0) -> 0.10108797 | I28: =IFERROR((F26-I26)/F26,0) -> 0.15163196
B29: Annual Base Rent Escalation Rate (%) | C29: 0.03 | E29: Full-Lease FV (all months, no date filter) | F29: =SUM(N75:N198) -> 2691076.8 | G29: =SUM(T75:T198) -> 2555948.5 | H29: =SUM(U75:U198) -> 2420820.2 | I29: =SUM(V75:V198) -> 2285691.9
B30: CAMS Annual Escalation Rate (%) | C30: 0.03 | E30: Cross-check: NNN after discount (orphan) | F30: =F18*(1-F15) -> 10258.25 | G30: =F18*(1-G15) -> 9232.425 | H30: =F18*(1-H15) -> 8206.6 | I30: =F18*(1-I15) -> 7180.775
B31: Insurance Annual Escalation Rate (%) | C31: 0.03
B32: Taxes Annual Escalation Rate (%) | C32: 0.03 | E32: SCENARIO COMPARISON - exit | F32: Effective Date of Analysis: | G32: =C12 -> 44205
B33: Security Annual Escalation Rate (%) | C33: 0.02 | F33: Full Obligation | G33: Mild Discount | H33: Moderate Discount | I33: Material Discount | J33: Significant Discount
B34: Other Items Annual Escalation Rate (%) | C34: 0.02 | E34: % Buyout | F34: 0 | G34: 0.2 | H34: 0.3 | I34: 0.4 | J34: 0.5
E35: Monthly Base Rent | F35: =F16 -> 10609 | G35: =F35 -> 10609 | H35: =F35 -> 10609 | I35: =F35 -> 10609 | J35: =F35 -> 10609
B36: Abatement: | E36: Base/$PSF | F36: =IF($C$7=0,0,F35/$C$7) -> 0.70726667 | G36: =IF($C$7=0,0,G35/$C$7) -> 0.70726667 | H36: =IF($C$7=0,0,H35/$C$7) -> 0.70726667 | I36: =IF($C$7=0,0,I35/$C$7) -> 0.70726667 | J36: =IF($C$7=0,0,J35/$C$7) -> 0.70726667
B37: Abatement duration (months) | C37: 1 | E37: Additional Rent (NNN) | F37: =F18 -> 10258.25 | G37: =F37 -> 10258.25 | H37: =F37 -> 10258.25 | I37: =F37 -> 10258.25
B38: Abatement start | C38: 43956 | E38: Total Occupancy Cost | F38: =F35+F37 -> 20867.25 | G38: =G35+G37 -> 20867.25 | H38: =H35+H37 -> 20867.25 | I38: =I35+I37 -> 20867.25
B39: Abatement end | C39: 44321 | E39: Effective $/PSF | F39: =IF($C$7=0,0,F38/$C$7) -> 1.39115 | G39: =IF($C$7=0,0,G38/$C$7) -> 1.39115 | H39: =IF($C$7=0,0,H38/$C$7) -> 1.39115 | I39: =IF($C$7=0,0,I38/$C$7) -> 1.39115
B40: Abatement % of full rent (dependent, don't change) | C40: =IF(C21=0,0,C41/C21) -> 0.3 | E40: Remaining Obligation (FV) | F40: =F21 -> 2153223.6 | G40: =F40*(1-G34) -> 1722578.9 | H40: =F40*(1-H34) -> 1507256.6 | I40: =F40*(1-I34) -> 1291934.2 | J40: =F40*(1-J34) -> 1076611.8
A41: 13 | B41: Abatement amt (dollars) | C41: 3000 | E41: Gross Savings vs Base ($) | F41: =0 -> 0 | G41: =F40-G40 -> 430644.73 | H41: =F40-H40 -> 645967.09 | I41: =F40-I40 -> 861289.46 | J41: =F40-J40 -> 1076611.8
A42: 14 | B42: *Additional abatement later in lease? (If yes, view the lease schedule abatement column and hardcode your values) | C42: yes | E42: (+)Free Rent | G42: =F35*$F$42 -> 0 | H42: =F35*$F$42 -> 0 | I42: =F35*$F$42 -> 0
E43: (+)TI | G43: =$F$24*$C$7 -> 0 | H43: =$F$24*$C$7 -> 0 | I43: =$F$24*$C$7 -> 0
A44: 15 | B44: Free Rent | E44: Total Savings From Base | F44: ="-" -> - | G44: =SUM(G41:G43) -> 430644.73 | H44: =SUM(H41:H43) -> 645967.09 | I44: =SUM(I41:I43) -> 861289.46 | J44: =SUM(J41:J43) -> 1076611.8
B45: Free Rent duration (months) | C45: 0 | E45: NPV | F45: =F26 -> 1638686.8 | G45: =F26*(1-G34) -> 1310949.4 | H45: =F26*(1-H34) -> 1147080.8 | I45: =F26*(1-I34) -> 983212.08 | J45: =F26*(1-J34) -> 819343.4
B46: Free Rent Start | C46: 43352 | E46: NPV Savings vs Base | F46: - | G46: =F45-G45 -> 327737.36 | H46: =F45-H45 -> 491606.04 | I46: =F45-I45 -> 655474.72 | J46: =F45-J45 -> 819343.4
B47: Free Rent End | C47: 43413 | E47: % Savings vs Base | F47: - | G47: =IFERROR((F45-G45)/F45,0) -> 0.2 | H47: =IFERROR((F45-H45)/F45,0) -> 0.3 | I47: =IFERROR((F45-I45)/F45,0) -> 0.4 | J47: =IFERROR((F45-J45)/F45,0) -> 0.5
B48: Free Rent assumption = 100%, if not.. Edit | C48: 1 | E48: Full-Lease FV (all months, no date filter) | F48: =SUM(N75:N198) -> 2691076.8 | G48: =SUM(T75:T198) -> 2555948.5 | H48: =SUM(U75:U198) -> 2420820.2 | I48: =SUM(V75:V198) -> 2285691.9 | J48: =SUM(AA75:AA198) -> 2015435.3
B49: *Additional free rent later in lease? (If yes, view the lease schedule free rent column and harcode your values) | C49: No | E49: Simplified cross-check: Full FV × (1-buyout%) | F49: =F29*(1-F34) -> 2691076.8 | G49: =F29*(1-G34) -> 2152861.5 | H49: =F29*(1-H34) -> 1883753.8 | I49: =F29*(1-I34) -> 1614646.1 | J49: =F29*(1-J34) -> 1345538.4
A53: 16 | B53: Non Recurring Charges:
B54: One-Time Charge | C54: Amount (USD) | D54: Incurred / Due Date
B55: Security Deposit | C55: 45000 | D55: 43352
B56: TIA — Initial Funding | C56: -150000 | D56: 43497
B57: TIA — Final Funding | C57: -75000 | D57: 43586
B58: Landlord Work Contribution | C58: -60000 | D58: 43717
B59: Moving Allowance | C59: -18000 | D59: 43383
B60: Base Rent Abatement (Months 1–4) | C60: -120000 | D60: 43352
B61: Lease Commission — Tenant's Broker (JLL) | C61: 103125 | D61: 43352
B62: Lease Commission — Landlord's Broker | C62: 51562.5 | D62: 43352
B63: Parking Stall Deposit (20 stalls) | C63: 12000 | D63: 43352
B64: HVAC Change-Order Charge | C64: 10200 | D64: 43536
B65: After-Hours Access Control Install | C65: 5040 | D65: 43625
B66: Roof Curb / Supplemental Mechanical Work | C66: 15300 | D66: 43748
B67: Letter of Credit (in lieu of cash deposit) | C67: 30000 | D67: 43891
B68: TOTAL | C68: =SUM(C55:C67) -> -150772.5
B73: Existing Lease | T73: Renegotiation and exit
A74: Period Start | B74: Period End | C74: Month # | D74: Year # | E74: Scheduled Base Rent | F74: Base Rent Applied | G74: Abatement | H74: CAMS | I74: Insurance | J74: Taxes | K74: Security | L74: Other Items | M74: Total NNN ① | N74: Total Monthly Obligation ② | O74: Effective $/SF | P74: Obligation Remaining | Q74: Base Rent Remaining | R74: NNN Remaining | S74: OTC Remaining | T74: Renego: Modest (10%) | U74: Renego: Material (20%) | V74: Renego: Significant (30%) | W74: Exit: Full Obligation (0%) | X74: Exit: Mild Discount (20%) | Y74: Exit: Moderate Discount (30%) | Z74: Exit: Material Discount (40%) | AA74: Exit: Significant Discount (50%)
A75: =$C$8 -> 43352 | B75: =EDATE($C$8,1)-1 -> 43381 | C75: =ROW()-ROW($C$74) -> 1 | D75: =INT((C75-1)/12)+1 -> 1 | E75: =IF(C75>$C$10,0,$C$21*(1+$C$29)^(D75-1)) -> 10000 | F75: =IF(C75>$C$10,0,IF(AND($C$38>0,A75>=$C$38,EOMONTH(A75,0)<=$C$39),E75*(1-$C$40),E75)) -> 10000 | G75: =IF(C75>$C$10,0,IF(AND($C$38>0,A75>=$C$38,EOMONTH(A75,0)<=$C$39),-E75*$C$40,0)) -> 0 | H75: =IF(C75>$C$10,0,$C$24*(1+$C$30)^(D75-1)) -> 3750 | I75: =IF(C75>$C$10,0,$C$22*(1+$C$31)^(D75-1)) -> 1875 | J75: =IF(C75>$C$10,0,$C$23*(1+$C$32)^(D75-1)) -> 3125 | K75: =IF(C75>$C$10,0,$C$25*(1+$C$33)^(D75-1)) -> 625 | L75: =IF(C75>$C$10,0,$C$26*(1+$C$34)^(D75-1)) -> 312.5 | M75: =H75+I75+J75+K75+L75 -> 9687.5 | N75: =F75+M75 -> 19687.5 | O75: =IF($C$7=0,0,N75/$C$7) -> 1.3125 | P75: =MAX(SUM(N75:N198)+S75,0) -> 2540304.3 | Q75: =SUM(F75:F198) -> 1351283.1 | R75: =SUM(M75:M198) -> 1339793.8 | S75: =SUMPRODUCT(($C$55:$C$67)*($D$55:$D$67>=$A75)) -> -150772.5 | T75: =IF(C75>$C$10,0,IF(AND($C$38>0,A75>=$C$38,EOMONTH(A75,0)<=$C$39),E75*(1-$C$40)*(1-G$15),E75*(1-G$15)))+M75 -> 18687.5 | U75: =IF(C75>$C$10,0,IF(AND($C$38>0,A75>=$C$38,EOMONTH(A75,0)<=$C$39),E75*(1-$C$40)*(1-H$15),E75*(1-H$15)))+M75 -> 17687.5 | V75: =IF(C75>$C$10,0,IF(AND($C$38>0,A75>=$C$38,EOMONTH(A75,0)<=$C$39),E75*(1-$C$40)*(1-I$15),E75*(1-I$15)))+M75 -> 16687.5 | W75: =IF(C75>$C$10,0,IF(AND($C$38>0,A75>=$C$38,EOMONTH(A75,0)<=$C$39),E75*(1-$C$40)*(1-F$34),E75*(1-F$34)))+M75 -> 19687.5 | X75: =IF(C75>$C$10,0,IF(AND($C$38>0,A75>=$C$38,EOMONTH(A75,0)<=$C$39),E75*(1-$C$40)*(1-G$34),E75*(1-G$34)))+M75 -> 17687.5 | Y75: =IF(C75>$C$10,0,IF(AND($C$38>0,A75>=$C$38,EOMONTH(A75,0)<=$C$39),E75*(1-$C$40)*(1-H$34),E75*(1-H$34)))+M75 -> 16687.5 | Z75: =IF(C75>$C$10,0,IF(AND($C$38>0,A75>=$C$38,EOMONTH(A75,0)<=$C$39),E75*(1-$C$40)*(1-I$34),E75*(1-I$34)))+M75 -> 15687.5 | AA75: =IF(C75>$C$10,0,IF(AND($C$38>0,A75>=$C$38,EOMONTH(A75,0)<=$C$39),E75*(1-$C$40)*(1-J$34),E75*(1-J$34)))+M75 -> 14687.5
A76: =EDATE($C$8,1) -> 43382 | B76: =EDATE($C$8,2)-1 -> 43412 | C76: =ROW()-ROW($C$74) -> 2 | D76: =INT((C76-1)/12)+1 -> 1 | E76: =IF(C76>$C$10,0,$C$21*(1+$C$29)^(D76-1)) -> 10000 | F76: =IF(C76>$C$10,0,IF(AND($C$38>0,A76>=$C$38,EOMONTH(A76,0)<=$C$39),E76*(1-$C$40),E76)) -> 10000 | G76: =IF(C76>$C$10,0,IF(AND($C$38>0,A76>=$C$38,EOMONTH(A76,0)<=$C$39),-E76*$C$40,0)) -> 0 | H76: =IF(C76>$C$10,0,$C$24*(1+$C$30)^(D76-1)) -> 3750 | I76: =IF(C76>$C$10,0,$C$22*(1+$C$31)^(D76-1)) -> 1875 | J76: =IF(C76>$C$10,0,$C$23*(1+$C$32)^(D76-1)) -> 3125 | K76: =IF(C76>$C$10,0,$C$25*(1+$C$33)^(D76-1)) -> 625 | L76: =IF(C76>$C$10,0,$C$26*(1+$C$34)^(D76-1)) -> 312.5 | M76: =H76+I76+J76+K76+L76 -> 9687.5 | N76: =F76+M76 -> 19687.5 | O76: =IF($C$7=0,0,N76/$C$7) -> 1.3125 | P76: =MAX(SUM(N76:N198)+S76,0) -> 2428929.3 | Q76: =SUM(F76:F198) -> 1341283.1 | R76: =SUM(M76:M198) -> 1330106.3 | S76: =SUMPRODUCT(($C$55:$C$67)*($D$55:$D$67>=$A76)) -> -242460 | T76: =IF(C76>$C$10,0,IF(AND($C$38>0,A76>=$C$38,EOMONTH(A76,0)<=$C$39),E76*(1-$C$40)*(1-G$15),E76*(1-G$15)))+M76 -> 18687.5 | U76: =IF(C76>$C$10,0,IF(AND($C$38>0,A76>=$C$38,EOMONTH(A76,0)<=$C$39),E76*(1-$C$40)*(1-H$15),E76*(1-H$15)))+M76 -> 17687.5 | V76: =IF(C76>$C$10,0,IF(AND($C$38>0,A76>=$C$38,EOMONTH(A76,0)<=$C$39),E76*(1-$C$40)*(1-I$15),E76*(1-I$15)))+M76 -> 16687.5 | W76: =IF(C76>$C$10,0,IF(AND($C$38>0,A76>=$C$38,EOMONTH(A76,0)<=$C$39),E76*(1-$C$40)*(1-F$34),E76*(1-F$34)))+M76 -> 19687.5 | X76: =IF(C76>$C$10,0,IF(AND($C$38>0,A76>=$C$38,EOMONTH(A76,0)<=$C$39),E76*(1-$C$40)*(1-G$34),E76*(1-G$34)))+M76 -> 17687.5 | Y76: =IF(C76>$C$10,0,IF(AND($C$38>0,A76>=$C$38,EOMONTH(A76,0)<=$C$39),E76*(1-$C$40)*(1-H$34),E76*(1-H$34)))+M76 -> 16687.5 | Z76: =IF(C76>$C$10,0,IF(AND($C$38>0,A76>=$C$38,EOMONTH(A76,0)<=$C$39),E76*(1-$C$40)*(1-I$34),E76*(1-I$34)))+M76 -> 15687.5 | AA76: =IF(C76>$C$10,0,IF(AND($C$38>0,A76>=$C$38,EOMONTH(A76,0)<=$C$39),E76*(1-$C$40)*(1-J$34),E76*(1-J$34)))+M76 -> 14687.5
A77: =EDATE($C$8,2) -> 43413 | B77: =EDATE($C$8,3)-1 -> 43442 | C77: =ROW()-ROW($C$74) -> 3 | D77: =INT((C77-1)/12)+1 -> 1 | E77: =IF(C77>$C$10,0,$C$21*(1+$C$29)^(D77-1)) -> 10000 | F77: =IF(C77>$C$10,0,IF(AND($C$38>0,A77>=$C$38,EOMONTH(A77,0)<=$C$39),E77*(1-$C$40),E77)) -> 10000 | G77: =IF(C77>$C$10,0,IF(AND($C$38>0,A77>=$C$38,EOMONTH(A77,0)<=$C$39),-E77*$C$40,0)) -> 0 | H77: =IF(C77>$C$10,0,$C$24*(1+$C$30)^(D77-1)) -> 3750 | I77: =IF(C77>$C$10,0,$C$22*(1+$C$31)^(D77-1)) -> 1875 | J77: =IF(C77>$C$10,0,$C$23*(1+$C$32)^(D77-1)) -> 3125 | K77: =IF(C77>$C$10,0,$C$25*(1+$C$33)^(D77-1)) -> 625 | L77: =IF(C77>$C$10,0,$C$26*(1+$C$34)^(D77-1)) -> 312.5 | M77: =H77+I77+J77+K77+L77 -> 9687.5 | N77: =F77+M77 -> 19687.5 | O77: =IF($C$7=0,0,N77/$C$7) -> 1.3125 | P77: =MAX(SUM(N77:N198)+S77,0) -> 2427241.8 | Q77: =SUM(F77:F198) -> 1331283.1 | R77: =SUM(M77:M198) -> 1320418.8 | S77: =SUMPRODUCT(($C$55:$C$67)*($D$55:$D$67>=$A77)) -> -224460 | T77: =IF(C77>$C$10,0,IF(AND($C$38>0,A77>=$C$38,EOMONTH(A77,0)<=$C$39),E77*(1-$C$40)*(1-G$15),E77*(1-G$15)))+M77 -> 18687.5 | U77: =IF(C77>$C$10,0,IF(AND($C$38>0,A77>=$C$38,EOMONTH(A77,0)<=$C$39),E77*(1-$C$40)*(1-H$15),E77*(1-H$15)))+M77 -> 17687.5 | V77: =IF(C77>$C$10,0,IF(AND($C$38>0,A77>=$C$38,EOMONTH(A77,0)<=$C$39),E77*(1-$C$40)*(1-I$15),E77*(1-I$15)))+M77 -> 16687.5 | W77: =IF(C77>$C$10,0,IF(AND($C$38>0,A77>=$C$38,EOMONTH(A77,0)<=$C$39),E77*(1-$C$40)*(1-F$34),E77*(1-F$34)))+M77 -> 19687.5 | X77: =IF(C77>$C$10,0,IF(AND($C$38>0,A77>=$C$38,EOMONTH(A77,0)<=$C$39),E77*(1-$C$40)*(1-G$34),E77*(1-G$34)))+M77 -> 17687.5 | Y77: =IF(C77>$C$10,0,IF(AND($C$38>0,A77>=$C$38,EOMONTH(A77,0)<=$C$39),E77*(1-$C$40)*(1-H$34),E77*(1-H$34)))+M77 -> 16687.5 | Z77: =IF(C77>$C$10,0,IF(AND($C$38>0,A77>=$C$38,EOMONTH(A77,0)<=$C$39),E77*(1-$C$40)*(1-I$34),E77*(1-I$34)))+M77 -> 15687.5 | AA77: =IF(C77>$C$10,0,IF(AND($C$38>0,A77>=$C$38,EOMONTH(A77,0)<=$C$39),E77*(1-$C$40)*(1-J$34),E77*(1-J$34)))+M77 -> 14687.5
A78: =EDATE($C$8,3) -> 43443 | B78: =EDATE($C$8,4)-1 -> 43473 | C78: =ROW()-ROW($C$74) -> 4 | D78: =INT((C78-1)/12)+1 -> 1 | E78: =IF(C78>$C$10,0,$C$21*(1+$C$29)^(D78-1)) -> 10000 | F78: =IF(C78>$C$10,0,IF(AND($C$38>0,A78>=$C$38,EOMONTH(A78,0)<=$C$39),E78*(1-$C$40),E78)) -> 10000 | G78: =IF(C78>$C$10,0,IF(AND($C$38>0,A78>=$C$38,EOMONTH(A78,0)<=$C$39),-E78*$C$40,0)) -> 0 | H78: =IF(C78>$C$10,0,$C$24*(1+$C$30)^(D78-1)) -> 3750 | I78: =IF(C78>$C$10,0,$C$22*(1+$C$31)^(D78-1)) -> 1875 | J78: =IF(C78>$C$10,0,$C$23*(1+$C$32)^(D78-1)) -> 3125 | K78: =IF(C78>$C$10,0,$C$25*(1+$C$33)^(D78-1)) -> 625 | L78: =IF(C78>$C$10,0,$C$26*(1+$C$34)^(D78-1)) -> 312.5 | M78: =H78+I78+J78+K78+L78 -> 9687.5 | N78: =F78+M78 -> 19687.5 | O78: =IF($C$7=0,0,N78/$C$7) -> 1.3125 | P78: =MAX(SUM(N78:N198)+S78,0) -> 2407554.3 | Q78: =SUM(F78:F198) -> 1321283.1 | R78: =SUM(M78:M198) -> 1310731.3 | S78: =SUMPRODUCT(($C$55:$C$67)*($D$55:$D$67>=$A78)) -> -224460 | T78: =IF(C78>$C$10,0,IF(AND($C$38>0,A78>=$C$38,EOMONTH(A78,0)<=$C$39),E78*(1-$C$40)*(1-G$15),E78*(1-G$15)))+M78 -> 18687.5 | U78: =IF(C78>$C$10,0,IF(AND($C$38>0,A78>=$C$38,EOMONTH(A78,0)<=$C$39),E78*(1-$C$40)*(1-H$15),E78*(1-H$15)))+M78 -> 17687.5 | V78: =IF(C78>$C$10,0,IF(AND($C$38>0,A78>=$C$38,EOMONTH(A78,0)<=$C$39),E78*(1-$C$40)*(1-I$15),E78*(1-I$15)))+M78 -> 16687.5 | W78: =IF(C78>$C$10,0,IF(AND($C$38>0,A78>=$C$38,EOMONTH(A78,0)<=$C$39),E78*(1-$C$40)*(1-F$34),E78*(1-F$34)))+M78 -> 19687.5 | X78: =IF(C78>$C$10,0,IF(AND($C$38>0,A78>=$C$38,EOMONTH(A78,0)<=$C$39),E78*(1-$C$40)*(1-G$34),E78*(1-G$34)))+M78 -> 17687.5 | Y78: =IF(C78>$C$10,0,IF(AND($C$38>0,A78>=$C$38,EOMONTH(A78,0)<=$C$39),E78*(1-$C$40)*(1-H$34),E78*(1-H$34)))+M78 -> 16687.5 | Z78: =IF(C78>$C$10,0,IF(AND($C$38>0,A78>=$C$38,EOMONTH(A78,0)<=$C$39),E78*(1-$C$40)*(1-I$34),E78*(1-I$34)))+M78 -> 15687.5 | AA78: =IF(C78>$C$10,0,IF(AND($C$38>0,A78>=$C$38,EOMONTH(A78,0)<=$C$39),E78*(1-$C$40)*(1-J$34),E78*(1-J$34)))+M78 -> 14687.5
A79: =EDATE($C$8,4) -> 43474 | B79: =EDATE($C$8,5)-1 -> 43504 | C79: =ROW()-ROW($C$74) -> 5 | D79: =INT((C79-1)/12)+1 -> 1 | E79: =IF(C79>$C$10,0,$C$21*(1+$C$29)^(D79-1)) -> 10000 | F79: =IF(C79>$C$10,0,IF(AND($C$38>0,A79>=$C$38,EOMONTH(A79,0)<=$C$39),E79*(1-$C$40),E79)) -> 10000 | G79: =IF(C79>$C$10,0,IF(AND($C$38>0,A79>=$C$38,EOMONTH(A79,0)<=$C$39),-E79*$C$40,0)) -> 0 | H79: =IF(C79>$C$10,0,$C$24*(1+$C$30)^(D79-1)) -> 3750 | I79: =IF(C79>$C$10,0,$C$22*(1+$C$31)^(D79-1)) -> 1875 | J79: =IF(C79>$C$10,0,$C$23*(1+$C$32)^(D79-1)) -> 3125 | K79: =IF(C79>$C$10,0,$C$25*(1+$C$33)^(D79-1)) -> 625 | L79: =IF(C79>$C$10,0,$C$26*(1+$C$34)^(D79-1)) -> 312.5 | M79: =H79+I79+J79+K79+L79 -> 9687.5 | N79: =F79+M79 -> 19687.5 | O79: =IF($C$7=0,0,N79/$C$7) -> 1.3125 | P79: =MAX(SUM(N79:N198)+S79,0) -> 2387866.8 | Q79: =SUM(F79:F198) -> 1311283.1 | R79: =SUM(M79:M198) -> 1301043.8 | S79: =SUMPRODUCT(($C$55:$C$67)*($D$55:$D$67>=$A79)) -> -224460 | T79: =IF(C79>$C$10,0,IF(AND($C$38>0,A79>=$C$38,EOMONTH(A79,0)<=$C$39),E79*(1-$C$40)*(1-G$15),E79*(1-G$15)))+M79 -> 18687.5 | U79: =IF(C79>$C$10,0,IF(AND($C$38>0,A79>=$C$38,EOMONTH(A79,0)<=$C$39),E79*(1-$C$40)*(1-H$15),E79*(1-H$15)))+M79 -> 17687.5 | V79: =IF(C79>$C$10,0,IF(AND($C$38>0,A79>=$C$38,EOMONTH(A79,0)<=$C$39),E79*(1-$C$40)*(1-I$15),E79*(1-I$15)))+M79 -> 16687.5 | W79: =IF(C79>$C$10,0,IF(AND($C$38>0,A79>=$C$38,EOMONTH(A79,0)<=$C$39),E79*(1-$C$40)*(1-F$34),E79*(1-F$34)))+M79 -> 19687.5 | X79: =IF(C79>$C$10,0,IF(AND($C$38>0,A79>=$C$38,EOMONTH(A79,0)<=$C$39),E79*(1-$C$40)*(1-G$34),E79*(1-G$34)))+M79 -> 17687.5 | Y79: =IF(C79>$C$10,0,IF(AND($C$38>0,A79>=$C$38,EOMONTH(A79,0)<=$C$39),E79*(1-$C$40)*(1-H$34),E79*(1-H$34)))+M79 -> 16687.5 | Z79: =IF(C79>$C$10,0,IF(AND($C$38>0,A79>=$C$38,EOMONTH(A79,0)<=$C$39),E79*(1-$C$40)*(1-I$34),E79*(1-I$34)))+M79 -> 15687.5 | AA79: =IF(C79>$C$10,0,IF(AND($C$38>0,A79>=$C$38,EOMONTH(A79,0)<=$C$39),E79*(1-$C$40)*(1-J$34),E79*(1-J$34)))+M79 -> 14687.5
A80: =EDATE($C$8,5) -> 43505 | B80: =EDATE($C$8,6)-1 -> 43532 | C80: =ROW()-ROW($C$74) -> 6 | D80: =INT((C80-1)/12)+1 -> 1 | E80: =IF(C80>$C$10,0,$C$21*(1+$C$29)^(D80-1)) -> 10000 | F80: =IF(C80>$C$10,0,IF(AND($C$38>0,A80>=$C$38,EOMONTH(A80,0)<=$C$39),E80*(1-$C$40),E80)) -> 10000 | G80: =IF(C80>$C$10,0,IF(AND($C$38>0,A80>=$C$38,EOMONTH(A80,0)<=$C$39),-E80*$C$40,0)) -> 0 | H80: =IF(C80>$C$10,0,$C$24*(1+$C$30)^(D80-1)) -> 3750 | I80: =IF(C80>$C$10,0,$C$22*(1+$C$31)^(D80-1)) -> 1875 | J80: =IF(C80>$C$10,0,$C$23*(1+$C$32)^(D80-1)) -> 3125 | K80: =IF(C80>$C$10,0,$C$25*(1+$C$33)^(D80-1)) -> 625 | L80: =IF(C80>$C$10,0,$C$26*(1+$C$34)^(D80-1)) -> 312.5 | M80: =H80+I80+J80+K80+L80 -> 9687.5 | N80: =F80+M80 -> 19687.5 | O80: =IF($C$7=0,0,N80/$C$7) -> 1.3125 | P80: =MAX(SUM(N80:N198)+S80,0) -> 2518179.3 | Q80: =SUM(F80:F198) -> 1301283.1 | R80: =SUM(M80:M198) -> 1291356.3 | S80: =SUMPRODUCT(($C$55:$C$67)*($D$55:$D$67>=$A80)) -> -74460 | T80: =IF(C80>$C$10,0,IF(AND($C$38>0,A80>=$C$38,EOMONTH(A80,0)<=$C$39),E80*(1-$C$40)*(1-G$15),E80*(1-G$15)))+M80 -> 18687.5 | U80: =IF(C80>$C$10,0,IF(AND($C$38>0,A80>=$C$38,EOMONTH(A80,0)<=$C$39),E80*(1-$C$40)*(1-H$15),E80*(1-H$15)))+M80 -> 17687.5 | V80: =IF(C80>$C$10,0,IF(AND($C$38>0,A80>=$C$38,EOMONTH(A80,0)<=$C$39),E80*(1-$C$40)*(1-I$15),E80*(1-I$15)))+M80 -> 16687.5 | W80: =IF(C80>$C$10,0,IF(AND($C$38>0,A80>=$C$38,EOMONTH(A80,0)<=$C$39),E80*(1-$C$40)*(1-F$34),E80*(1-F$34)))+M80 -> 19687.5 | X80: =IF(C80>$C$10,0,IF(AND($C$38>0,A80>=$C$38,EOMONTH(A80,0)<=$C$39),E80*(1-$C$40)*(1-G$34),E80*(1-G$34)))+M80 -> 17687.5 | Y80: =IF(C80>$C$10,0,IF(AND($C$38>0,A80>=$C$38,EOMONTH(A80,0)<=$C$39),E80*(1-$C$40)*(1-H$34),E80*(1-H$34)))+M80 -> 16687.5 | Z80: =IF(C80>$C$10,0,IF(AND($C$38>0,A80>=$C$38,EOMONTH(A80,0)<=$C$39),E80*(1-$C$40)*(1-I$34),E80*(1-I$34)))+M80 -> 15687.5 | AA80: =IF(C80>$C$10,0,IF(AND($C$38>0,A80>=$C$38,EOMONTH(A80,0)<=$C$39),E80*(1-$C$40)*(1-J$34),E80*(1-J$34)))+M80 -> 14687.5
A81: =EDATE($C$8,6) -> 43533 | B81: =EDATE($C$8,7)-1 -> 43563 | C81: =ROW()-ROW($C$74) -> 7 | D81: =INT((C81-1)/12)+1 -> 1 | E81: =IF(C81>$C$10,0,$C$21*(1+$C$29)^(D81-1)) -> 10000 | F81: =IF(C81>$C$10,0,IF(AND($C$38>0,A81>=$C$38,EOMONTH(A81,0)<=$C$39),E81*(1-$C$40),E81)) -> 10000 | G81: =IF(C81>$C$10,0,IF(AND($C$38>0,A81>=$C$38,EOMONTH(A81,0)<=$C$39),-E81*$C$40,0)) -> 0 | H81: =IF(C81>$C$10,0,$C$24*(1+$C$30)^(D81-1)) -> 3750 | I81: =IF(C81>$C$10,0,$C$22*(1+$C$31)^(D81-1)) -> 1875 | J81: =IF(C81>$C$10,0,$C$23*(1+$C$32)^(D81-1)) -> 3125 | K81: =IF(C81>$C$10,0,$C$25*(1+$C$33)^(D81-1)) -> 625 | L81: =IF(C81>$C$10,0,$C$26*(1+$C$34)^(D81-1)) -> 312.5 | M81: =H81+I81+J81+K81+L81 -> 9687.5 | N81: =F81+M81 -> 19687.5 | O81: =IF($C$7=0,0,N81/$C$7) -> 1.3125 | P81: =MAX(SUM(N81:N198)+S81,0) -> 2498491.8 | Q81: =SUM(F81:F198) -> 1291283.1 | R81: =SUM(M81:M198) -> 1281668.8 | S81: =SUMPRODUCT(($C$55:$C$67)*($D$55:$D$67>=$A81)) -> -74460 | T81: =IF(C81>$C$10,0,IF(AND($C$38>0,A81>=$C$38,EOMONTH(A81,0)<=$C$39),E81*(1-$C$40)*(1-G$15),E81*(1-G$15)))+M81 -> 18687.5 | U81: =IF(C81>$C$10,0,IF(AND($C$38>0,A81>=$C$38,EOMONTH(A81,0)<=$C$39),E81*(1-$C$40)*(1-H$15),E81*(1-H$15)))+M81 -> 17687.5 | V81: =IF(C81>$C$10,0,IF(AND($C$38>0,A81>=$C$38,EOMONTH(A81,0)<=$C$39),E81*(1-$C$40)*(1-I$15),E81*(1-I$15)))+M81 -> 16687.5 | W81: =IF(C81>$C$10,0,IF(AND($C$38>0,A81>=$C$38,EOMONTH(A81,0)<=$C$39),E81*(1-$C$40)*(1-F$34),E81*(1-F$34)))+M81 -> 19687.5 | X81: =IF(C81>$C$10,0,IF(AND($C$38>0,A81>=$C$38,EOMONTH(A81,0)<=$C$39),E81*(1-$C$40)*(1-G$34),E81*(1-G$34)))+M81 -> 17687.5 | Y81: =IF(C81>$C$10,0,IF(AND($C$38>0,A81>=$C$38,EOMONTH(A81,0)<=$C$39),E81*(1-$C$40)*(1-H$34),E81*(1-H$34)))+M81 -> 16687.5 | Z81: =IF(C81>$C$10,0,IF(AND($C$38>0,A81>=$C$38,EOMONTH(A81,0)<=$C$39),E81*(1-$C$40)*(1-I$34),E81*(1-I$34)))+M81 -> 15687.5 | AA81: =IF(C81>$C$10,0,IF(AND($C$38>0,A81>=$C$38,EOMONTH(A81,0)<=$C$39),E81*(1-$C$40)*(1-J$34),E81*(1-J$34)))+M81 -> 14687.5
A82: =EDATE($C$8,7) -> 43564 | B82: =EDATE($C$8,8)-1 -> 43593 | C82: =ROW()-ROW($C$74) -> 8 | D82: =INT((C82-1)/12)+1 -> 1 | E82: =IF(C82>$C$10,0,$C$21*(1+$C$29)^(D82-1)) -> 10000 | F82: =IF(C82>$C$10,0,IF(AND($C$38>0,A82>=$C$38,EOMONTH(A82,0)<=$C$39),E82*(1-$C$40),E82)) -> 10000 | G82: =IF(C82>$C$10,0,IF(AND($C$38>0,A82>=$C$38,EOMONTH(A82,0)<=$C$39),-E82*$C$40,0)) -> 0 | H82: =IF(C82>$C$10,0,$C$24*(1+$C$30)^(D82-1)) -> 3750 | I82: =IF(C82>$C$10,0,$C$22*(1+$C$31)^(D82-1)) -> 1875 | J82: =IF(C82>$C$10,0,$C$23*(1+$C$32)^(D82-1)) -> 3125 | K82: =IF(C82>$C$10,0,$C$25*(1+$C$33)^(D82-1)) -> 625 | L82: =IF(C82>$C$10,0,$C$26*(1+$C$34)^(D82-1)) -> 312.5 | M82: =H82+I82+J82+K82+L82 -> 9687.5 | N82: =F82+M82 -> 19687.5 | O82: =IF($C$7=0,0,N82/$C$7) -> 1.3125 | P82: =MAX(SUM(N82:N198)+S82,0) -> 2468604.3 | Q82: =SUM(F82:F198) -> 1281283.1 | R82: =SUM(M82:M198) -> 1271981.3 | S82: =SUMPRODUCT(($C$55:$C$67)*($D$55:$D$67>=$A82)) -> -84660 | T82: =IF(C82>$C$10,0,IF(AND($C$38>0,A82>=$C$38,EOMONTH(A82,0)<=$C$39),E82*(1-$C$40)*(1-G$15),E82*(1-G$15)))+M82 -> 18687.5 | U82: =IF(C82>$C$10,0,IF(AND($C$38>0,A82>=$C$38,EOMONTH(A82,0)<=$C$39),E82*(1-$C$40)*(1-H$15),E82*(1-H$15)))+M82 -> 17687.5 | V82: =IF(C82>$C$10,0,IF(AND($C$38>0,A82>=$C$38,EOMONTH(A82,0)<=$C$39),E82*(1-$C$40)*(1-I$15),E82*(1-I$15)))+M82 -> 16687.5 | W82: =IF(C82>$C$10,0,IF(AND($C$38>0,A82>=$C$38,EOMONTH(A82,0)<=$C$39),E82*(1-$C$40)*(1-F$34),E82*(1-F$34)))+M82 -> 19687.5 | X82: =IF(C82>$C$10,0,IF(AND($C$38>0,A82>=$C$38,EOMONTH(A82,0)<=$C$39),E82*(1-$C$40)*(1-G$34),E82*(1-G$34)))+M82 -> 17687.5 | Y82: =IF(C82>$C$10,0,IF(AND($C$38>0,A82>=$C$38,EOMONTH(A82,0)<=$C$39),E82*(1-$C$40)*(1-H$34),E82*(1-H$34)))+M82 -> 16687.5 | Z82: =IF(C82>$C$10,0,IF(AND($C$38>0,A82>=$C$38,EOMONTH(A82,0)<=$C$39),E82*(1-$C$40)*(1-I$34),E82*(1-I$34)))+M82 -> 15687.5 | AA82: =IF(C82>$C$10,0,IF(AND($C$38>0,A82>=$C$38,EOMONTH(A82,0)<=$C$39),E82*(1-$C$40)*(1-J$34),E82*(1-J$34)))+M82 -> 14687.5
A83: =EDATE($C$8,8) -> 43594 | B83: =EDATE($C$8,9)-1 -> 43624 | C83: =ROW()-ROW($C$74) -> 9 | D83: =INT((C83-1)/12)+1 -> 1 | E83: =IF(C83>$C$10,0,$C$21*(1+$C$29)^(D83-1)) -> 10000 | F83: =IF(C83>$C$10,0,IF(AND($C$38>0,A83>=$C$38,EOMONTH(A83,0)<=$C$39),E83*(1-$C$40),E83)) -> 10000 | G83: =IF(C83>$C$10,0,IF(AND($C$38>0,A83>=$C$38,EOMONTH(A83,0)<=$C$39),-E83*$C$40,0)) -> 0 | H83: =IF(C83>$C$10,0,$C$24*(1+$C$30)^(D83-1)) -> 3750 | I83: =IF(C83>$C$10,0,$C$22*(1+$C$31)^(D83-1)) -> 1875 | J83: =IF(C83>$C$10,0,$C$23*(1+$C$32)^(D83-1)) -> 3125 | K83: =IF(C83>$C$10,0,$C$25*(1+$C$33)^(D83-1)) -> 625 | L83: =IF(C83>$C$10,0,$C$26*(1+$C$34)^(D83-1)) -> 312.5 | M83: =H83+I83+J83+K83+L83 -> 9687.5 | N83: =F83+M83 -> 19687.5 | O83: =IF($C$7=0,0,N83/$C$7) -> 1.3125 | P83: =MAX(SUM(N83:N198)+S83,0) -> 2523916.8 | Q83: =SUM(F83:F198) -> 1271283.1 | R83: =SUM(M83:M198) -> 1262293.8 | S83: =SUMPRODUCT(($C$55:$C$67)*($D$55:$D$67>=$A83)) -> -9660 | T83: =IF(C83>$C$10,0,IF(AND($C$38>0,A83>=$C$38,EOMONTH(A83,0)<=$C$39),E83*(1-$C$40)*(1-G$15),E83*(1-G$15)))+M83 -> 18687.5 | U83: =IF(C83>$C$10,0,IF(AND($C$38>0,A83>=$C$38,EOMONTH(A83,0)<=$C$39),E83*(1-$C$40)*(1-H$15),E83*(1-H$15)))+M83 -> 17687.5 | V83: =IF(C83>$C$10,0,IF(AND($C$38>0,A83>=$C$38,EOMONTH(A83,0)<=$C$39),E83*(1-$C$40)*(1-I$15),E83*(1-I$15)))+M83 -> 16687.5 | W83: =IF(C83>$C$10,0,IF(AND($C$38>0,A83>=$C$38,EOMONTH(A83,0)<=$C$39),E83*(1-$C$40)*(1-F$34),E83*(1-F$34)))+M83 -> 19687.5 | X83: =IF(C83>$C$10,0,IF(AND($C$38>0,A83>=$C$38,EOMONTH(A83,0)<=$C$39),E83*(1-$C$40)*(1-G$34),E83*(1-G$34)))+M83 -> 17687.5 | Y83: =IF(C83>$C$10,0,IF(AND($C$38>0,A83>=$C$38,EOMONTH(A83,0)<=$C$39),E83*(1-$C$40)*(1-H$34),E83*(1-H$34)))+M83 -> 16687.5 | Z83: =IF(C83>$C$10,0,IF(AND($C$38>0,A83>=$C$38,EOMONTH(A83,0)<=$C$39),E83*(1-$C$40)*(1-I$34),E83*(1-I$34)))+M83 -> 15687.5 | AA83: =IF(C83>$C$10,0,IF(AND($C$38>0,A83>=$C$38,EOMONTH(A83,0)<=$C$39),E83*(1-$C$40)*(1-J$34),E83*(1-J$34)))+M83 -> 14687.5
A84: =EDATE($C$8,9) -> 43625 | B84: =EDATE($C$8,10)-1 -> 43654 | C84: =ROW()-ROW($C$74) -> 10 | D84: =INT((C84-1)/12)+1 -> 1 | E84: =IF(C84>$C$10,0,$C$21*(1+$C$29)^(D84-1)) -> 10000 | F84: =IF(C84>$C$10,0,IF(AND($C$38>0,A84>=$C$38,EOMONTH(A84,0)<=$C$39),E84*(1-$C$40),E84)) -> 10000 | G84: =IF(C84>$C$10,0,IF(AND($C$38>0,A84>=$C$38,EOMONTH(A84,0)<=$C$39),-E84*$C$40,0)) -> 0 | H84: =IF(C84>$C$10,0,$C$24*(1+$C$30)^(D84-1)) -> 3750 | I84: =IF(C84>$C$10,0,$C$22*(1+$C$31)^(D84-1)) -> 1875 | J84: =IF(C84>$C$10,0,$C$23*(1+$C$32)^(D84-1)) -> 3125 | K84: =IF(C84>$C$10,0,$C$25*(1+$C$33)^(D84-1)) -> 625 | L84: =IF(C84>$C$10,0,$C$26*(1+$C$34)^(D84-1)) -> 312.5 | M84: =H84+I84+J84+K84+L84 -> 9687.5 | N84: =F84+M84 -> 19687.5 | O84: =IF($C$7=0,0,N84/$C$7) -> 1.3125 | P84: =MAX(SUM(N84:N198)+S84,0) -> 2504229.3 | Q84: =SUM(F84:F198) -> 1261283.1 | R84: =SUM(M84:M198) -> 1252606.3 | S84: =SUMPRODUCT(($C$55:$C$67)*($D$55:$D$67>=$A84)) -> -9660 | T84: =IF(C84>$C$10,0,IF(AND($C$38>0,A84>=$C$38,EOMONTH(A84,0)<=$C$39),E84*(1-$C$40)*(1-G$15),E84*(1-G$15)))+M84 -> 18687.5 | U84: =IF(C84>$C$10,0,IF(AND($C$38>0,A84>=$C$38,EOMONTH(A84,0)<=$C$39),E84*(1-$C$40)*(1-H$15),E84*(1-H$15)))+M84 -> 17687.5 | V84: =IF(C84>$C$10,0,IF(AND($C$38>0,A84>=$C$38,EOMONTH(A84,0)<=$C$39),E84*(1-$C$40)*(1-I$15),E84*(1-I$15)))+M84 -> 16687.5 | W84: =IF(C84>$C$10,0,IF(AND($C$38>0,A84>=$C$38,EOMONTH(A84,0)<=$C$39),E84*(1-$C$40)*(1-F$34),E84*(1-F$34)))+M84 -> 19687.5 | X84: =IF(C84>$C$10,0,IF(AND($C$38>0,A84>=$C$38,EOMONTH(A84,0)<=$C$39),E84*(1-$C$40)*(1-G$34),E84*(1-G$34)))+M84 -> 17687.5 | Y84: =IF(C84>$C$10,0,IF(AND($C$38>0,A84>=$C$38,EOMONTH(A84,0)<=$C$39),E84*(1-$C$40)*(1-H$34),E84*(1-H$34)))+M84 -> 16687.5 | Z84: =IF(C84>$C$10,0,IF(AND($C$38>0,A84>=$C$38,EOMONTH(A84,0)<=$C$39),E84*(1-$C$40)*(1-I$34),E84*(1-I$34)))+M84 -> 15687.5 | AA84: =IF(C84>$C$10,0,IF(AND($C$38>0,A84>=$C$38,EOMONTH(A84,0)<=$C$39),E84*(1-$C$40)*(1-J$34),E84*(1-J$34)))+M84 -> 14687.5
A85: =EDATE($C$8,10) -> 43655 | B85: =EDATE($C$8,11)-1 -> 43685 | C85: =ROW()-ROW($C$74) -> 11 | D85: =INT((C85-1)/12)+1 -> 1 | E85: =IF(C85>$C$10,0,$C$21*(1+$C$29)^(D85-1)) -> 10000 | F85: =IF(C85>$C$10,0,IF(AND($C$38>0,A85>=$C$38,EOMONTH(A85,0)<=$C$39),E85*(1-$C$40),E85)) -> 10000 | G85: =IF(C85>$C$10,0,IF(AND($C$38>0,A85>=$C$38,EOMONTH(A85,0)<=$C$39),-E85*$C$40,0)) -> 0 | H85: =IF(C85>$C$10,0,$C$24*(1+$C$30)^(D85-1)) -> 3750 | I85: =IF(C85>$C$10,0,$C$22*(1+$C$31)^(D85-1)) -> 1875 | J85: =IF(C85>$C$10,0,$C$23*(1+$C$32)^(D85-1)) -> 3125 | K85: =IF(C85>$C$10,0,$C$25*(1+$C$33)^(D85-1)) -> 625 | L85: =IF(C85>$C$10,0,$C$26*(1+$C$34)^(D85-1)) -> 312.5 | M85: =H85+I85+J85+K85+L85 -> 9687.5 | N85: =F85+M85 -> 19687.5 | O85: =IF($C$7=0,0,N85/$C$7) -> 1.3125 | P85: =MAX(SUM(N85:N198)+S85,0) -> 2479501.8 | Q85: =SUM(F85:F198) -> 1251283.1 | R85: =SUM(M85:M198) -> 1242918.8 | S85: =SUMPRODUCT(($C$55:$C$67)*($D$55:$D$67>=$A85)) -> -14700 | T85: =IF(C85>$C$10,0,IF(AND($C$38>0,A85>=$C$38,EOMONTH(A85,0)<=$C$39),E85*(1-$C$40)*(1-G$15),E85*(1-G$15)))+M85 -> 18687.5 | U85: =IF(C85>$C$10,0,IF(AND($C$38>0,A85>=$C$38,EOMONTH(A85,0)<=$C$39),E85*(1-$C$40)*(1-H$15),E85*(1-H$15)))+M85 -> 17687.5 | V85: =IF(C85>$C$10,0,IF(AND($C$38>0,A85>=$C$38,EOMONTH(A85,0)<=$C$39),E85*(1-$C$40)*(1-I$15),E85*(1-I$15)))+M85 -> 16687.5 | W85: =IF(C85>$C$10,0,IF(AND($C$38>0,A85>=$C$38,EOMONTH(A85,0)<=$C$39),E85*(1-$C$40)*(1-F$34),E85*(1-F$34)))+M85 -> 19687.5 | X85: =IF(C85>$C$10,0,IF(AND($C$38>0,A85>=$C$38,EOMONTH(A85,0)<=$C$39),E85*(1-$C$40)*(1-G$34),E85*(1-G$34)))+M85 -> 17687.5 | Y85: =IF(C85>$C$10,0,IF(AND($C$38>0,A85>=$C$38,EOMONTH(A85,0)<=$C$39),E85*(1-$C$40)*(1-H$34),E85*(1-H$34)))+M85 -> 16687.5 | Z85: =IF(C85>$C$10,0,IF(AND($C$38>0,A85>=$C$38,EOMONTH(A85,0)<=$C$39),E85*(1-$C$40)*(1-I$34),E85*(1-I$34)))+M85 -> 15687.5 | AA85: =IF(C85>$C$10,0,IF(AND($C$38>0,A85>=$C$38,EOMONTH(A85,0)<=$C$39),E85*(1-$C$40)*(1-J$34),E85*(1-J$34)))+M85 -> 14687.5
A86: =EDATE($C$8,11) -> 43686 | B86: =EDATE($C$8,12)-1 -> 43716 | C86: =ROW()-ROW($C$74) -> 12 | D86: =INT((C86-1)/12)+1 -> 1 | E86: =IF(C86>$C$10,0,$C$21*(1+$C$29)^(D86-1)) -> 10000 | F86: =IF(C86>$C$10,0,IF(AND($C$38>0,A86>=$C$38,EOMONTH(A86,0)<=$C$39),E86*(1-$C$40),E86)) -> 10000 | G86: =IF(C86>$C$10,0,IF(AND($C$38>0,A86>=$C$38,EOMONTH(A86,0)<=$C$39),-E86*$C$40,0)) -> 0 | H86: =IF(C86>$C$10,0,$C$24*(1+$C$30)^(D86-1)) -> 3750 | I86: =IF(C86>$C$10,0,$C$22*(1+$C$31)^(D86-1)) -> 1875 | J86: =IF(C86>$C$10,0,$C$23*(1+$C$32)^(D86-1)) -> 3125 | K86: =IF(C86>$C$10,0,$C$25*(1+$C$33)^(D86-1)) -> 625 | L86: =IF(C86>$C$10,0,$C$26*(1+$C$34)^(D86-1)) -> 312.5 | M86: =H86+I86+J86+K86+L86 -> 9687.5 | N86: =F86+M86 -> 19687.5 | O86: =IF($C$7=0,0,N86/$C$7) -> 1.3125 | P86: =MAX(SUM(N86:N198)+S86,0) -> 2459814.3 | Q86: =SUM(F86:F198) -> 1241283.1 | R86: =SUM(M86:M198) -> 1233231.3 | S86: =SUMPRODUCT(($C$55:$C$67)*($D$55:$D$67>=$A86)) -> -14700 | T86: =IF(C86>$C$10,0,IF(AND($C$38>0,A86>=$C$38,EOMONTH(A86,0)<=$C$39),E86*(1-$C$40)*(1-G$15),E86*(1-G$15)))+M86 -> 18687.5 | U86: =IF(C86>$C$10,0,IF(AND($C$38>0,A86>=$C$38,EOMONTH(A86,0)<=$C$39),E86*(1-$C$40)*(1-H$15),E86*(1-H$15)))+M86 -> 17687.5 | V86: =IF(C86>$C$10,0,IF(AND($C$38>0,A86>=$C$38,EOMONTH(A86,0)<=$C$39),E86*(1-$C$40)*(1-I$15),E86*(1-I$15)))+M86 -> 16687.5 | W86: =IF(C86>$C$10,0,IF(AND($C$38>0,A86>=$C$38,EOMONTH(A86,0)<=$C$39),E86*(1-$C$40)*(1-F$34),E86*(1-F$34)))+M86 -> 19687.5 | X86: =IF(C86>$C$10,0,IF(AND($C$38>0,A86>=$C$38,EOMONTH(A86,0)<=$C$39),E86*(1-$C$40)*(1-G$34),E86*(1-G$34)))+M86 -> 17687.5 | Y86: =IF(C86>$C$10,0,IF(AND($C$38>0,A86>=$C$38,EOMONTH(A86,0)<=$C$39),E86*(1-$C$40)*(1-H$34),E86*(1-H$34)))+M86 -> 16687.5 | Z86: =IF(C86>$C$10,0,IF(AND($C$38>0,A86>=$C$38,EOMONTH(A86,0)<=$C$39),E86*(1-$C$40)*(1-I$34),E86*(1-I$34)))+M86 -> 15687.5 | AA86: =IF(C86>$C$10,0,IF(AND($C$38>0,A86>=$C$38,EOMONTH(A86,0)<=$C$39),E86*(1-$C$40)*(1-J$34),E86*(1-J$34)))+M86 -> 14687.5
A87: =EDATE($C$8,12) -> 43717 | B87: =EDATE($C$8,13)-1 -> 43746 | C87: =ROW()-ROW($C$74) -> 13 | D87: =INT((C87-1)/12)+1 -> 2 | E87: =IF(C87>$C$10,0,$C$21*(1+$C$29)^(D87-1)) -> 10300 | F87: =IF(C87>$C$10,0,IF(AND($C$38>0,A87>=$C$38,EOMONTH(A87,0)<=$C$39),E87*(1-$C$40),E87)) -> 10300 | G87: =IF(C87>$C$10,0,IF(AND($C$38>0,A87>=$C$38,EOMONTH(A87,0)<=$C$39),-E87*$C$40,0)) -> 0 | H87: =IF(C87>$C$10,0,$C$24*(1+$C$30)^(D87-1)) -> 3862.5 | I87: =IF(C87>$C$10,0,$C$22*(1+$C$31)^(D87-1)) -> 1931.25 | J87: =IF(C87>$C$10,0,$C$23*(1+$C$32)^(D87-1)) -> 3218.75 | K87: =IF(C87>$C$10,0,$C$25*(1+$C$33)^(D87-1)) -> 637.5 | L87: =IF(C87>$C$10,0,$C$26*(1+$C$34)^(D87-1)) -> 318.75 | M87: =H87+I87+J87+K87+L87 -> 9968.75 | N87: =F87+M87 -> 20268.75 | O87: =IF($C$7=0,0,N87/$C$7) -> 1.35125 | P87: =MAX(SUM(N87:N198)+S87,0) -> 2440126.8 | Q87: =SUM(F87:F198) -> 1231283.1 | R87: =SUM(M87:M198) -> 1223543.8 | S87: =SUMPRODUCT(($C$55:$C$67)*($D$55:$D$67>=$A87)) -> -14700 | T87: =IF(C87>$C$10,0,IF(AND($C$38>0,A87>=$C$38,EOMONTH(A87,0)<=$C$39),E87*(1-$C$40)*(1-G$15),E87*(1-G$15)))+M87 -> 19238.75 | U87: =IF(C87>$C$10,0,IF(AND($C$38>0,A87>=$C$38,EOMONTH(A87,0)<=$C$39),E87*(1-$C$40)*(1-H$15),E87*(1-H$15)))+M87 -> 18208.75 | V87: =IF(C87>$C$10,0,IF(AND($C$38>0,A87>=$C$38,EOMONTH(A87,0)<=$C$39),E87*(1-$C$40)*(1-I$15),E87*(1-I$15)))+M87 -> 17178.75 | W87: =IF(C87>$C$10,0,IF(AND($C$38>0,A87>=$C$38,EOMONTH(A87,0)<=$C$39),E87*(1-$C$40)*(1-F$34),E87*(1-F$34)))+M87 -> 20268.75 | X87: =IF(C87>$C$10,0,IF(AND($C$38>0,A87>=$C$38,EOMONTH(A87,0)<=$C$39),E87*(1-$C$40)*(1-G$34),E87*(1-G$34)))+M87 -> 18208.75 | Y87: =IF(C87>$C$10,0,IF(AND($C$38>0,A87>=$C$38,EOMONTH(A87,0)<=$C$39),E87*(1-$C$40)*(1-H$34),E87*(1-H$34)))+M87 -> 17178.75 | Z87: =IF(C87>$C$10,0,IF(AND($C$38>0,A87>=$C$38,EOMONTH(A87,0)<=$C$39),E87*(1-$C$40)*(1-I$34),E87*(1-I$34)))+M87 -> 16148.75 | AA87: =IF(C87>$C$10,0,IF(AND($C$38>0,A87>=$C$38,EOMONTH(A87,0)<=$C$39),E87*(1-$C$40)*(1-J$34),E87*(1-J$34)))+M87 -> 15118.75
A88: =EDATE($C$8,13) -> 43747 | B88: =EDATE($C$8,14)-1 -> 43777 | C88: =ROW()-ROW($C$74) -> 14 | D88: =INT((C88-1)/12)+1 -> 2 | E88: =IF(C88>$C$10,0,$C$21*(1+$C$29)^(D88-1)) -> 10300 | F88: =IF(C88>$C$10,0,IF(AND($C$38>0,A88>=$C$38,EOMONTH(A88,0)<=$C$39),E88*(1-$C$40),E88)) -> 10300 | G88: =IF(C88>$C$10,0,IF(AND($C$38>0,A88>=$C$38,EOMONTH(A88,0)<=$C$39),-E88*$C$40,0)) -> 0 | H88: =IF(C88>$C$10,0,$C$24*(1+$C$30)^(D88-1)) -> 3862.5 | I88: =IF(C88>$C$10,0,$C$22*(1+$C$31)^(D88-1)) -> 1931.25 | J88: =IF(C88>$C$10,0,$C$23*(1+$C$32)^(D88-1)) -> 3218.75 | K88: =IF(C88>$C$10,0,$C$25*(1+$C$33)^(D88-1)) -> 637.5 | L88: =IF(C88>$C$10,0,$C$26*(1+$C$34)^(D88-1)) -> 318.75 | M88: =H88+I88+J88+K88+L88 -> 9968.75 | N88: =F88+M88 -> 20268.75 | O88: =IF($C$7=0,0,N88/$C$7) -> 1.35125 | P88: =MAX(SUM(N88:N198)+S88,0) -> 2479858.1 | Q88: =SUM(F88:F198) -> 1220983.1 | R88: =SUM(M88:M198) -> 1213575 | S88: =SUMPRODUCT(($C$55:$C$67)*($D$55:$D$67>=$A88)) -> 45300 | T88: =IF(C88>$C$10,0,IF(AND($C$38>0,A88>=$C$38,EOMONTH(A88,0)<=$C$39),E88*(1-$C$40)*(1-G$15),E88*(1-G$15)))+M88 -> 19238.75 | U88: =IF(C88>$C$10,0,IF(AND($C$38>0,A88>=$C$38,EOMONTH(A88,0)<=$C$39),E88*(1-$C$40)*(1-H$15),E88*(1-H$15)))+M88 -> 18208.75 | V88: =IF(C88>$C$10,0,IF(AND($C$38>0,A88>=$C$38,EOMONTH(A88,0)<=$C$39),E88*(1-$C$40)*(1-I$15),E88*(1-I$15)))+M88 -> 17178.75 | W88: =IF(C88>$C$10,0,IF(AND($C$38>0,A88>=$C$38,EOMONTH(A88,0)<=$C$39),E88*(1-$C$40)*(1-F$34),E88*(1-F$34)))+M88 -> 20268.75 | X88: =IF(C88>$C$10,0,IF(AND($C$38>0,A88>=$C$38,EOMONTH(A88,0)<=$C$39),E88*(1-$C$40)*(1-G$34),E88*(1-G$34)))+M88 -> 18208.75 | Y88: =IF(C88>$C$10,0,IF(AND($C$38>0,A88>=$C$38,EOMONTH(A88,0)<=$C$39),E88*(1-$C$40)*(1-H$34),E88*(1-H$34)))+M88 -> 17178.75 | Z88: =IF(C88>$C$10,0,IF(AND($C$38>0,A88>=$C$38,EOMONTH(A88,0)<=$C$39),E88*(1-$C$40)*(1-I$34),E88*(1-I$34)))+M88 -> 16148.75 | AA88: =IF(C88>$C$10,0,IF(AND($C$38>0,A88>=$C$38,EOMONTH(A88,0)<=$C$39),E88*(1-$C$40)*(1-J$34),E88*(1-J$34)))+M88 -> 15118.75
A89: =EDATE($C$8,14) -> 43778 | B89: =EDATE($C$8,15)-1 -> 43807 | C89: =ROW()-ROW($C$74) -> 15 | D89: =INT((C89-1)/12)+1 -> 2 | E89: =IF(C89>$C$10,0,$C$21*(1+$C$29)^(D89-1)) -> 10300 | F89: =IF(C89>$C$10,0,IF(AND($C$38>0,A89>=$C$38,EOMONTH(A89,0)<=$C$39),E89*(1-$C$40),E89)) -> 10300 | G89: =IF(C89>$C$10,0,IF(AND($C$38>0,A89>=$C$38,EOMONTH(A89,0)<=$C$39),-E89*$C$40,0)) -> 0 | H89: =IF(C89>$C$10,0,$C$24*(1+$C$30)^(D89-1)) -> 3862.5 | I89: =IF(C89>$C$10,0,$C$22*(1+$C$31)^(D89-1)) -> 1931.25 | J89: =IF(C89>$C$10,0,$C$23*(1+$C$32)^(D89-1)) -> 3218.75 | K89: =IF(C89>$C$10,0,$C$25*(1+$C$33)^(D89-1)) -> 637.5 | L89: =IF(C89>$C$10,0,$C$26*(1+$C$34)^(D89-1)) -> 318.75 | M89: =H89+I89+J89+K89+L89 -> 9968.75 | N89: =F89+M89 -> 20268.75 | O89: =IF($C$7=0,0,N89/$C$7) -> 1.35125 | P89: =MAX(SUM(N89:N198)+S89,0) -> 2444289.3 | Q89: =SUM(F89:F198) -> 1210683.1 | R89: =SUM(M89:M198) -> 1203606.3 | S89: =SUMPRODUCT(($C$55:$C$67)*($D$55:$D$67>=$A89)) -> 30000 | T89: =IF(C89>$C$10,0,IF(AND($C$38>0,A89>=$C$38,EOMONTH(A89,0)<=$C$39),E89*(1-$C$40)*(1-G$15),E89*(1-G$15)))+M89 -> 19238.75 | U89: =IF(C89>$C$10,0,IF(AND($C$38>0,A89>=$C$38,EOMONTH(A89,0)<=$C$39),E89*(1-$C$40)*(1-H$15),E89*(1-H$15)))+M89 -> 18208.75 | V89: =IF(C89>$C$10,0,IF(AND($C$38>0,A89>=$C$38,EOMONTH(A89,0)<=$C$39),E89*(1-$C$40)*(1-I$15),E89*(1-I$15)))+M89 -> 17178.75 | W89: =IF(C89>$C$10,0,IF(AND($C$38>0,A89>=$C$38,EOMONTH(A89,0)<=$C$39),E89*(1-$C$40)*(1-F$34),E89*(1-F$34)))+M89 -> 20268.75 | X89: =IF(C89>$C$10,0,IF(AND($C$38>0,A89>=$C$38,EOMONTH(A89,0)<=$C$39),E89*(1-$C$40)*(1-G$34),E89*(1-G$34)))+M89 -> 18208.75 | Y89: =IF(C89>$C$10,0,IF(AND($C$38>0,A89>=$C$38,EOMONTH(A89,0)<=$C$39),E89*(1-$C$40)*(1-H$34),E89*(1-H$34)))+M89 -> 17178.75 | Z89: =IF(C89>$C$10,0,IF(AND($C$38>0,A89>=$C$38,EOMONTH(A89,0)<=$C$39),E89*(1-$C$40)*(1-I$34),E89*(1-I$34)))+M89 -> 16148.75 | AA89: =IF(C89>$C$10,0,IF(AND($C$38>0,A89>=$C$38,EOMONTH(A89,0)<=$C$39),E89*(1-$C$40)*(1-J$34),E89*(1-J$34)))+M89 -> 15118.75
A90: =EDATE($C$8,15) -> 43808 | B90: =EDATE($C$8,16)-1 -> 43838 | C90: =ROW()-ROW($C$74) -> 16 | D90: =INT((C90-1)/12)+1 -> 2 | E90: =IF(C90>$C$10,0,$C$21*(1+$C$29)^(D90-1)) -> 10300 | F90: =IF(C90>$C$10,0,IF(AND($C$38>0,A90>=$C$38,EOMONTH(A90,0)<=$C$39),E90*(1-$C$40),E90)) -> 10300 | G90: =IF(C90>$C$10,0,IF(AND($C$38>0,A90>=$C$38,EOMONTH(A90,0)<=$C$39),-E90*$C$40,0)) -> 0 | H90: =IF(C90>$C$10,0,$C$24*(1+$C$30)^(D90-1)) -> 3862.5 | I90: =IF(C90>$C$10,0,$C$22*(1+$C$31)^(D90-1)) -> 1931.25 | J90: =IF(C90>$C$10,0,$C$23*(1+$C$32)^(D90-1)) -> 3218.75 | K90: =IF(C90>$C$10,0,$C$25*(1+$C$33)^(D90-1)) -> 637.5 | L90: =IF(C90>$C$10,0,$C$26*(1+$C$34)^(D90-1)) -> 318.75 | M90: =H90+I90+J90+K90+L90 -> 9968.75 | N90: =F90+M90 -> 20268.75 | O90: =IF($C$7=0,0,N90/$C$7) -> 1.35125 | P90: =MAX(SUM(N90:N198)+S90,0) -> 2424020.6 | Q90: =SUM(F90:F198) -> 1200383.1 | R90: =SUM(M90:M198) -> 1193637.5 | S90: =SUMPRODUCT(($C$55:$C$67)*($D$55:$D$67>=$A90)) -> 30000 | T90: =IF(C90>$C$10,0,IF(AND($C$38>0,A90>=$C$38,EOMONTH(A90,0)<=$C$39),E90*(1-$C$40)*(1-G$15),E90*(1-G$15)))+M90 -> 19238.75 | U90: =IF(C90>$C$10,0,IF(AND($C$38>0,A90>=$C$38,EOMONTH(A90,0)<=$C$39),E90*(1-$C$40)*(1-H$15),E90*(1-H$15)))+M90 -> 18208.75 | V90: =IF(C90>$C$10,0,IF(AND($C$38>0,A90>=$C$38,EOMONTH(A90,0)<=$C$39),E90*(1-$C$40)*(1-I$15),E90*(1-I$15)))+M90 -> 17178.75 | W90: =IF(C90>$C$10,0,IF(AND($C$38>0,A90>=$C$38,EOMONTH(A90,0)<=$C$39),E90*(1-$C$40)*(1-F$34),E90*(1-F$34)))+M90 -> 20268.75 | X90: =IF(C90>$C$10,0,IF(AND($C$38>0,A90>=$C$38,EOMONTH(A90,0)<=$C$39),E90*(1-$C$40)*(1-G$34),E90*(1-G$34)))+M90 -> 18208.75 | Y90: =IF(C90>$C$10,0,IF(AND($C$38>0,A90>=$C$38,EOMONTH(A90,0)<=$C$39),E90*(1-$C$40)*(1-H$34),E90*(1-H$34)))+M90 -> 17178.75 | Z90: =IF(C90>$C$10,0,IF(AND($C$38>0,A90>=$C$38,EOMONTH(A90,0)<=$C$39),E90*(1-$C$40)*(1-I$34),E90*(1-I$34)))+M90 -> 16148.75 | AA90: =IF(C90>$C$10,0,IF(AND($C$38>0,A90>=$C$38,EOMONTH(A90,0)<=$C$39),E90*(1-$C$40)*(1-J$34),E90*(1-J$34)))+M90 -> 15118.75
A91: =EDATE($C$8,16) -> 43839 | B91: =EDATE($C$8,17)-1 -> 43869 | C91: =ROW()-ROW($C$74) -> 17 | D91: =INT((C91-1)/12)+1 -> 2 | E91: =IF(C91>$C$10,0,$C$21*(1+$C$29)^(D91-1)) -> 10300 | F91: =IF(C91>$C$10,0,IF(AND($C$38>0,A91>=$C$38,EOMONTH(A91,0)<=$C$39),E91*(1-$C$40),E91)) -> 10300 | G91: =IF(C91>$C$10,0,IF(AND($C$38>0,A91>=$C$38,EOMONTH(A91,0)<=$C$39),-E91*$C$40,0)) -> 0 | H91: =IF(C91>$C$10,0,$C$24*(1+$C$30)^(D91-1)) -> 3862.5 | I91: =IF(C91>$C$10,0,$C$22*(1+$C$31)^(D91-1)) -> 1931.25 | J91: =IF(C91>$C$10,0,$C$23*(1+$C$32)^(D91-1)) -> 3218.75 | K91: =IF(C91>$C$10,0,$C$25*(1+$C$33)^(D91-1)) -> 637.5 | L91: =IF(C91>$C$10,0,$C$26*(1+$C$34)^(D91-1)) -> 318.75 | M91: =H91+I91+J91+K91+L91 -> 9968.75 | N91: =F91+M91 -> 20268.75 | O91: =IF($C$7=0,0,N91/$C$7) -> 1.35125 | P91: =MAX(SUM(N91:N198)+S91,0) -> 2403751.8 | Q91: =SUM(F91:F198) -> 1190083.1 | R91: =SUM(M91:M198) -> 1183668.8 | S91: =SUMPRODUCT(($C$55:$C$67)*($D$55:$D$67>=$A91)) -> 30000 | T91: =IF(C91>$C$10,0,IF(AND($C$38>0,A91>=$C$38,EOMONTH(A91,0)<=$C$39),E91*(1-$C$40)*(1-G$15),E91*(1-G$15)))+M91 -> 19238.75 | U91: =IF(C91>$C$10,0,IF(AND($C$38>0,A91>=$C$38,EOMONTH(A91,0)<=$C$39),E91*(1-$C$40)*(1-H$15),E91*(1-H$15)))+M91 -> 18208.75 | V91: =IF(C91>$C$10,0,IF(AND($C$38>0,A91>=$C$38,EOMONTH(A91,0)<=$C$39),E91*(1-$C$40)*(1-I$15),E91*(1-I$15)))+M91 -> 17178.75 | W91: =IF(C91>$C$10,0,IF(AND($C$38>0,A91>=$C$38,EOMONTH(A91,0)<=$C$39),E91*(1-$C$40)*(1-F$34),E91*(1-F$34)))+M91 -> 20268.75 | X91: =IF(C91>$C$10,0,IF(AND($C$38>0,A91>=$C$38,EOMONTH(A91,0)<=$C$39),E91*(1-$C$40)*(1-G$34),E91*(1-G$34)))+M91 -> 18208.75 | Y91: =IF(C91>$C$10,0,IF(AND($C$38>0,A91>=$C$38,EOMONTH(A91,0)<=$C$39),E91*(1-$C$40)*(1-H$34),E91*(1-H$34)))+M91 -> 17178.75 | Z91: =IF(C91>$C$10,0,IF(AND($C$38>0,A91>=$C$38,EOMONTH(A91,0)<=$C$39),E91*(1-$C$40)*(1-I$34),E91*(1-I$34)))+M91 -> 16148.75 | AA91: =IF(C91>$C$10,0,IF(AND($C$38>0,A91>=$C$38,EOMONTH(A91,0)<=$C$39),E91*(1-$C$40)*(1-J$34),E91*(1-J$34)))+M91 -> 15118.75
A92: =EDATE($C$8,17) -> 43870 | B92: =EDATE($C$8,18)-1 -> 43898 | C92: =ROW()-ROW($C$74) -> 18 | D92: =INT((C92-1)/12)+1 -> 2 | E92: =IF(C92>$C$10,0,$C$21*(1+$C$29)^(D92-1)) -> 10300 | F92: =IF(C92>$C$10,0,IF(AND($C$38>0,A92>=$C$38,EOMONTH(A92,0)<=$C$39),E92*(1-$C$40),E92)) -> 10300 | G92: =IF(C92>$C$10,0,IF(AND($C$38>0,A92>=$C$38,EOMONTH(A92,0)<=$C$39),-E92*$C$40,0)) -> 0 | H92: =IF(C92>$C$10,0,$C$24*(1+$C$30)^(D92-1)) -> 3862.5 | I92: =IF(C92>$C$10,0,$C$22*(1+$C$31)^(D92-1)) -> 1931.25 | J92: =IF(C92>$C$10,0,$C$23*(1+$C$32)^(D92-1)) -> 3218.75 | K92: =IF(C92>$C$10,0,$C$25*(1+$C$33)^(D92-1)) -> 637.5 | L92: =IF(C92>$C$10,0,$C$26*(1+$C$34)^(D92-1)) -> 318.75 | M92: =H92+I92+J92+K92+L92 -> 9968.75 | N92: =F92+M92 -> 20268.75 | O92: =IF($C$7=0,0,N92/$C$7) -> 1.35125 | P92: =MAX(SUM(N92:N198)+S92,0) -> 2383483.1 | Q92: =SUM(F92:F198) -> 1179783.1 | R92: =SUM(M92:M198) -> 1173700 | S92: =SUMPRODUCT(($C$55:$C$67)*($D$55:$D$67>=$A92)) -> 30000 | T92: =IF(C92>$C$10,0,IF(AND($C$38>0,A92>=$C$38,EOMONTH(A92,0)<=$C$39),E92*(1-$C$40)*(1-G$15),E92*(1-G$15)))+M92 -> 19238.75 | U92: =IF(C92>$C$10,0,IF(AND($C$38>0,A92>=$C$38,EOMONTH(A92,0)<=$C$39),E92*(1-$C$40)*(1-H$15),E92*(1-H$15)))+M92 -> 18208.75 | V92: =IF(C92>$C$10,0,IF(AND($C$38>0,A92>=$C$38,EOMONTH(A92,0)<=$C$39),E92*(1-$C$40)*(1-I$15),E92*(1-I$15)))+M92 -> 17178.75 | W92: =IF(C92>$C$10,0,IF(AND($C$38>0,A92>=$C$38,EOMONTH(A92,0)<=$C$39),E92*(1-$C$40)*(1-F$34),E92*(1-F$34)))+M92 -> 20268.75 | X92: =IF(C92>$C$10,0,IF(AND($C$38>0,A92>=$C$38,EOMONTH(A92,0)<=$C$39),E92*(1-$C$40)*(1-G$34),E92*(1-G$34)))+M92 -> 18208.75 | Y92: =IF(C92>$C$10,0,IF(AND($C$38>0,A92>=$C$38,EOMONTH(A92,0)<=$C$39),E92*(1-$C$40)*(1-H$34),E92*(1-H$34)))+M92 -> 17178.75 | Z92: =IF(C92>$C$10,0,IF(AND($C$38>0,A92>=$C$38,EOMONTH(A92,0)<=$C$39),E92*(1-$C$40)*(1-I$34),E92*(1-I$34)))+M92 -> 16148.75 | AA92: =IF(C92>$C$10,0,IF(AND($C$38>0,A92>=$C$38,EOMONTH(A92,0)<=$C$39),E92*(1-$C$40)*(1-J$34),E92*(1-J$34)))+M92 -> 15118.75
A93: =EDATE($C$8,18) -> 43899 | B93: =EDATE($C$8,19)-1 -> 43929 | C93: =ROW()-ROW($C$74) -> 19 | D93: =INT((C93-1)/12)+1 -> 2 | E93: =IF(C93>$C$10,0,$C$21*(1+$C$29)^(D93-1)) -> 10300 | F93: =IF(C93>$C$10,0,IF(AND($C$38>0,A93>=$C$38,EOMONTH(A93,0)<=$C$39),E93*(1-$C$40),E93)) -> 10300 | G93: =IF(C93>$C$10,0,IF(AND($C$38>0,A93>=$C$38,EOMONTH(A93,0)<=$C$39),-E93*$C$40,0)) -> 0 | H93: =IF(C93>$C$10,0,$C$24*(1+$C$30)^(D93-1)) -> 3862.5 | I93: =IF(C93>$C$10,0,$C$22*(1+$C$31)^(D93-1)) -> 1931.25 | J93: =IF(C93>$C$10,0,$C$23*(1+$C$32)^(D93-1)) -> 3218.75 | K93: =IF(C93>$C$10,0,$C$25*(1+$C$33)^(D93-1)) -> 637.5 | L93: =IF(C93>$C$10,0,$C$26*(1+$C$34)^(D93-1)) -> 318.75 | M93: =H93+I93+J93+K93+L93 -> 9968.75 | N93: =F93+M93 -> 20268.75 | O93: =IF($C$7=0,0,N93/$C$7) -> 1.35125 | P93: =MAX(SUM(N93:N198)+S93,0) -> 2333214.3 | Q93: =SUM(F93:F198) -> 1169483.1 | R93: =SUM(M93:M198) -> 1163731.3 | S93: =SUMPRODUCT(($C$55:$C$67)*($D$55:$D$67>=$A93)) -> 0 | T93: =IF(C93>$C$10,0,IF(AND($C$38>0,A93>=$C$38,EOMONTH(A93,0)<=$C$39),E93*(1-$C$40)*(1-G$15),E93*(1-G$15)))+M93 -> 19238.75 | U93: =IF(C93>$C$10,0,IF(AND($C$38>0,A93>=$C$38,EOMONTH(A93,0)<=$C$39),E93*(1-$C$40)*(1-H$15),E93*(1-H$15)))+M93 -> 18208.75 | V93: =IF(C93>$C$10,0,IF(AND($C$38>0,A93>=$C$38,EOMONTH(A93,0)<=$C$39),E93*(1-$C$40)*(1-I$15),E93*(1-I$15)))+M93 -> 17178.75 | W93: =IF(C93>$C$10,0,IF(AND($C$38>0,A93>=$C$38,EOMONTH(A93,0)<=$C$39),E93*(1-$C$40)*(1-F$34),E93*(1-F$34)))+M93 -> 20268.75 | X93: =IF(C93>$C$10,0,IF(AND($C$38>0,A93>=$C$38,EOMONTH(A93,0)<=$C$39),E93*(1-$C$40)*(1-G$34),E93*(1-G$34)))+M93 -> 18208.75 | Y93: =IF(C93>$C$10,0,IF(AND($C$38>0,A93>=$C$38,EOMONTH(A93,0)<=$C$39),E93*(1-$C$40)*(1-H$34),E93*(1-H$34)))+M93 -> 17178.75 | Z93: =IF(C93>$C$10,0,IF(AND($C$38>0,A93>=$C$38,EOMONTH(A93,0)<=$C$39),E93*(1-$C$40)*(1-I$34),E93*(1-I$34)))+M93 -> 16148.75 | AA93: =IF(C93>$C$10,0,IF(AND($C$38>0,A93>=$C$38,EOMONTH(A93,0)<=$C$39),E93*(1-$C$40)*(1-J$34),E93*(1-J$34)))+M93 -> 15118.75
A94: =EDATE($C$8,19) -> 43930 | B94: =EDATE($C$8,20)-1 -> 43959 | C94: =ROW()-ROW($C$74) -> 20 | D94: =INT((C94-1)/12)+1 -> 2 | E94: =IF(C94>$C$10,0,$C$21*(1+$C$29)^(D94-1)) -> 10300 | F94: =IF(C94>$C$10,0,IF(AND($C$38>0,A94>=$C$38,EOMONTH(A94,0)<=$C$39),E94*(1-$C$40),E94)) -> 10300 | G94: =IF(C94>$C$10,0,IF(AND($C$38>0,A94>=$C$38,EOMONTH(A94,0)<=$C$39),-E94*$C$40,0)) -> 0 | H94: =IF(C94>$C$10,0,$C$24*(1+$C$30)^(D94-1)) -> 3862.5 | I94: =IF(C94>$C$10,0,$C$22*(1+$C$31)^(D94-1)) -> 1931.25 | J94: =IF(C94>$C$10,0,$C$23*(1+$C$32)^(D94-1)) -> 3218.75 | K94: =IF(C94>$C$10,0,$C$25*(1+$C$33)^(D94-1)) -> 637.5 | L94: =IF(C94>$C$10,0,$C$26*(1+$C$34)^(D94-1)) -> 318.75 | M94: =H94+I94+J94+K94+L94 -> 9968.75 | N94: =F94+M94 -> 20268.75 | O94: =IF($C$7=0,0,N94/$C$7) -> 1.35125 | P94: =MAX(SUM(N94:N198)+S94,0) -> 2312945.6 | Q94: =SUM(F94:F198) -> 1159183.1 | R94: =SUM(M94:M198) -> 1153762.5 | S94: =SUMPRODUCT(($C$55:$C$67)*($D$55:$D$67>=$A94)) -> 0 | T94: =IF(C94>$C$10,0,IF(AND($C$38>0,A94>=$C$38,EOMONTH(A94,0)<=$C$39),E94*(1-$C$40)*(1-G$15),E94*(1-G$15)))+M94 -> 19238.75 | U94: =IF(C94>$C$10,0,IF(AND($C$38>0,A94>=$C$38,EOMONTH(A94,0)<=$C$39),E94*(1-$C$40)*(1-H$15),E94*(1-H$15)))+M94 -> 18208.75 | V94: =IF(C94>$C$10,0,IF(AND($C$38>0,A94>=$C$38,EOMONTH(A94,0)<=$C$39),E94*(1-$C$40)*(1-I$15),E94*(1-I$15)))+M94 -> 17178.75 | W94: =IF(C94>$C$10,0,IF(AND($C$38>0,A94>=$C$38,EOMONTH(A94,0)<=$C$39),E94*(1-$C$40)*(1-F$34),E94*(1-F$34)))+M94 -> 20268.75 | X94: =IF(C94>$C$10,0,IF(AND($C$38>0,A94>=$C$38,EOMONTH(A94,0)<=$C$39),E94*(1-$C$40)*(1-G$34),E94*(1-G$34)))+M94 -> 18208.75 | Y94: =IF(C94>$C$10,0,IF(AND($C$38>0,A94>=$C$38,EOMONTH(A94,0)<=$C$39),E94*(1-$C$40)*(1-H$34),E94*(1-H$34)))+M94 -> 17178.75 | Z94: =IF(C94>$C$10,0,IF(AND($C$38>0,A94>=$C$38,EOMONTH(A94,0)<=$C$39),E94*(1-$C$40)*(1-I$34),E94*(1-I$34)))+M94 -> 16148.75 | AA94: =IF(C94>$C$10,0,IF(AND($C$38>0,A94>=$C$38,EOMONTH(A94,0)<=$C$39),E94*(1-$C$40)*(1-J$34),E94*(1-J$34)))+M94 -> 15118.75
A95: =EDATE($C$8,20) -> 43960 | B95: =EDATE($C$8,21)-1 -> 43990 | C95: =ROW()-ROW($C$74) -> 21 | D95: =INT((C95-1)/12)+1 -> 2 | E95: =IF(C95>$C$10,0,$C$21*(1+$C$29)^(D95-1)) -> 10300 | F95: =IF(C95>$C$10,0,IF(AND($C$38>0,A95>=$C$38,EOMONTH(A95,0)<=$C$39),E95*(1-$C$40),E95)) -> 7210 | G95: =IF(C95>$C$10,0,IF(AND($C$38>0,A95>=$C$38,EOMONTH(A95,0)<=$C$39),-E95*$C$40,0)) -> -3090 | H95: =IF(C95>$C$10,0,$C$24*(1+$C$30)^(D95-1)) -> 3862.5 | I95: =IF(C95>$C$10,0,$C$22*(1+$C$31)^(D95-1)) -> 1931.25 | J95: =IF(C95>$C$10,0,$C$23*(1+$C$32)^(D95-1)) -> 3218.75 | K95: =IF(C95>$C$10,0,$C$25*(1+$C$33)^(D95-1)) -> 637.5 | L95: =IF(C95>$C$10,0,$C$26*(1+$C$34)^(D95-1)) -> 318.75 | M95: =H95+I95+J95+K95+L95 -> 9968.75 | N95: =F95+M95 -> 17178.75 | O95: =IF($C$7=0,0,N95/$C$7) -> 1.14525 | P95: =MAX(SUM(N95:N198)+S95,0) -> 2292676.8 | Q95: =SUM(F95:F198) -> 1148883.1 | R95: =SUM(M95:M198) -> 1143793.8 | S95: =SUMPRODUCT(($C$55:$C$67)*($D$55:$D$67>=$A95)) -> 0 | T95: =IF(C95>$C$10,0,IF(AND($C$38>0,A95>=$C$38,EOMONTH(A95,0)<=$C$39),E95*(1-$C$40)*(1-G$15),E95*(1-G$15)))+M95 -> 16457.75 | U95: =IF(C95>$C$10,0,IF(AND($C$38>0,A95>=$C$38,EOMONTH(A95,0)<=$C$39),E95*(1-$C$40)*(1-H$15),E95*(1-H$15)))+M95 -> 15736.75 | V95: =IF(C95>$C$10,0,IF(AND($C$38>0,A95>=$C$38,EOMONTH(A95,0)<=$C$39),E95*(1-$C$40)*(1-I$15),E95*(1-I$15)))+M95 -> 15015.75 | W95: =IF(C95>$C$10,0,IF(AND($C$38>0,A95>=$C$38,EOMONTH(A95,0)<=$C$39),E95*(1-$C$40)*(1-F$34),E95*(1-F$34)))+M95 -> 17178.75 | X95: =IF(C95>$C$10,0,IF(AND($C$38>0,A95>=$C$38,EOMONTH(A95,0)<=$C$39),E95*(1-$C$40)*(1-G$34),E95*(1-G$34)))+M95 -> 15736.75 | Y95: =IF(C95>$C$10,0,IF(AND($C$38>0,A95>=$C$38,EOMONTH(A95,0)<=$C$39),E95*(1-$C$40)*(1-H$34),E95*(1-H$34)))+M95 -> 15015.75 | Z95: =IF(C95>$C$10,0,IF(AND($C$38>0,A95>=$C$38,EOMONTH(A95,0)<=$C$39),E95*(1-$C$40)*(1-I$34),E95*(1-I$34)))+M95 -> 14294.75 | AA95: =IF(C95>$C$10,0,IF(AND($C$38>0,A95>=$C$38,EOMONTH(A95,0)<=$C$39),E95*(1-$C$40)*(1-J$34),E95*(1-J$34)))+M95 -> 13573.75
A96: =EDATE($C$8,21) -> 43991 | B96: =EDATE($C$8,22)-1 -> 44020 | C96: =ROW()-ROW($C$74) -> 22 | D96: =INT((C96-1)/12)+1 -> 2 | E96: =IF(C96>$C$10,0,$C$21*(1+$C$29)^(D96-1)) -> 10300 | F96: =IF(C96>$C$10,0,IF(AND($C$38>0,A96>=$C$38,EOMONTH(A96,0)<=$C$39),E96*(1-$C$40),E96)) -> 7210 | G96: =IF(C96>$C$10,0,IF(AND($C$38>0,A96>=$C$38,EOMONTH(A96,0)<=$C$39),-E96*$C$40,0)) -> -3090 | H96: =IF(C96>$C$10,0,$C$24*(1+$C$30)^(D96-1)) -> 3862.5 | I96: =IF(C96>$C$10,0,$C$22*(1+$C$31)^(D96-1)) -> 1931.25 | J96: =IF(C96>$C$10,0,$C$23*(1+$C$32)^(D96-1)) -> 3218.75 | K96: =IF(C96>$C$10,0,$C$25*(1+$C$33)^(D96-1)) -> 637.5 | L96: =IF(C96>$C$10,0,$C$26*(1+$C$34)^(D96-1)) -> 318.75 | M96: =H96+I96+J96+K96+L96 -> 9968.75 | N96: =F96+M96 -> 17178.75 | O96: =IF($C$7=0,0,N96/$C$7) -> 1.14525 | P96: =MAX(SUM(N96:N198)+S96,0) -> 2275498.1 | Q96: =SUM(F96:F198) -> 1141673.1 | R96: =SUM(M96:M198) -> 1133825 | S96: =SUMPRODUCT(($C$55:$C$67)*($D$55:$D$67>=$A96)) -> 0 | T96: =IF(C96>$C$10,0,IF(AND($C$38>0,A96>=$C$38,EOMONTH(A96,0)<=$C$39),E96*(1-$C$40)*(1-G$15),E96*(1-G$15)))+M96 -> 16457.75 | U96: =IF(C96>$C$10,0,IF(AND($C$38>0,A96>=$C$38,EOMONTH(A96,0)<=$C$39),E96*(1-$C$40)*(1-H$15),E96*(1-H$15)))+M96 -> 15736.75 | V96: =IF(C96>$C$10,0,IF(AND($C$38>0,A96>=$C$38,EOMONTH(A96,0)<=$C$39),E96*(1-$C$40)*(1-I$15),E96*(1-I$15)))+M96 -> 15015.75 | W96: =IF(C96>$C$10,0,IF(AND($C$38>0,A96>=$C$38,EOMONTH(A96,0)<=$C$39),E96*(1-$C$40)*(1-F$34),E96*(1-F$34)))+M96 -> 17178.75 | X96: =IF(C96>$C$10,0,IF(AND($C$38>0,A96>=$C$38,EOMONTH(A96,0)<=$C$39),E96*(1-$C$40)*(1-G$34),E96*(1-G$34)))+M96 -> 15736.75 | Y96: =IF(C96>$C$10,0,IF(AND($C$38>0,A96>=$C$38,EOMONTH(A96,0)<=$C$39),E96*(1-$C$40)*(1-H$34),E96*(1-H$34)))+M96 -> 15015.75 | Z96: =IF(C96>$C$10,0,IF(AND($C$38>0,A96>=$C$38,EOMONTH(A96,0)<=$C$39),E96*(1-$C$40)*(1-I$34),E96*(1-I$34)))+M96 -> 14294.75 | AA96: =IF(C96>$C$10,0,IF(AND($C$38>0,A96>=$C$38,EOMONTH(A96,0)<=$C$39),E96*(1-$C$40)*(1-J$34),E96*(1-J$34)))+M96 -> 13573.75
A97: =EDATE($C$8,22) -> 44021 | B97: =EDATE($C$8,23)-1 -> 44051 | C97: =ROW()-ROW($C$74) -> 23 | D97: =INT((C97-1)/12)+1 -> 2 | E97: =IF(C97>$C$10,0,$C$21*(1+$C$29)^(D97-1)) -> 10300 | F97: =IF(C97>$C$10,0,IF(AND($C$38>0,A97>=$C$38,EOMONTH(A97,0)<=$C$39),E97*(1-$C$40),E97)) -> 7210 | G97: =IF(C97>$C$10,0,IF(AND($C$38>0,A97>=$C$38,EOMONTH(A97,0)<=$C$39),-E97*$C$40,0)) -> -3090 | H97: =IF(C97>$C$10,0,$C$24*(1+$C$30)^(D97-1)) -> 3862.5 | I97: =IF(C97>$C$10,0,$C$22*(1+$C$31)^(D97-1)) -> 1931.25 | J97: =IF(C97>$C$10,0,$C$23*(1+$C$32)^(D97-1)) -> 3218.75 | K97: =IF(C97>$C$10,0,$C$25*(1+$C$33)^(D97-1)) -> 637.5 | L97: =IF(C97>$C$10,0,$C$26*(1+$C$34)^(D97-1)) -> 318.75 | M97: =H97+I97+J97+K97+L97 -> 9968.75 | N97: =F97+M97 -> 17178.75 | O97: =IF($C$7=0,0,N97/$C$7) -> 1.14525 | P97: =MAX(SUM(N97:N198)+S97,0) -> 2258319.3 | Q97: =SUM(F97:F198) -> 1134463.1 | R97: =SUM(M97:M198) -> 1123856.3 | S97: =SUMPRODUCT(($C$55:$C$67)*($D$55:$D$67>=$A97)) -> 0 | T97: =IF(C97>$C$10,0,IF(AND($C$38>0,A97>=$C$38,EOMONTH(A97,0)<=$C$39),E97*(1-$C$40)*(1-G$15),E97*(1-G$15)))+M97 -> 16457.75 | U97: =IF(C97>$C$10,0,IF(AND($C$38>0,A97>=$C$38,EOMONTH(A97,0)<=$C$39),E97*(1-$C$40)*(1-H$15),E97*(1-H$15)))+M97 -> 15736.75 | V97: =IF(C97>$C$10,0,IF(AND($C$38>0,A97>=$C$38,EOMONTH(A97,0)<=$C$39),E97*(1-$C$40)*(1-I$15),E97*(1-I$15)))+M97 -> 15015.75 | W97: =IF(C97>$C$10,0,IF(AND($C$38>0,A97>=$C$38,EOMONTH(A97,0)<=$C$39),E97*(1-$C$40)*(1-F$34),E97*(1-F$34)))+M97 -> 17178.75 | X97: =IF(C97>$C$10,0,IF(AND($C$38>0,A97>=$C$38,EOMONTH(A97,0)<=$C$39),E97*(1-$C$40)*(1-G$34),E97*(1-G$34)))+M97 -> 15736.75 | Y97: =IF(C97>$C$10,0,IF(AND($C$38>0,A97>=$C$38,EOMONTH(A97,0)<=$C$39),E97*(1-$C$40)*(1-H$34),E97*(1-H$34)))+M97 -> 15015.75 | Z97: =IF(C97>$C$10,0,IF(AND($C$38>0,A97>=$C$38,EOMONTH(A97,0)<=$C$39),E97*(1-$C$40)*(1-I$34),E97*(1-I$34)))+M97 -> 14294.75 | AA97: =IF(C97>$C$10,0,IF(AND($C$38>0,A97>=$C$38,EOMONTH(A97,0)<=$C$39),E97*(1-$C$40)*(1-J$34),E97*(1-J$34)))+M97 -> 13573.75
A98: =EDATE($C$8,23) -> 44052 | B98: =EDATE($C$8,24)-1 -> 44082 | C98: =ROW()-ROW($C$74) -> 24 | D98: =INT((C98-1)/12)+1 -> 2 | E98: =IF(C98>$C$10,0,$C$21*(1+$C$29)^(D98-1)) -> 10300 | F98: =IF(C98>$C$10,0,IF(AND($C$38>0,A98>=$C$38,EOMONTH(A98,0)<=$C$39),E98*(1-$C$40),E98)) -> 7210 | G98: =IF(C98>$C$10,0,IF(AND($C$38>0,A98>=$C$38,EOMONTH(A98,0)<=$C$39),-E98*$C$40,0)) -> -3090 | H98: =IF(C98>$C$10,0,$C$24*(1+$C$30)^(D98-1)) -> 3862.5 | I98: =IF(C98>$C$10,0,$C$22*(1+$C$31)^(D98-1)) -> 1931.25 | J98: =IF(C98>$C$10,0,$C$23*(1+$C$32)^(D98-1)) -> 3218.75 | K98: =IF(C98>$C$10,0,$C$25*(1+$C$33)^(D98-1)) -> 637.5 | L98: =IF(C98>$C$10,0,$C$26*(1+$C$34)^(D98-1)) -> 318.75 | M98: =H98+I98+J98+K98+L98 -> 9968.75 | N98: =F98+M98 -> 17178.75 | O98: =IF($C$7=0,0,N98/$C$7) -> 1.14525 | P98: =MAX(SUM(N98:N198)+S98,0) -> 2241140.6 | Q98: =SUM(F98:F198) -> 1127253.1 | R98: =SUM(M98:M198) -> 1113887.5 | S98: =SUMPRODUCT(($C$55:$C$67)*($D$55:$D$67>=$A98)) -> 0 | T98: =IF(C98>$C$10,0,IF(AND($C$38>0,A98>=$C$38,EOMONTH(A98,0)<=$C$39),E98*(1-$C$40)*(1-G$15),E98*(1-G$15)))+M98 -> 16457.75 | U98: =IF(C98>$C$10,0,IF(AND($C$38>0,A98>=$C$38,EOMONTH(A98,0)<=$C$39),E98*(1-$C$40)*(1-H$15),E98*(1-H$15)))+M98 -> 15736.75 | V98: =IF(C98>$C$10,0,IF(AND($C$38>0,A98>=$C$38,EOMONTH(A98,0)<=$C$39),E98*(1-$C$40)*(1-I$15),E98*(1-I$15)))+M98 -> 15015.75 | W98: =IF(C98>$C$10,0,IF(AND($C$38>0,A98>=$C$38,EOMONTH(A98,0)<=$C$39),E98*(1-$C$40)*(1-F$34),E98*(1-F$34)))+M98 -> 17178.75 | X98: =IF(C98>$C$10,0,IF(AND($C$38>0,A98>=$C$38,EOMONTH(A98,0)<=$C$39),E98*(1-$C$40)*(1-G$34),E98*(1-G$34)))+M98 -> 15736.75 | Y98: =IF(C98>$C$10,0,IF(AND($C$38>0,A98>=$C$38,EOMONTH(A98,0)<=$C$39),E98*(1-$C$40)*(1-H$34),E98*(1-H$34)))+M98 -> 15015.75 | Z98: =IF(C98>$C$10,0,IF(AND($C$38>0,A98>=$C$38,EOMONTH(A98,0)<=$C$39),E98*(1-$C$40)*(1-I$34),E98*(1-I$34)))+M98 -> 14294.75 | AA98: =IF(C98>$C$10,0,IF(AND($C$38>0,A98>=$C$38,EOMONTH(A98,0)<=$C$39),E98*(1-$C$40)*(1-J$34),E98*(1-J$34)))+M98 -> 13573.75
A99: =EDATE($C$8,24) -> 44083 | B99: =EDATE($C$8,25)-1 -> 44112 | C99: =ROW()-ROW($C$74) -> 25 | D99: =INT((C99-1)/12)+1 -> 3 | E99: =IF(C99>$C$10,0,$C$21*(1+$C$29)^(D99-1)) -> 10609 | F99: =IF(C99>$C$10,0,IF(AND($C$38>0,A99>=$C$38,EOMONTH(A99,0)<=$C$39),E99*(1-$C$40),E99)) -> 7426.3 | G99: =IF(C99>$C$10,0,IF(AND($C$38>0,A99>=$C$38,EOMONTH(A99,0)<=$C$39),-E99*$C$40,0)) -> -3182.7 | H99: =IF(C99>$C$10,0,$C$24*(1+$C$30)^(D99-1)) -> 3978.375 | I99: =IF(C99>$C$10,0,$C$22*(1+$C$31)^(D99-1)) -> 1989.1875 | J99: =IF(C99>$C$10,0,$C$23*(1+$C$32)^(D99-1)) -> 3315.3125 | K99: =IF(C99>$C$10,0,$C$25*(1+$C$33)^(D99-1)) -> 650.25 | L99: =IF(C99>$C$10,0,$C$26*(1+$C$34)^(D99-1)) -> 325.125 | M99: =H99+I99+J99+K99+L99 -> 10258.25 | N99: =F99+M99 -> 17684.55 | O99: =IF($C$7=0,0,N99/$C$7) -> 1.17897 | P99: =MAX(SUM(N99:N198)+S99,0) -> 2223961.8 | Q99: =SUM(F99:F198) -> 1120043.1 | R99: =SUM(M99:M198) -> 1103918.8 | S99: =SUMPRODUCT(($C$55:$C$67)*($D$55:$D$67>=$A99)) -> 0 | T99: =IF(C99>$C$10,0,IF(AND($C$38>0,A99>=$C$38,EOMONTH(A99,0)<=$C$39),E99*(1-$C$40)*(1-G$15),E99*(1-G$15)))+M99 -> 16941.92 | U99: =IF(C99>$C$10,0,IF(AND($C$38>0,A99>=$C$38,EOMONTH(A99,0)<=$C$39),E99*(1-$C$40)*(1-H$15),E99*(1-H$15)))+M99 -> 16199.29 | V99: =IF(C99>$C$10,0,IF(AND($C$38>0,A99>=$C$38,EOMONTH(A99,0)<=$C$39),E99*(1-$C$40)*(1-I$15),E99*(1-I$15)))+M99 -> 15456.66 | W99: =IF(C99>$C$10,0,IF(AND($C$38>0,A99>=$C$38,EOMONTH(A99,0)<=$C$39),E99*(1-$C$40)*(1-F$34),E99*(1-F$34)))+M99 -> 17684.55 | X99: =IF(C99>$C$10,0,IF(AND($C$38>0,A99>=$C$38,EOMONTH(A99,0)<=$C$39),E99*(1-$C$40)*(1-G$34),E99*(1-G$34)))+M99 -> 16199.29 | Y99: =IF(C99>$C$10,0,IF(AND($C$38>0,A99>=$C$38,EOMONTH(A99,0)<=$C$39),E99*(1-$C$40)*(1-H$34),E99*(1-H$34)))+M99 -> 15456.66 | Z99: =IF(C99>$C$10,0,IF(AND($C$38>0,A99>=$C$38,EOMONTH(A99,0)<=$C$39),E99*(1-$C$40)*(1-I$34),E99*(1-I$34)))+M99 -> 14714.03 | AA99: =IF(C99>$C$10,0,IF(AND($C$38>0,A99>=$C$38,EOMONTH(A99,0)<=$C$39),E99*(1-$C$40)*(1-J$34),E99*(1-J$34)))+M99 -> 13971.4
A100: =EDATE($C$8,25) -> 44113 | B100: =EDATE($C$8,26)-1 -> 44143 | C100: =ROW()-ROW($C$74) -> 26 | D100: =INT((C100-1)/12)+1 -> 3 | E100: =IF(C100>$C$10,0,$C$21*(1+$C$29)^(D100-1)) -> 10609 | F100: =IF(C100>$C$10,0,IF(AND($C$38>0,A100>=$C$38,EOMONTH(A100,0)<=$C$39),E100*(1-$C$40),E100)) -> 7426.3 | G100: =IF(C100>$C$10,0,IF(AND($C$38>0,A100>=$C$38,EOMONTH(A100,0)<=$C$39),-E100*$C$40,0)) -> -3182.7 | H100: =IF(C100>$C$10,0,$C$24*(1+$C$30)^(D100-1)) -> 3978.375 | I100: =IF(C100>$C$10,0,$C$22*(1+$C$31)^(D100-1)) -> 1989.1875 | J100: =IF(C100>$C$10,0,$C$23*(1+$C$32)^(D100-1)) -> 3315.3125 | K100: =IF(C100>$C$10,0,$C$25*(1+$C$33)^(D100-1)) -> 650.25 | L100: =IF(C100>$C$10,0,$C$26*(1+$C$34)^(D100-1)) -> 325.125 | M100: =H100+I100+J100+K100+L100 -> 10258.25 | N100: =F100+M100 -> 17684.55 | O100: =IF($C$7=0,0,N100/$C$7) -> 1.17897 | P100: =MAX(SUM(N100:N198)+S100,0) -> 2206277.3 | Q100: =SUM(F100:F198) -> 1112616.8 | R100: =SUM(M100:M198) -> 1093660.5 | S100: =SUMPRODUCT(($C$55:$C$67)*($D$55:$D$67>=$A100)) -> 0 | T100: =IF(C100>$C$10,0,IF(AND($C$38>0,A100>=$C$38,EOMONTH(A100,0)<=$C$39),E100*(1-$C$40)*(1-G$15),E100*(1-G$15)))+M100 -> 16941.92 | U100: =IF(C100>$C$10,0,IF(AND($C$38>0,A100>=$C$38,EOMONTH(A100,0)<=$C$39),E100*(1-$C$40)*(1-H$15),E100*(1-H$15)))+M100 -> 16199.29 | V100: =IF(C100>$C$10,0,IF(AND($C$38>0,A100>=$C$38,EOMONTH(A100,0)<=$C$39),E100*(1-$C$40)*(1-I$15),E100*(1-I$15)))+M100 -> 15456.66 | W100: =IF(C100>$C$10,0,IF(AND($C$38>0,A100>=$C$38,EOMONTH(A100,0)<=$C$39),E100*(1-$C$40)*(1-F$34),E100*(1-F$34)))+M100 -> 17684.55 | X100: =IF(C100>$C$10,0,IF(AND($C$38>0,A100>=$C$38,EOMONTH(A100,0)<=$C$39),E100*(1-$C$40)*(1-G$34),E100*(1-G$34)))+M100 -> 16199.29 | Y100: =IF(C100>$C$10,0,IF(AND($C$38>0,A100>=$C$38,EOMONTH(A100,0)<=$C$39),E100*(1-$C$40)*(1-H$34),E100*(1-H$34)))+M100 -> 15456.66 | Z100: =IF(C100>$C$10,0,IF(AND($C$38>0,A100>=$C$38,EOMONTH(A100,0)<=$C$39),E100*(1-$C$40)*(1-I$34),E100*(1-I$34)))+M100 -> 14714.03 | AA100: =IF(C100>$C$10,0,IF(AND($C$38>0,A100>=$C$38,EOMONTH(A100,0)<=$C$39),E100*(1-$C$40)*(1-J$34),E100*(1-J$34)))+M100 -> 13971.4
A101: =EDATE($C$8,26) -> 44144 | B101: =EDATE($C$8,27)-1 -> 44173 | C101: =ROW()-ROW($C$74) -> 27 | D101: =INT((C101-1)/12)+1 -> 3 | E101: =IF(C101>$C$10,0,$C$21*(1+$C$29)^(D101-1)) -> 10609 | F101: =IF(C101>$C$10,0,IF(AND($C$38>0,A101>=$C$38,EOMONTH(A101,0)<=$C$39),E101*(1-$C$40),E101)) -> 7426.3 | G101: =IF(C101>$C$10,0,IF(AND($C$38>0,A101>=$C$38,EOMONTH(A101,0)<=$C$39),-E101*$C$40,0)) -> -3182.7 | H101: =IF(C101>$C$10,0,$C$24*(1+$C$30)^(D101-1)) -> 3978.375 | I101: =IF(C101>$C$10,0,$C$22*(1+$C$31)^(D101-1)) -> 1989.1875 | J101: =IF(C101>$C$10,0,$C$23*(1+$C$32)^(D101-1)) -> 3315.3125 | K101: =IF(C101>$C$10,0,$C$25*(1+$C$33)^(D101-1)) -> 650.25 | L101: =IF(C101>$C$10,0,$C$26*(1+$C$34)^(D101-1)) -> 325.125 | M101: =H101+I101+J101+K101+L101 -> 10258.25 | N101: =F101+M101 -> 17684.55 | O101: =IF($C$7=0,0,N101/$C$7) -> 1.17897 | P101: =MAX(SUM(N101:N198)+S101,0) -> 2188592.7 | Q101: =SUM(F101:F198) -> 1105190.5 | R101: =SUM(M101:M198) -> 1083402.3 | S101: =SUMPRODUCT(($C$55:$C$67)*($D$55:$D$67>=$A101)) -> 0 | T101: =IF(C101>$C$10,0,IF(AND($C$38>0,A101>=$C$38,EOMONTH(A101,0)<=$C$39),E101*(1-$C$40)*(1-G$15),E101*(1-G$15)))+M101 -> 16941.92 | U101: =IF(C101>$C$10,0,IF(AND($C$38>0,A101>=$C$38,EOMONTH(A101,0)<=$C$39),E101*(1-$C$40)*(1-H$15),E101*(1-H$15)))+M101 -> 16199.29 | V101: =IF(C101>$C$10,0,IF(AND($C$38>0,A101>=$C$38,EOMONTH(A101,0)<=$C$39),E101*(1-$C$40)*(1-I$15),E101*(1-I$15)))+M101 -> 15456.66 | W101: =IF(C101>$C$10,0,IF(AND($C$38>0,A101>=$C$38,EOMONTH(A101,0)<=$C$39),E101*(1-$C$40)*(1-F$34),E101*(1-F$34)))+M101 -> 17684.55 | X101: =IF(C101>$C$10,0,IF(AND($C$38>0,A101>=$C$38,EOMONTH(A101,0)<=$C$39),E101*(1-$C$40)*(1-G$34),E101*(1-G$34)))+M101 -> 16199.29 | Y101: =IF(C101>$C$10,0,IF(AND($C$38>0,A101>=$C$38,EOMONTH(A101,0)<=$C$39),E101*(1-$C$40)*(1-H$34),E101*(1-H$34)))+M101 -> 15456.66 | Z101: =IF(C101>$C$10,0,IF(AND($C$38>0,A101>=$C$38,EOMONTH(A101,0)<=$C$39),E101*(1-$C$40)*(1-I$34),E101*(1-I$34)))+M101 -> 14714.03 | AA101: =IF(C101>$C$10,0,IF(AND($C$38>0,A101>=$C$38,EOMONTH(A101,0)<=$C$39),E101*(1-$C$40)*(1-J$34),E101*(1-J$34)))+M101 -> 13971.4
A102: =EDATE($C$8,27) -> 44174 | B102: =EDATE($C$8,28)-1 -> 44204 | C102: =ROW()-ROW($C$74) -> 28 | D102: =INT((C102-1)/12)+1 -> 3 | E102: =IF(C102>$C$10,0,$C$21*(1+$C$29)^(D102-1)) -> 10609 | F102: =IF(C102>$C$10,0,IF(AND($C$38>0,A102>=$C$38,EOMONTH(A102,0)<=$C$39),E102*(1-$C$40),E102)) -> 7426.3 | G102: =IF(C102>$C$10,0,IF(AND($C$38>0,A102>=$C$38,EOMONTH(A102,0)<=$C$39),-E102*$C$40,0)) -> -3182.7 | H102: =IF(C102>$C$10,0,$C$24*(1+$C$30)^(D102-1)) -> 3978.375 | I102: =IF(C102>$C$10,0,$C$22*(1+$C$31)^(D102-1)) -> 1989.1875 | J102: =IF(C102>$C$10,0,$C$23*(1+$C$32)^(D102-1)) -> 3315.3125 | K102: =IF(C102>$C$10,0,$C$25*(1+$C$33)^(D102-1)) -> 650.25 | L102: =IF(C102>$C$10,0,$C$26*(1+$C$34)^(D102-1)) -> 325.125 | M102: =H102+I102+J102+K102+L102 -> 10258.25 | N102: =F102+M102 -> 17684.55 | O102: =IF($C$7=0,0,N102/$C$7) -> 1.17897 | P102: =MAX(SUM(N102:N198)+S102,0) -> 2170908.2 | Q102: =SUM(F102:F198) -> 1097764.2 | R102: =SUM(M102:M198) -> 1073144 | S102: =SUMPRODUCT(($C$55:$C$67)*($D$55:$D$67>=$A102)) -> 0 | T102: =IF(C102>$C$10,0,IF(AND($C$38>0,A102>=$C$38,EOMONTH(A102,0)<=$C$39),E102*(1-$C$40)*(1-G$15),E102*(1-G$15)))+M102 -> 16941.92 | U102: =IF(C102>$C$10,0,IF(AND($C$38>0,A102>=$C$38,EOMONTH(A102,0)<=$C$39),E102*(1-$C$40)*(1-H$15),E102*(1-H$15)))+M102 -> 16199.29 | V102: =IF(C102>$C$10,0,IF(AND($C$38>0,A102>=$C$38,EOMONTH(A102,0)<=$C$39),E102*(1-$C$40)*(1-I$15),E102*(1-I$15)))+M102 -> 15456.66 | W102: =IF(C102>$C$10,0,IF(AND($C$38>0,A102>=$C$38,EOMONTH(A102,0)<=$C$39),E102*(1-$C$40)*(1-F$34),E102*(1-F$34)))+M102 -> 17684.55 | X102: =IF(C102>$C$10,0,IF(AND($C$38>0,A102>=$C$38,EOMONTH(A102,0)<=$C$39),E102*(1-$C$40)*(1-G$34),E102*(1-G$34)))+M102 -> 16199.29 | Y102: =IF(C102>$C$10,0,IF(AND($C$38>0,A102>=$C$38,EOMONTH(A102,0)<=$C$39),E102*(1-$C$40)*(1-H$34),E102*(1-H$34)))+M102 -> 15456.66 | Z102: =IF(C102>$C$10,0,IF(AND($C$38>0,A102>=$C$38,EOMONTH(A102,0)<=$C$39),E102*(1-$C$40)*(1-I$34),E102*(1-I$34)))+M102 -> 14714.03 | AA102: =IF(C102>$C$10,0,IF(AND($C$38>0,A102>=$C$38,EOMONTH(A102,0)<=$C$39),E102*(1-$C$40)*(1-J$34),E102*(1-J$34)))+M102 -> 13971.4
A103: =EDATE($C$8,28) -> 44205 | B103: =EDATE($C$8,29)-1 -> 44235 | C103: =ROW()-ROW($C$74) -> 29 | D103: =INT((C103-1)/12)+1 -> 3 | E103: =IF(C103>$C$10,0,$C$21*(1+$C$29)^(D103-1)) -> 10609 | F103: =IF(C103>$C$10,0,IF(AND($C$38>0,A103>=$C$38,EOMONTH(A103,0)<=$C$39),E103*(1-$C$40),E103)) -> 7426.3 | G103: =IF(C103>$C$10,0,IF(AND($C$38>0,A103>=$C$38,EOMONTH(A103,0)<=$C$39),-E103*$C$40,0)) -> -3182.7 | H103: =IF(C103>$C$10,0,$C$24*(1+$C$30)^(D103-1)) -> 3978.375 | I103: =IF(C103>$C$10,0,$C$22*(1+$C$31)^(D103-1)) -> 1989.1875 | J103: =IF(C103>$C$10,0,$C$23*(1+$C$32)^(D103-1)) -> 3315.3125 | K103: =IF(C103>$C$10,0,$C$25*(1+$C$33)^(D103-1)) -> 650.25 | L103: =IF(C103>$C$10,0,$C$26*(1+$C$34)^(D103-1)) -> 325.125 | M103: =H103+I103+J103+K103+L103 -> 10258.25 | N103: =F103+M103 -> 17684.55 | O103: =IF($C$7=0,0,N103/$C$7) -> 1.17897 | P103: =MAX(SUM(N103:N198)+S103,0) -> 2153223.6 | Q103: =SUM(F103:F198) -> 1090337.9 | R103: =SUM(M103:M198) -> 1062885.8 | S103: =SUMPRODUCT(($C$55:$C$67)*($D$55:$D$67>=$A103)) -> 0 | T103: =IF(C103>$C$10,0,IF(AND($C$38>0,A103>=$C$38,EOMONTH(A103,0)<=$C$39),E103*(1-$C$40)*(1-G$15),E103*(1-G$15)))+M103 -> 16941.92 | U103: =IF(C103>$C$10,0,IF(AND($C$38>0,A103>=$C$38,EOMONTH(A103,0)<=$C$39),E103*(1-$C$40)*(1-H$15),E103*(1-H$15)))+M103 -> 16199.29 | V103: =IF(C103>$C$10,0,IF(AND($C$38>0,A103>=$C$38,EOMONTH(A103,0)<=$C$39),E103*(1-$C$40)*(1-I$15),E103*(1-I$15)))+M103 -> 15456.66 | W103: =IF(C103>$C$10,0,IF(AND($C$38>0,A103>=$C$38,EOMONTH(A103,0)<=$C$39),E103*(1-$C$40)*(1-F$34),E103*(1-F$34)))+M103 -> 17684.55 | X103: =IF(C103>$C$10,0,IF(AND($C$38>0,A103>=$C$38,EOMONTH(A103,0)<=$C$39),E103*(1-$C$40)*(1-G$34),E103*(1-G$34)))+M103 -> 16199.29 | Y103: =IF(C103>$C$10,0,IF(AND($C$38>0,A103>=$C$38,EOMONTH(A103,0)<=$C$39),E103*(1-$C$40)*(1-H$34),E103*(1-H$34)))+M103 -> 15456.66 | Z103: =IF(C103>$C$10,0,IF(AND($C$38>0,A103>=$C$38,EOMONTH(A103,0)<=$C$39),E103*(1-$C$40)*(1-I$34),E103*(1-I$34)))+M103 -> 14714.03 | AA103: =IF(C103>$C$10,0,IF(AND($C$38>0,A103>=$C$38,EOMONTH(A103,0)<=$C$39),E103*(1-$C$40)*(1-J$34),E103*(1-J$34)))+M103 -> 13971.4
A104: =EDATE($C$8,29) -> 44236 | B104: =EDATE($C$8,30)-1 -> 44263 | C104: =ROW()-ROW($C$74) -> 30 | D104: =INT((C104-1)/12)+1 -> 3 | E104: =IF(C104>$C$10,0,$C$21*(1+$C$29)^(D104-1)) -> 10609 | F104: =IF(C104>$C$10,0,IF(AND($C$38>0,A104>=$C$38,EOMONTH(A104,0)<=$C$39),E104*(1-$C$40),E104)) -> 7426.3 | G104: =IF(C104>$C$10,0,IF(AND($C$38>0,A104>=$C$38,EOMONTH(A104,0)<=$C$39),-E104*$C$40,0)) -> -3182.7 | H104: =IF(C104>$C$10,0,$C$24*(1+$C$30)^(D104-1)) -> 3978.375 | I104: =IF(C104>$C$10,0,$C$22*(1+$C$31)^(D104-1)) -> 1989.1875 | J104: =IF(C104>$C$10,0,$C$23*(1+$C$32)^(D104-1)) -> 3315.3125 | K104: =IF(C104>$C$10,0,$C$25*(1+$C$33)^(D104-1)) -> 650.25 | L104: =IF(C104>$C$10,0,$C$26*(1+$C$34)^(D104-1)) -> 325.125 | M104: =H104+I104+J104+K104+L104 -> 10258.25 | N104: =F104+M104 -> 17684.55 | O104: =IF($C$7=0,0,N104/$C$7) -> 1.17897 | P104: =MAX(SUM(N104:N198)+S104,0) -> 2135539.1 | Q104: =SUM(F104:F198) -> 1082911.6 | R104: =SUM(M104:M198) -> 1052627.5 | S104: =SUMPRODUCT(($C$55:$C$67)*($D$55:$D$67>=$A104)) -> 0 | T104: =IF(C104>$C$10,0,IF(AND($C$38>0,A104>=$C$38,EOMONTH(A104,0)<=$C$39),E104*(1-$C$40)*(1-G$15),E104*(1-G$15)))+M104 -> 16941.92 | U104: =IF(C104>$C$10,0,IF(AND($C$38>0,A104>=$C$38,EOMONTH(A104,0)<=$C$39),E104*(1-$C$40)*(1-H$15),E104*(1-H$15)))+M104 -> 16199.29 | V104: =IF(C104>$C$10,0,IF(AND($C$38>0,A104>=$C$38,EOMONTH(A104,0)<=$C$39),E104*(1-$C$40)*(1-I$15),E104*(1-I$15)))+M104 -> 15456.66 | W104: =IF(C104>$C$10,0,IF(AND($C$38>0,A104>=$C$38,EOMONTH(A104,0)<=$C$39),E104*(1-$C$40)*(1-F$34),E104*(1-F$34)))+M104 -> 17684.55 | X104: =IF(C104>$C$10,0,IF(AND($C$38>0,A104>=$C$38,EOMONTH(A104,0)<=$C$39),E104*(1-$C$40)*(1-G$34),E104*(1-G$34)))+M104 -> 16199.29 | Y104: =IF(C104>$C$10,0,IF(AND($C$38>0,A104>=$C$38,EOMONTH(A104,0)<=$C$39),E104*(1-$C$40)*(1-H$34),E104*(1-H$34)))+M104 -> 15456.66 | Z104: =IF(C104>$C$10,0,IF(AND($C$38>0,A104>=$C$38,EOMONTH(A104,0)<=$C$39),E104*(1-$C$40)*(1-I$34),E104*(1-I$34)))+M104 -> 14714.03 | AA104: =IF(C104>$C$10,0,IF(AND($C$38>0,A104>=$C$38,EOMONTH(A104,0)<=$C$39),E104*(1-$C$40)*(1-J$34),E104*(1-J$34)))+M104 -> 13971.4
A105: =EDATE($C$8,30) -> 44264 | B105: =EDATE($C$8,31)-1 -> 44294 | C105: =ROW()-ROW($C$74) -> 31 | D105: =INT((C105-1)/12)+1 -> 3 | E105: =IF(C105>$C$10,0,$C$21*(1+$C$29)^(D105-1)) -> 10609 | F105: =IF(C105>$C$10,0,IF(AND($C$38>0,A105>=$C$38,EOMONTH(A105,0)<=$C$39),E105*(1-$C$40),E105)) -> 7426.3 | G105: =IF(C105>$C$10,0,IF(AND($C$38>0,A105>=$C$38,EOMONTH(A105,0)<=$C$39),-E105*$C$40,0)) -> -3182.7 | H105: =IF(C105>$C$10,0,$C$24*(1+$C$30)^(D105-1)) -> 3978.375 | I105: =IF(C105>$C$10,0,$C$22*(1+$C$31)^(D105-1)) -> 1989.1875 | J105: =IF(C105>$C$10,0,$C$23*(1+$C$32)^(D105-1)) -> 3315.3125 | K105: =IF(C105>$C$10,0,$C$25*(1+$C$33)^(D105-1)) -> 650.25 | L105: =IF(C105>$C$10,0,$C$26*(1+$C$34)^(D105-1)) -> 325.125 | M105: =H105+I105+J105+K105+L105 -> 10258.25 | N105: =F105+M105 -> 17684.55 | O105: =IF($C$7=0,0,N105/$C$7) -> 1.17897 | P105: =MAX(SUM(N105:N198)+S105,0) -> 2117854.5 | Q105: =SUM(F105:F198) -> 1075485.3 | R105: =SUM(M105:M198) -> 1042369.3 | S105: =SUMPRODUCT(($C$55:$C$67)*($D$55:$D$67>=$A105)) -> 0 | T105: =IF(C105>$C$10,0,IF(AND($C$38>0,A105>=$C$38,EOMONTH(A105,0)<=$C$39),E105*(1-$C$40)*(1-G$15),E105*(1-G$15)))+M105 -> 16941.92 | U105: =IF(C105>$C$10,0,IF(AND($C$38>0,A105>=$C$38,EOMONTH(A105,0)<=$C$39),E105*(1-$C$40)*(1-H$15),E105*(1-H$15)))+M105 -> 16199.29 | V105: =IF(C105>$C$10,0,IF(AND($C$38>0,A105>=$C$38,EOMONTH(A105,0)<=$C$39),E105*(1-$C$40)*(1-I$15),E105*(1-I$15)))+M105 -> 15456.66 | W105: =IF(C105>$C$10,0,IF(AND($C$38>0,A105>=$C$38,EOMONTH(A105,0)<=$C$39),E105*(1-$C$40)*(1-F$34),E105*(1-F$34)))+M105 -> 17684.55 | X105: =IF(C105>$C$10,0,IF(AND($C$38>0,A105>=$C$38,EOMONTH(A105,0)<=$C$39),E105*(1-$C$40)*(1-G$34),E105*(1-G$34)))+M105 -> 16199.29 | Y105: =IF(C105>$C$10,0,IF(AND($C$38>0,A105>=$C$38,EOMONTH(A105,0)<=$C$39),E105*(1-$C$40)*(1-H$34),E105*(1-H$34)))+M105 -> 15456.66 | Z105: =IF(C105>$C$10,0,IF(AND($C$38>0,A105>=$C$38,EOMONTH(A105,0)<=$C$39),E105*(1-$C$40)*(1-I$34),E105*(1-I$34)))+M105 -> 14714.03 | AA105: =IF(C105>$C$10,0,IF(AND($C$38>0,A105>=$C$38,EOMONTH(A105,0)<=$C$39),E105*(1-$C$40)*(1-J$34),E105*(1-J$34)))+M105 -> 13971.4
A106: =EDATE($C$8,31) -> 44295 | B106: =EDATE($C$8,32)-1 -> 44324 | C106: =ROW()-ROW($C$74) -> 32 | D106: =INT((C106-1)/12)+1 -> 3 | E106: =IF(C106>$C$10,0,$C$21*(1+$C$29)^(D106-1)) -> 10609 | F106: =IF(C106>$C$10,0,IF(AND($C$38>0,A106>=$C$38,EOMONTH(A106,0)<=$C$39),E106*(1-$C$40),E106)) -> 7426.3 | G106: =IF(C106>$C$10,0,IF(AND($C$38>0,A106>=$C$38,EOMONTH(A106,0)<=$C$39),-E106*$C$40,0)) -> -3182.7 | H106: =IF(C106>$C$10,0,$C$24*(1+$C$30)^(D106-1)) -> 3978.375 | I106: =IF(C106>$C$10,0,$C$22*(1+$C$31)^(D106-1)) -> 1989.1875 | J106: =IF(C106>$C$10,0,$C$23*(1+$C$32)^(D106-1)) -> 3315.3125 | K106: =IF(C106>$C$10,0,$C$25*(1+$C$33)^(D106-1)) -> 650.25 | L106: =IF(C106>$C$10,0,$C$26*(1+$C$34)^(D106-1)) -> 325.125 | M106: =H106+I106+J106+K106+L106 -> 10258.25 | N106: =F106+M106 -> 17684.55 | O106: =IF($C$7=0,0,N106/$C$7) -> 1.17897 | P106: =MAX(SUM(N106:N198)+S106,0) -> 2100170 | Q106: =SUM(F106:F198) -> 1068059 | R106: =SUM(M106:M198) -> 1032111 | S106: =SUMPRODUCT(($C$55:$C$67)*($D$55:$D$67>=$A106)) -> 0 | T106: =IF(C106>$C$10,0,IF(AND($C$38>0,A106>=$C$38,EOMONTH(A106,0)<=$C$39),E106*(1-$C$40)*(1-G$15),E106*(1-G$15)))+M106 -> 16941.92 | U106: =IF(C106>$C$10,0,IF(AND($C$38>0,A106>=$C$38,EOMONTH(A106,0)<=$C$39),E106*(1-$C$40)*(1-H$15),E106*(1-H$15)))+M106 -> 16199.29 | V106: =IF(C106>$C$10,0,IF(AND($C$38>0,A106>=$C$38,EOMONTH(A106,0)<=$C$39),E106*(1-$C$40)*(1-I$15),E106*(1-I$15)))+M106 -> 15456.66 | W106: =IF(C106>$C$10,0,IF(AND($C$38>0,A106>=$C$38,EOMONTH(A106,0)<=$C$39),E106*(1-$C$40)*(1-F$34),E106*(1-F$34)))+M106 -> 17684.55 | X106: =IF(C106>$C$10,0,IF(AND($C$38>0,A106>=$C$38,EOMONTH(A106,0)<=$C$39),E106*(1-$C$40)*(1-G$34),E106*(1-G$34)))+M106 -> 16199.29 | Y106: =IF(C106>$C$10,0,IF(AND($C$38>0,A106>=$C$38,EOMONTH(A106,0)<=$C$39),E106*(1-$C$40)*(1-H$34),E106*(1-H$34)))+M106 -> 15456.66 | Z106: =IF(C106>$C$10,0,IF(AND($C$38>0,A106>=$C$38,EOMONTH(A106,0)<=$C$39),E106*(1-$C$40)*(1-I$34),E106*(1-I$34)))+M106 -> 14714.03 | AA106: =IF(C106>$C$10,0,IF(AND($C$38>0,A106>=$C$38,EOMONTH(A106,0)<=$C$39),E106*(1-$C$40)*(1-J$34),E106*(1-J$34)))+M106 -> 13971.4
A107: =EDATE($C$8,32) -> 44325 | B107: =EDATE($C$8,33)-1 -> 44355 | C107: =ROW()-ROW($C$74) -> 33 | D107: =INT((C107-1)/12)+1 -> 3 | E107: =IF(C107>$C$10,0,$C$21*(1+$C$29)^(D107-1)) -> 10609 | F107: =IF(C107>$C$10,0,IF(AND($C$38>0,A107>=$C$38,EOMONTH(A107,0)<=$C$39),E107*(1-$C$40),E107)) -> 10609 | G107: =IF(C107>$C$10,0,IF(AND($C$38>0,A107>=$C$38,EOMONTH(A107,0)<=$C$39),-E107*$C$40,0)) -> 0 | H107: =IF(C107>$C$10,0,$C$24*(1+$C$30)^(D107-1)) -> 3978.375 | I107: =IF(C107>$C$10,0,$C$22*(1+$C$31)^(D107-1)) -> 1989.1875 | J107: =IF(C107>$C$10,0,$C$23*(1+$C$32)^(D107-1)) -> 3315.3125 | K107: =IF(C107>$C$10,0,$C$25*(1+$C$33)^(D107-1)) -> 650.25 | L107: =IF(C107>$C$10,0,$C$26*(1+$C$34)^(D107-1)) -> 325.125 | M107: =H107+I107+J107+K107+L107 -> 10258.25 | N107: =F107+M107 -> 20867.25 | O107: =IF($C$7=0,0,N107/$C$7) -> 1.39115 | P107: =MAX(SUM(N107:N198)+S107,0) -> 2082485.4 | Q107: =SUM(F107:F198) -> 1060632.7 | R107: =SUM(M107:M198) -> 1021852.8 | S107: =SUMPRODUCT(($C$55:$C$67)*($D$55:$D$67>=$A107)) -> 0 | T107: =IF(C107>$C$10,0,IF(AND($C$38>0,A107>=$C$38,EOMONTH(A107,0)<=$C$39),E107*(1-$C$40)*(1-G$15),E107*(1-G$15)))+M107 -> 19806.35 | U107: =IF(C107>$C$10,0,IF(AND($C$38>0,A107>=$C$38,EOMONTH(A107,0)<=$C$39),E107*(1-$C$40)*(1-H$15),E107*(1-H$15)))+M107 -> 18745.45 | V107: =IF(C107>$C$10,0,IF(AND($C$38>0,A107>=$C$38,EOMONTH(A107,0)<=$C$39),E107*(1-$C$40)*(1-I$15),E107*(1-I$15)))+M107 -> 17684.55 | W107: =IF(C107>$C$10,0,IF(AND($C$38>0,A107>=$C$38,EOMONTH(A107,0)<=$C$39),E107*(1-$C$40)*(1-F$34),E107*(1-F$34)))+M107 -> 20867.25 | X107: =IF(C107>$C$10,0,IF(AND($C$38>0,A107>=$C$38,EOMONTH(A107,0)<=$C$39),E107*(1-$C$40)*(1-G$34),E107*(1-G$34)))+M107 -> 18745.45 | Y107: =IF(C107>$C$10,0,IF(AND($C$38>0,A107>=$C$38,EOMONTH(A107,0)<=$C$39),E107*(1-$C$40)*(1-H$34),E107*(1-H$34)))+M107 -> 17684.55 | Z107: =IF(C107>$C$10,0,IF(AND($C$38>0,A107>=$C$38,EOMONTH(A107,0)<=$C$39),E107*(1-$C$40)*(1-I$34),E107*(1-I$34)))+M107 -> 16623.65 | AA107: =IF(C107>$C$10,0,IF(AND($C$38>0,A107>=$C$38,EOMONTH(A107,0)<=$C$39),E107*(1-$C$40)*(1-J$34),E107*(1-J$34)))+M107 -> 15562.75
A108: =EDATE($C$8,33) -> 44356 | B108: =EDATE($C$8,34)-1 -> 44385 | C108: =ROW()-ROW($C$74) -> 34 | D108: =INT((C108-1)/12)+1 -> 3 | E108: =IF(C108>$C$10,0,$C$21*(1+$C$29)^(D108-1)) -> 10609 | F108: =IF(C108>$C$10,0,IF(AND($C$38>0,A108>=$C$38,EOMONTH(A108,0)<=$C$39),E108*(1-$C$40),E108)) -> 10609 | G108: =IF(C108>$C$10,0,IF(AND($C$38>0,A108>=$C$38,EOMONTH(A108,0)<=$C$39),-E108*$C$40,0)) -> 0 | H108: =IF(C108>$C$10,0,$C$24*(1+$C$30)^(D108-1)) -> 3978.375 | I108: =IF(C108>$C$10,0,$C$22*(1+$C$31)^(D108-1)) -> 1989.1875 | J108: =IF(C108>$C$10,0,$C$23*(1+$C$32)^(D108-1)) -> 3315.3125 | K108: =IF(C108>$C$10,0,$C$25*(1+$C$33)^(D108-1)) -> 650.25 | L108: =IF(C108>$C$10,0,$C$26*(1+$C$34)^(D108-1)) -> 325.125 | M108: =H108+I108+J108+K108+L108 -> 10258.25 | N108: =F108+M108 -> 20867.25 | O108: =IF($C$7=0,0,N108/$C$7) -> 1.39115 | P108: =MAX(SUM(N108:N198)+S108,0) -> 2061618.2 | Q108: =SUM(F108:F198) -> 1050023.7 | R108: =SUM(M108:M198) -> 1011594.5 | S108: =SUMPRODUCT(($C$55:$C$67)*($D$55:$D$67>=$A108)) -> 0 | T108: =IF(C108>$C$10,0,IF(AND($C$38>0,A108>=$C$38,EOMONTH(A108,0)<=$C$39),E108*(1-$C$40)*(1-G$15),E108*(1-G$15)))+M108 -> 19806.35 | U108: =IF(C108>$C$10,0,IF(AND($C$38>0,A108>=$C$38,EOMONTH(A108,0)<=$C$39),E108*(1-$C$40)*(1-H$15),E108*(1-H$15)))+M108 -> 18745.45 | V108: =IF(C108>$C$10,0,IF(AND($C$38>0,A108>=$C$38,EOMONTH(A108,0)<=$C$39),E108*(1-$C$40)*(1-I$15),E108*(1-I$15)))+M108 -> 17684.55 | W108: =IF(C108>$C$10,0,IF(AND($C$38>0,A108>=$C$38,EOMONTH(A108,0)<=$C$39),E108*(1-$C$40)*(1-F$34),E108*(1-F$34)))+M108 -> 20867.25 | X108: =IF(C108>$C$10,0,IF(AND($C$38>0,A108>=$C$38,EOMONTH(A108,0)<=$C$39),E108*(1-$C$40)*(1-G$34),E108*(1-G$34)))+M108 -> 18745.45 | Y108: =IF(C108>$C$10,0,IF(AND($C$38>0,A108>=$C$38,EOMONTH(A108,0)<=$C$39),E108*(1-$C$40)*(1-H$34),E108*(1-H$34)))+M108 -> 17684.55 | Z108: =IF(C108>$C$10,0,IF(AND($C$38>0,A108>=$C$38,EOMONTH(A108,0)<=$C$39),E108*(1-$C$40)*(1-I$34),E108*(1-I$34)))+M108 -> 16623.65 | AA108: =IF(C108>$C$10,0,IF(AND($C$38>0,A108>=$C$38,EOMONTH(A108,0)<=$C$39),E108*(1-$C$40)*(1-J$34),E108*(1-J$34)))+M108 -> 15562.75
A109: =EDATE($C$8,34) -> 44386 | B109: =EDATE($C$8,35)-1 -> 44416 | C109: =ROW()-ROW($C$74) -> 35 | D109: =INT((C109-1)/12)+1 -> 3 | E109: =IF(C109>$C$10,0,$C$21*(1+$C$29)^(D109-1)) -> 10609 | F109: =IF(C109>$C$10,0,IF(AND($C$38>0,A109>=$C$38,EOMONTH(A109,0)<=$C$39),E109*(1-$C$40),E109)) -> 10609 | G109: =IF(C109>$C$10,0,IF(AND($C$38>0,A109>=$C$38,EOMONTH(A109,0)<=$C$39),-E109*$C$40,0)) -> 0 | H109: =IF(C109>$C$10,0,$C$24*(1+$C$30)^(D109-1)) -> 3978.375 | I109: =IF(C109>$C$10,0,$C$22*(1+$C$31)^(D109-1)) -> 1989.1875 | J109: =IF(C109>$C$10,0,$C$23*(1+$C$32)^(D109-1)) -> 3315.3125 | K109: =IF(C109>$C$10,0,$C$25*(1+$C$33)^(D109-1)) -> 650.25 | L109: =IF(C109>$C$10,0,$C$26*(1+$C$34)^(D109-1)) -> 325.125 | M109: =H109+I109+J109+K109+L109 -> 10258.25 | N109: =F109+M109 -> 20867.25 | O109: =IF($C$7=0,0,N109/$C$7) -> 1.39115 | P109: =MAX(SUM(N109:N198)+S109,0) -> 2040750.9 | Q109: =SUM(F109:F198) -> 1039414.7 | R109: =SUM(M109:M198) -> 1001336.3 | S109: =SUMPRODUCT(($C$55:$C$67)*($D$55:$D$67>=$A109)) -> 0 | T109: =IF(C109>$C$10,0,IF(AND($C$38>0,A109>=$C$38,EOMONTH(A109,0)<=$C$39),E109*(1-$C$40)*(1-G$15),E109*(1-G$15)))+M109 -> 19806.35 | U109: =IF(C109>$C$10,0,IF(AND($C$38>0,A109>=$C$38,EOMONTH(A109,0)<=$C$39),E109*(1-$C$40)*(1-H$15),E109*(1-H$15)))+M109 -> 18745.45 | V109: =IF(C109>$C$10,0,IF(AND($C$38>0,A109>=$C$38,EOMONTH(A109,0)<=$C$39),E109*(1-$C$40)*(1-I$15),E109*(1-I$15)))+M109 -> 17684.55 | W109: =IF(C109>$C$10,0,IF(AND($C$38>0,A109>=$C$38,EOMONTH(A109,0)<=$C$39),E109*(1-$C$40)*(1-F$34),E109*(1-F$34)))+M109 -> 20867.25 | X109: =IF(C109>$C$10,0,IF(AND($C$38>0,A109>=$C$38,EOMONTH(A109,0)<=$C$39),E109*(1-$C$40)*(1-G$34),E109*(1-G$34)))+M109 -> 18745.45 | Y109: =IF(C109>$C$10,0,IF(AND($C$38>0,A109>=$C$38,EOMONTH(A109,0)<=$C$39),E109*(1-$C$40)*(1-H$34),E109*(1-H$34)))+M109 -> 17684.55 | Z109: =IF(C109>$C$10,0,IF(AND($C$38>0,A109>=$C$38,EOMONTH(A109,0)<=$C$39),E109*(1-$C$40)*(1-I$34),E109*(1-I$34)))+M109 -> 16623.65 | AA109: =IF(C109>$C$10,0,IF(AND($C$38>0,A109>=$C$38,EOMONTH(A109,0)<=$C$39),E109*(1-$C$40)*(1-J$34),E109*(1-J$34)))+M109 -> 15562.75
...

Sheet Annual Summary
A1: Period Start | B1: Period End | C1: Lease Year | D1: Months | E1: Base Rent Applied | F1: Total NNN | G1: Total Monthly Obligation | H1: % of Grand Total
A2: 43160 | B2: 43524 | C2: 1 | D2: =COUNTIF('Lease Schedule (populated)'!$D$75:$D$198,1) -> 12 | E2: =SUMIF('Lease Schedule (populated)'!$D$75:$D$198,1,'Lease Schedule (populated)'!$F$75:$F$198) -> 120000 | F2: =SUMIF('Lease Schedule (populated)'!$D$75:$D$198,1,'Lease Schedule (populated)'!$M$75:$M$198) -> 116250 | G2: =SUMIF('Lease Schedule (populated)'!$D$75:$D$198,1,'Lease Schedule (populated)'!$N$75:$N$198) -> 236250 | H2: =IF(G13=0,0,G2/G13) -> 0.087790135
A3: 43525 | B3: 43890 | C3: 2 | D3: =COUNTIF('Lease Schedule (populated)'!$D$75:$D$198,2) -> 12 | E3: =SUMIF('Lease Schedule (populated)'!$D$75:$D$198,2,'Lease Schedule (populated)'!$F$75:$F$198) -> 111240 | F3: =SUMIF('Lease Schedule (populated)'!$D$75:$D$198,2,'Lease Schedule (populated)'!$M$75:$M$198) -> 119625 | G3: =SUMIF('Lease Schedule (populated)'!$D$75:$D$198,2,'Lease Schedule (populated)'!$N$75:$N$198) -> 230865 | H3: =IF(G13=0,0,G3/G13) -> 0.085789077
A4: 43891 | B4: 44255 | C4: 3 | D4: =COUNTIF('Lease Schedule (populated)'!$D$75:$D$198,3) -> 12 | E4: =SUMIF('Lease Schedule (populated)'!$D$75:$D$198,3,'Lease Schedule (populated)'!$F$75:$F$198) -> 101846.4 | F4: =SUMIF('Lease Schedule (populated)'!$D$75:$D$198,3,'Lease Schedule (populated)'!$M$75:$M$198) -> 123099 | G4: =SUMIF('Lease Schedule (populated)'!$D$75:$D$198,3,'Lease Schedule (populated)'!$N$75:$N$198) -> 224945.4 | H4: =IF(G13=0,0,G4/G13) -> 0.083589363
A5: 44256 | B5: 44620 | C5: 4 | D5: =COUNTIF('Lease Schedule (populated)'!$D$75:$D$198,4) -> 12 | E5: =SUMIF('Lease Schedule (populated)'!$D$75:$D$198,4,'Lease Schedule (populated)'!$F$75:$F$198) -> 131127.24 | F5: =SUMIF('Lease Schedule (populated)'!$D$75:$D$198,4,'Lease Schedule (populated)'!$M$75:$M$198) -> 126674.92 | G5: =SUMIF('Lease Schedule (populated)'!$D$75:$D$198,4,'Lease Schedule (populated)'!$N$75:$N$198) -> 257802.16 | H5: =IF(G13=0,0,G5/G13) -> 0.095798886
A6: 44621 | B6: 44985 | C6: 5 | D6: =COUNTIF('Lease Schedule (populated)'!$D$75:$D$198,5) -> 12 | E6: =SUMIF('Lease Schedule (populated)'!$D$75:$D$198,5,'Lease Schedule (populated)'!$F$75:$F$198) -> 135061.06 | F6: =SUMIF('Lease Schedule (populated)'!$D$75:$D$198,5,'Lease Schedule (populated)'!$M$75:$M$198) -> 130355.79 | G6: =SUMIF('Lease Schedule (populated)'!$D$75:$D$198,5,'Lease Schedule (populated)'!$N$75:$N$198) -> 265416.84 | H6: =IF(G13=0,0,G6/G13) -> 0.098628489
A7: 44986 | B7: 45351 | C7: 6 | D7: =COUNTIF('Lease Schedule (populated)'!$D$75:$D$198,6) -> 12 | E7: =SUMIF('Lease Schedule (populated)'!$D$75:$D$198,6,'Lease Schedule (populated)'!$F$75:$F$198) -> 139112.89 | F7: =SUMIF('Lease Schedule (populated)'!$D$75:$D$198,6,'Lease Schedule (populated)'!$M$75:$M$198) -> 134144.69 | G7: =SUMIF('Lease Schedule (populated)'!$D$75:$D$198,6,'Lease Schedule (populated)'!$N$75:$N$198) -> 273257.58 | H7: =IF(G13=0,0,G7/G13) -> 0.10154209
A8: 45352 | B8: 45716 | C8: 7 | D8: =COUNTIF('Lease Schedule (populated)'!$D$75:$D$198,7) -> 12 | E8: =SUMIF('Lease Schedule (populated)'!$D$75:$D$198,7,'Lease Schedule (populated)'!$F$75:$F$198) -> 143286.28 | F8: =SUMIF('Lease Schedule (populated)'!$D$75:$D$198,7,'Lease Schedule (populated)'!$M$75:$M$198) -> 138044.82 | G8: =SUMIF('Lease Schedule (populated)'!$D$75:$D$198,7,'Lease Schedule (populated)'!$N$75:$N$198) -> 281331.09 | H8: =IF(G13=0,0,G8/G13) -> 0.1045422
A9: 45717 | B9: 46081 | C9: 8 | D9: =COUNTIF('Lease Schedule (populated)'!$D$75:$D$198,8) -> 12 | E9: =SUMIF('Lease Schedule (populated)'!$D$75:$D$198,8,'Lease Schedule (populated)'!$F$75:$F$198) -> 147584.86 | F9: =SUMIF('Lease Schedule (populated)'!$D$75:$D$198,8,'Lease Schedule (populated)'!$M$75:$M$198) -> 142059.47 | G9: =SUMIF('Lease Schedule (populated)'!$D$75:$D$198,8,'Lease Schedule (populated)'!$N$75:$N$198) -> 289644.33 | H9: =IF(G13=0,0,G9/G13) -> 0.10763139
A10: 46082 | B10: 46446 | C10: 9 | D10: =COUNTIF('Lease Schedule (populated)'!$D$75:$D$198,9) -> 12 | E10: =SUMIF('Lease Schedule (populated)'!$D$75:$D$198,9,'Lease Schedule (populated)'!$F$75:$F$198) -> 152012.41 | F10: =SUMIF('Lease Schedule (populated)'!$D$75:$D$198,9,'Lease Schedule (populated)'!$M$75:$M$198) -> 146192.03 | G10: =SUMIF('Lease Schedule (populated)'!$D$75:$D$198,9,'Lease Schedule (populated)'!$N$75:$N$198) -> 298204.44 | H10: =IF(G13=0,0,G10/G13) -> 0.11081231
A11: 46447 | B11: 46812 | C11: 10 | D11: =COUNTIF('Lease Schedule (populated)'!$D$75:$D$198,10) -> 12 | E11: =SUMIF('Lease Schedule (populated)'!$D$75:$D$198,10,'Lease Schedule (populated)'!$F$75:$F$198) -> 156572.78 | F11: =SUMIF('Lease Schedule (populated)'!$D$75:$D$198,10,'Lease Schedule (populated)'!$M$75:$M$198) -> 150445.98 | G11: =SUMIF('Lease Schedule (populated)'!$D$75:$D$198,10,'Lease Schedule (populated)'!$N$75:$N$198) -> 307018.76 | H11: =IF(G13=0,0,G11/G13) -> 0.1140877
A12: 46813 | B12: 46934 | C12: 11 (Stub) | D12: =COUNTIF('Lease Schedule (populated)'!$D$75:$D$198,11) -> 4 | E12: =SUMIF('Lease Schedule (populated)'!$D$75:$D$198,11,'Lease Schedule (populated)'!$F$75:$F$198) -> 13439.164 | F12: =SUMIF('Lease Schedule (populated)'!$D$75:$D$198,11,'Lease Schedule (populated)'!$M$75:$M$198) -> 12902.076 | G12: =SUMIF('Lease Schedule (populated)'!$D$75:$D$198,11,'Lease Schedule (populated)'!$N$75:$N$198) -> 26341.239 | H12: =IF(G13=0,0,G12/G13) -> 0.0097883639
A13: GRAND TOTAL | D13: =SUM(D2:D12) -> 124 | E13: =SUM(E2:E12) -> 1351283.1 | F13: =SUM(F2:F12) -> 1339793.8 | G13: =SUM(G2:G12) -> 2691076.8 | H13: =SUM(H2:H12) -> 1

Sheet Audit Trail
A1: Period Start | B1: Month # | C1: Period Factor | D1: Proration Factor | E1: Proration Basis | F1: CAMS Esc Year | G1: CAMS Active | H1: Ins Esc Year | I1: Ins Active | J1: Tax Esc Year | K1: Tax Active | L1: Sec Esc Year | M1: Sec Active | N1: Other Esc Year | O1: Other Active
A2: 43160 | B2: 1 | C2: 1 | D2: 0 | E2: full | F2: 0 | G2: true | H2: 0 | I2: true | J2: 0 | K2: true | L2: 0 | M2: true | N2: 0 | O2: true
A3: 43191 | B3: 2 | C3: 1 | D3: 0 | E3: full | F3: 0 | G3: true | H3: 0 | I3: true | J3: 0 | K3: true | L3: 0 | M3: true | N3: 0 | O3: true
A4: 43221 | B4: 3 | C4: 1 | D4: 0 | E4: full | F4: 0 | G4: true | H4: 0 | I4: true | J4: 0 | K4: true | L4: 0 | M4: true | N4: 0 | O4: true
A5: 43252 | B5: 4 | C5: 1 | D5: 0 | E5: full | F5: 0 | G5: true | H5: 0 | I5: true | J5: 0 | K5: true | L5: 0 | M5: true | N5: 0 | O5: true
A6: 43282 | B6: 5 | C6: 1 | D6: 1 | E6: full | F6: 0 | G6: true | H6: 0 | I6: true | J6: 0 | K6: true | L6: 0 | M6: true | N6: 0 | O6: true
A7: 43313 | B7: 6 | C7: 1 | D7: 1 | E7: full | F7: 0 | G7: true | H7: 0 | I7: true | J7: 0 | K7: true | L7: 0 | M7: true | N7: 0 | O7: true
A8: 43344 | B8: 7 | C8: 1 | D8: 1 | E8: full | F8: 0 | G8: true | H8: 0 | I8: true | J8: 0 | K8: true | L8: 0 | M8: true | N8: 0 | O8: true
A9: 43374 | B9: 8 | C9: 1 | D9: 1 | E9: full | F9: 0 | G9: true | H9: 0 | I9: true | J9: 0 | K9: true | L9: 0 | M9: true | N9: 0 | O9: true
A10: 43405 | B10: 9 | C10: 1 | D10: 1 | E10: full | F10: 0 | G10: true | H10: 0 | I10: true | J10: 0 | K10: true | L10: 0 | M10: true | N10: 0 | O10: true
A11: 43435 | B11: 10 | C11: 1 | D11: 1 | E11: full | F11: 0 | G11: true | H11: 0 | I11: true | J11: 0 | K11: true | L11: 0 | M11: true | N11: 0 | O11: true
A12: 43466 | B12: 11 | C12: 1 | D12: 1 | E12: full | F12: 0 | G12: true | H12: 0 | I12: true | J12: 0 | K12: true | L12: 0 | M12: true | N12: 0 | O12: true
A13: 43497 | B13: 12 | C13: 1 | D13: 1 | E13: full | F13: 0 | G13: true | H13: 0 | I13: true | J13: 0 | K13: true | L13: 0 | M13: true | N13: 0 | O13: true
... A125: 46905 | B125: 124 | C125: 1 | D125: 1 | E125: full | F125: 8 | G125: true | H125: 8 | I125: true | J125: 9 | K125: true | L125: 0 | M125: true | N125: 0 | O125: true
